.Xil/Vivado-4596-DESKTOP-89OFCK6/realtime/xfft_1_stub.v
// Copyright 1986-2022 Xilinx, Inc. All Rights Reserved.
// Copyright 2022-2023 Advanced Micro Devices, Inc. All Rights Reserved.

// This empty module with port declaration file causes synthesis tools to infer a black box for IP.
// Please paste the declaration into a Verilog source file or add the file as an additional source.
(* x_core_info = "xfft_v9_1_9,Vivado 2023.1" *)
module xfft_1(aclk, s_axis_config_tdata, 
  s_axis_config_tvalid, s_axis_config_tready, s_axis_data_tdata, s_axis_data_tvalid, 
  s_axis_data_tready, s_axis_data_tlast, m_axis_data_tdata, m_axis_data_tvalid, 
  m_axis_data_tready, m_axis_data_tlast, event_frame_started, event_tlast_unexpected, 
  event_tlast_missing, event_status_channel_halt, event_data_in_channel_halt, 
  event_data_out_channel_halt);
  input aclk /* synthesis syn_isclock = 1 */;
  input [15:0]s_axis_config_tdata;
  input s_axis_config_tvalid;
  output s_axis_config_tready;
  input [31:0]s_axis_data_tdata;
  input s_axis_data_tvalid;
  output s_axis_data_tready;
  input s_axis_data_tlast;
  output [31:0]m_axis_data_tdata;
  output m_axis_data_tvalid;
  input m_axis_data_tready;
  output m_axis_data_tlast;
  output event_frame_started;
  output event_tlast_unexpected;
  output event_tlast_missing;
  output event_status_channel_halt;
  output event_data_in_channel_halt;
  output event_data_out_channel_halt;
endmodule

sim/fft_tb.sv
`timescale 1ns / 1ps
`default_nettype none

module fft_tb();

  logic clk_in;
  logic rst_in;

  logic fft_valid;
  logic [7:0] audio_data;
  logic [31:0] fft_data;
  logic fft_last;
  logic fft_ready;
  logic [31:0] fft_out_data;
  logic fft_out_last;
  logic fft_out_valid;
  logic fft_out_ready;


  xfft_1 fft(
    .aclk(clk_in),
    .s_axis_data_tvalid(fft_valid), .s_axis_data_tdata(fft_data),
    .s_axis_data_tlast(fft_last), .s_axis_data_tready(fft_ready), 
    .s_axis_config_tdata(0), .s_axis_config_tvalid(0), .s_axis_config_tready(),
    .m_axis_data_tdata(fft_out_data), .m_axis_data_tvalid(fft_out_valid),
    .m_axis_data_tlast(fft_out_last), .m_axis_data_tready(fft_out_ready),
    .event_frame_started(), .event_tlast_unexpected(), .event_tlast_missing(),
    .event_data_in_channel_halt(), .event_data_out_channel_halt());

  always begin // 100 MHz clock
      #5; 
      clk_in = !clk_in;
  end

  initial begin
    $dumpfile("fft_tb.vcd"); 
    $dumpvars(0,fft_tb);
    $display("Starting Sim");
    rst_in = 0;
    #10;
    rst_in = 1;
    fft_valid = 0;
    fft_data = 0;
    fft_last = 0;
    fft_ready = 0;
    fft_out_data = 0;
    fft_out_last = 0;
    fft_out_valid = 0;
    fft_out_ready = 0;
    audio_data = 0;
    #10;

    rst_in = 0;
    fft_valid = 1;
    fft_last = 1;

    for (int i = 0; i<10000; i=i+1)begin
      audio_data = i;
      #10;
    end

    $display("Simulation finished");
    $finish;
  end
endmodule
`default_nettype wire

dump.vcd
$date
   Mon Dec 11 15:24:31 2023
$end
$version
  2023.1
$end
$timescale
  1ps
$end
$scope module fft_tb $end
$var reg 1 ! clk_in $end
$var reg 1 " rst_in $end
$var reg 1 # fft_valid $end
$var reg 8 $ audio_data [7:0] $end
$var reg 32 % fft_data [31:0] $end
$var reg 1 & fft_last $end
$var reg 1 ' fft_ready $end
$var reg 32 ( fft_out_data [31:0] $end
$var reg 1 ) fft_out_last $end
$var reg 1 * fft_out_valid $end
$var reg 1 + fft_out_ready $end
$scope module fft $end
$var wire 1 , aclk $end
$var wire 16 - s_axis_config_tdata $end
$var wire 1 . s_axis_config_tvalid $end
$var wire 1 / s_axis_config_tready $end
$var wire 32 0 s_axis_data_tdata $end
$var wire 1 1 s_axis_data_tvalid $end
$var wire 1 2 s_axis_data_tready $end
$var wire 1 3 s_axis_data_tlast $end
$var wire 32 4 m_axis_data_tdata $end
$var wire 1 5 m_axis_data_tvalid $end
$var wire 1 6 m_axis_data_tready $end
$var wire 1 7 m_axis_data_tlast $end
$var wire 1 8 event_frame_started $end
$var wire 1 9 event_tlast_unexpected $end
$var wire 1 : event_tlast_missing $end
$var wire 1 ; event_status_channel_halt $end
$var wire 1 < event_data_in_channel_halt $end
$var wire 1 = event_data_out_channel_halt $end
$upscope $end
$scope begin Block57_2 $end
$var reg 32 > i [31:0] $end
$upscope $end
$upscope $end
$enddefinitions $end
#0
$dumpvars
x!
0"
x#
bx $
bx %
x&
0'
b0 (
0)
0*
x+
x,
b0 -
0.
0/
bx 0
x1
02
x3
b0 4
05
x6
07
08
09
0:
0;
0<
0=
b0 >
$end
#10000
1"
0#
b0 $
b0 %
0&
0+
b0 0
06
#20000
0"
1#
1&
11
13
#30000
b1 $
b1 >
#40000
b10 $
b10 >
#50000
b11 $
b11 >
#60000
b100 $
b100 >
#70000
b101 $
b101 >
#80000
b110 $
b110 >
#90000
b111 $
b111 >
#100000
b1000 $
b1000 >
#110000
b1001 $
b1001 >
#120000
b1010 $
b1010 >
#130000
b1011 $
b1011 >
#140000
b1100 $
b1100 >
#150000
b1101 $
b1101 >
#160000
b1110 $
b1110 >
#170000
b1111 $
b1111 >
#180000
b10000 $
b10000 >
#190000
b10001 $
b10001 >
#200000
b10010 $
b10010 >
#210000
b10011 $
b10011 >
#220000
b10100 $
b10100 >
#230000
b10101 $
b10101 >
#240000
b10110 $
b10110 >
#250000
b10111 $
b10111 >
#260000
b11000 $
b11000 >
#270000
b11001 $
b11001 >
#280000
b11010 $
b11010 >
#290000
b11011 $
b11011 >
#300000
b11100 $
b11100 >
#310000
b11101 $
b11101 >
#320000
b11110 $
b11110 >
#330000
b11111 $
b11111 >
#340000
b100000 $
b100000 >
#350000
b100001 $
b100001 >
#360000
b100010 $
b100010 >
#370000
b100011 $
b100011 >
#380000
b100100 $
b100100 >
#390000
b100101 $
b100101 >
#400000
b100110 $
b100110 >
#410000
b100111 $
b100111 >
#420000
b101000 $
b101000 >
#430000
b101001 $
b101001 >
#440000
b101010 $
b101010 >
#450000
b101011 $
b101011 >
#460000
b101100 $
b101100 >
#470000
b101101 $
b101101 >
#480000
b101110 $
b101110 >
#490000
b101111 $
b101111 >
#500000
b110000 $
b110000 >
#510000
b110001 $
b110001 >
#520000
b110010 $
b110010 >
#530000
b110011 $
b110011 >
#540000
b110100 $
b110100 >
#550000
b110101 $
b110101 >
#560000
b110110 $
b110110 >
#570000
b110111 $
b110111 >
#580000
b111000 $
b111000 >
#590000
b111001 $
b111001 >
#600000
b111010 $
b111010 >
#610000
b111011 $
b111011 >
#620000
b111100 $
b111100 >
#630000
b111101 $
b111101 >
#640000
b111110 $
b111110 >
#650000
b111111 $
b111111 >
#660000
b1000000 $
b1000000 >
#670000
b1000001 $
b1000001 >
#680000
b1000010 $
b1000010 >
#690000
b1000011 $
b1000011 >
#700000
b1000100 $
b1000100 >
#710000
b1000101 $
b1000101 >
#720000
b1000110 $
b1000110 >
#730000
b1000111 $
b1000111 >
#740000
b1001000 $
b1001000 >
#750000
b1001001 $
b1001001 >
#760000
b1001010 $
b1001010 >
#770000
b1001011 $
b1001011 >
#780000
b1001100 $
b1001100 >
#790000
b1001101 $
b1001101 >
#800000
b1001110 $
b1001110 >
#810000
b1001111 $
b1001111 >
#820000
b1010000 $
b1010000 >
#830000
b1010001 $
b1010001 >
#840000
b1010010 $
b1010010 >
#850000
b1010011 $
b1010011 >
#860000
b1010100 $
b1010100 >
#870000
b1010101 $
b1010101 >
#880000
b1010110 $
b1010110 >
#890000
b1010111 $
b1010111 >
#900000
b1011000 $
b1011000 >
#910000
b1011001 $
b1011001 >
#920000
b1011010 $
b1011010 >
#930000
b1011011 $
b1011011 >
#940000
b1011100 $
b1011100 >
#950000
b1011101 $
b1011101 >
#960000
b1011110 $
b1011110 >
#970000
b1011111 $
b1011111 >
#980000
b1100000 $
b1100000 >
#990000
b1100001 $
b1100001 >
#1000000
b1100010 $
b1100010 >
#1010000
b1100011 $
b1100011 >
#1020000
b1100100 $
b1100100 >
#1030000
b1100101 $
b1100101 >
#1040000
b1100110 $
b1100110 >
#1050000
b1100111 $
b1100111 >
#1060000
b1101000 $
b1101000 >
#1070000
b1101001 $
b1101001 >
#1080000
b1101010 $
b1101010 >
#1090000
b1101011 $
b1101011 >
#1100000
b1101100 $
b1101100 >
#1110000
b1101101 $
b1101101 >
#1120000
b1101110 $
b1101110 >
#1130000
b1101111 $
b1101111 >
#1140000
b1110000 $
b1110000 >
#1150000
b1110001 $
b1110001 >
#1160000
b1110010 $
b1110010 >
#1170000
b1110011 $
b1110011 >
#1180000
b1110100 $
b1110100 >
#1190000
b1110101 $
b1110101 >
#1200000
b1110110 $
b1110110 >
#1210000
b1110111 $
b1110111 >
#1220000
b1111000 $
b1111000 >
#1230000
b1111001 $
b1111001 >
#1240000
b1111010 $
b1111010 >
#1250000
b1111011 $
b1111011 >
#1260000
b1111100 $
b1111100 >
#1270000
b1111101 $
b1111101 >
#1280000
b1111110 $
b1111110 >
#1290000
b1111111 $
b1111111 >
#1300000
b10000000 $
b10000000 >
#1310000
b10000001 $
b10000001 >
#1320000
b10000010 $
b10000010 >
#1330000
b10000011 $
b10000011 >
#1340000
b10000100 $
b10000100 >
#1350000
b10000101 $
b10000101 >
#1360000
b10000110 $
b10000110 >
#1370000
b10000111 $
b10000111 >
#1380000
b10001000 $
b10001000 >
#1390000
b10001001 $
b10001001 >
#1400000
b10001010 $
b10001010 >
#1410000
b10001011 $
b10001011 >
#1420000
b10001100 $
b10001100 >
#1430000
b10001101 $
b10001101 >
#1440000
b10001110 $
b10001110 >
#1450000
b10001111 $
b10001111 >
#1460000
b10010000 $
b10010000 >
#1470000
b10010001 $
b10010001 >
#1480000
b10010010 $
b10010010 >
#1490000
b10010011 $
b10010011 >
#1500000
b10010100 $
b10010100 >
#1510000
b10010101 $
b10010101 >
#1520000
b10010110 $
b10010110 >
#1530000
b10010111 $
b10010111 >
#1540000
b10011000 $
b10011000 >
#1550000
b10011001 $
b10011001 >
#1560000
b10011010 $
b10011010 >
#1570000
b10011011 $
b10011011 >
#1580000
b10011100 $
b10011100 >
#1590000
b10011101 $
b10011101 >
#1600000
b10011110 $
b10011110 >
#1610000
b10011111 $
b10011111 >
#1620000
b10100000 $
b10100000 >
#1630000
b10100001 $
b10100001 >
#1640000
b10100010 $
b10100010 >
#1650000
b10100011 $
b10100011 >
#1660000
b10100100 $
b10100100 >
#1670000
b10100101 $
b10100101 >
#1680000
b10100110 $
b10100110 >
#1690000
b10100111 $
b10100111 >
#1700000
b10101000 $
b10101000 >
#1710000
b10101001 $
b10101001 >
#1720000
b10101010 $
b10101010 >
#1730000
b10101011 $
b10101011 >
#1740000
b10101100 $
b10101100 >
#1750000
b10101101 $
b10101101 >
#1760000
b10101110 $
b10101110 >
#1770000
b10101111 $
b10101111 >
#1780000
b10110000 $
b10110000 >
#1790000
b10110001 $
b10110001 >
#1800000
b10110010 $
b10110010 >
#1810000
b10110011 $
b10110011 >
#1820000
b10110100 $
b10110100 >
#1830000
b10110101 $
b10110101 >
#1840000
b10110110 $
b10110110 >
#1850000
b10110111 $
b10110111 >
#1860000
b10111000 $
b10111000 >
#1870000
b10111001 $
b10111001 >
#1880000
b10111010 $
b10111010 >
#1890000
b10111011 $
b10111011 >
#1900000
b10111100 $
b10111100 >
#1910000
b10111101 $
b10111101 >
#1920000
b10111110 $
b10111110 >
#1930000
b10111111 $
b10111111 >
#1940000
b11000000 $
b11000000 >
#1950000
b11000001 $
b11000001 >
#1960000
b11000010 $
b11000010 >
#1970000
b11000011 $
b11000011 >
#1980000
b11000100 $
b11000100 >
#1990000
b11000101 $
b11000101 >
#2000000
b11000110 $
b11000110 >
#2010000
b11000111 $
b11000111 >
#2020000
b11001000 $
b11001000 >
#2030000
b11001001 $
b11001001 >
#2040000
b11001010 $
b11001010 >
#2050000
b11001011 $
b11001011 >
#2060000
b11001100 $
b11001100 >
#2070000
b11001101 $
b11001101 >
#2080000
b11001110 $
b11001110 >
#2090000
b11001111 $
b11001111 >
#2100000
b11010000 $
b11010000 >
#2110000
b11010001 $
b11010001 >
#2120000
b11010010 $
b11010010 >
#2130000
b11010011 $
b11010011 >
#2140000
b11010100 $
b11010100 >
#2150000
b11010101 $
b11010101 >
#2160000
b11010110 $
b11010110 >
#2170000
b11010111 $
b11010111 >
#2180000
b11011000 $
b11011000 >
#2190000
b11011001 $
b11011001 >
#2200000
b11011010 $
b11011010 >
#2210000
b11011011 $
b11011011 >
#2220000
b11011100 $
b11011100 >
#2230000
b11011101 $
b11011101 >
#2240000
b11011110 $
b11011110 >
#2250000
b11011111 $
b11011111 >
#2260000
b11100000 $
b11100000 >
#2270000
b11100001 $
b11100001 >
#2280000
b11100010 $
b11100010 >
#2290000
b11100011 $
b11100011 >
#2300000
b11100100 $
b11100100 >
#2310000
b11100101 $
b11100101 >
#2320000
b11100110 $
b11100110 >
#2330000
b11100111 $
b11100111 >
#2340000
b11101000 $
b11101000 >
#2350000
b11101001 $
b11101001 >
#2360000
b11101010 $
b11101010 >
#2370000
b11101011 $
b11101011 >
#2380000
b11101100 $
b11101100 >
#2390000
b11101101 $
b11101101 >
#2400000
b11101110 $
b11101110 >
#2410000
b11101111 $
b11101111 >
#2420000
b11110000 $
b11110000 >
#2430000
b11110001 $
b11110001 >
#2440000
b11110010 $
b11110010 >
#2450000
b11110011 $
b11110011 >
#2460000
b11110100 $
b11110100 >
#2470000
b11110101 $
b11110101 >
#2480000
b11110110 $
b11110110 >
#2490000
b11110111 $
b11110111 >
#2500000
b11111000 $
b11111000 >
#2510000
b11111001 $
b11111001 >
#2520000
b11111010 $
b11111010 >
#2530000
b11111011 $
b11111011 >
#2540000
b11111100 $
b11111100 >
#2550000
b11111101 $
b11111101 >
#2560000
b11111110 $
b11111110 >
#2570000
b11111111 $
b11111111 >
#2580000
b0 $
b100000000 >
#2590000
b1 $
b100000001 >
#2600000
b10 $
b100000010 >
#2610000
b11 $
b100000011 >
#2620000
b100 $
b100000100 >
#2630000
b101 $
b100000101 >
#2640000
b110 $
b100000110 >
#2650000
b111 $
b100000111 >
#2660000
b1000 $
b100001000 >
#2670000
b1001 $
b100001001 >
#2680000
b1010 $
b100001010 >
#2690000
b1011 $
b100001011 >
#2700000
b1100 $
b100001100 >
#2710000
b1101 $
b100001101 >
#2720000
b1110 $
b100001110 >
#2730000
b1111 $
b100001111 >
#2740000
b10000 $
b100010000 >
#2750000
b10001 $
b100010001 >
#2760000
b10010 $
b100010010 >
#2770000
b10011 $
b100010011 >
#2780000
b10100 $
b100010100 >
#2790000
b10101 $
b100010101 >
#2800000
b10110 $
b100010110 >
#2810000
b10111 $
b100010111 >
#2820000
b11000 $
b100011000 >
#2830000
b11001 $
b100011001 >
#2840000
b11010 $
b100011010 >
#2850000
b11011 $
b100011011 >
#2860000
b11100 $
b100011100 >
#2870000
b11101 $
b100011101 >
#2880000
b11110 $
b100011110 >
#2890000
b11111 $
b100011111 >
#2900000
b100000 $
b100100000 >
#2910000
b100001 $
b100100001 >
#2920000
b100010 $
b100100010 >
#2930000
b100011 $
b100100011 >
#2940000
b100100 $
b100100100 >
#2950000
b100101 $
b100100101 >
#2960000
b100110 $
b100100110 >
#2970000
b100111 $
b100100111 >
#2980000
b101000 $
b100101000 >
#2990000
b101001 $
b100101001 >
#3000000
b101010 $
b100101010 >
#3010000
b101011 $
b100101011 >
#3020000
b101100 $
b100101100 >
#3030000
b101101 $
b100101101 >
#3040000
b101110 $
b100101110 >
#3050000
b101111 $
b100101111 >
#3060000
b110000 $
b100110000 >
#3070000
b110001 $
b100110001 >
#3080000
b110010 $
b100110010 >
#3090000
b110011 $
b100110011 >
#3100000
b110100 $
b100110100 >
#3110000
b110101 $
b100110101 >
#3120000
b110110 $
b100110110 >
#3130000
b110111 $
b100110111 >
#3140000
b111000 $
b100111000 >
#3150000
b111001 $
b100111001 >
#3160000
b111010 $
b100111010 >
#3170000
b111011 $
b100111011 >
#3180000
b111100 $
b100111100 >
#3190000
b111101 $
b100111101 >
#3200000
b111110 $
b100111110 >
#3210000
b111111 $
b100111111 >
#3220000
b1000000 $
b101000000 >
#3230000
b1000001 $
b101000001 >
#3240000
b1000010 $
b101000010 >
#3250000
b1000011 $
b101000011 >
#3260000
b1000100 $
b101000100 >
#3270000
b1000101 $
b101000101 >
#3280000
b1000110 $
b101000110 >
#3290000
b1000111 $
b101000111 >
#3300000
b1001000 $
b101001000 >
#3310000
b1001001 $
b101001001 >
#3320000
b1001010 $
b101001010 >
#3330000
b1001011 $
b101001011 >
#3340000
b1001100 $
b101001100 >
#3350000
b1001101 $
b101001101 >
#3360000
b1001110 $
b101001110 >
#3370000
b1001111 $
b101001111 >
#3380000
b1010000 $
b101010000 >
#3390000
b1010001 $
b101010001 >
#3400000
b1010010 $
b101010010 >
#3410000
b1010011 $
b101010011 >
#3420000
b1010100 $
b101010100 >
#3430000
b1010101 $
b101010101 >
#3440000
b1010110 $
b101010110 >
#3450000
b1010111 $
b101010111 >
#3460000
b1011000 $
b101011000 >
#3470000
b1011001 $
b101011001 >
#3480000
b1011010 $
b101011010 >
#3490000
b1011011 $
b101011011 >
#3500000
b1011100 $
b101011100 >
#3510000
b1011101 $
b101011101 >
#3520000
b1011110 $
b101011110 >
#3530000
b1011111 $
b101011111 >
#3540000
b1100000 $
b101100000 >
#3550000
b1100001 $
b101100001 >
#3560000
b1100010 $
b101100010 >
#3570000
b1100011 $
b101100011 >
#3580000
b1100100 $
b101100100 >
#3590000
b1100101 $
b101100101 >
#3600000
b1100110 $
b101100110 >
#3610000
b1100111 $
b101100111 >
#3620000
b1101000 $
b101101000 >
#3630000
b1101001 $
b101101001 >
#3640000
b1101010 $
b101101010 >
#3650000
b1101011 $
b101101011 >
#3660000
b1101100 $
b101101100 >
#3670000
b1101101 $
b101101101 >
#3680000
b1101110 $
b101101110 >
#3690000
b1101111 $
b101101111 >
#3700000
b1110000 $
b101110000 >
#3710000
b1110001 $
b101110001 >
#3720000
b1110010 $
b101110010 >
#3730000
b1110011 $
b101110011 >
#3740000
b1110100 $
b101110100 >
#3750000
b1110101 $
b101110101 >
#3760000
b1110110 $
b101110110 >
#3770000
b1110111 $
b101110111 >
#3780000
b1111000 $
b101111000 >
#3790000
b1111001 $
b101111001 >
#3800000
b1111010 $
b101111010 >
#3810000
b1111011 $
b101111011 >
#3820000
b1111100 $
b101111100 >
#3830000
b1111101 $
b101111101 >
#3840000
b1111110 $
b101111110 >
#3850000
b1111111 $
b101111111 >
#3860000
b10000000 $
b110000000 >
#3870000
b10000001 $
b110000001 >
#3880000
b10000010 $
b110000010 >
#3890000
b10000011 $
b110000011 >
#3900000
b10000100 $
b110000100 >
#3910000
b10000101 $
b110000101 >
#3920000
b10000110 $
b110000110 >
#3930000
b10000111 $
b110000111 >
#3940000
b10001000 $
b110001000 >
#3950000
b10001001 $
b110001001 >
#3960000
b10001010 $
b110001010 >
#3970000
b10001011 $
b110001011 >
#3980000
b10001100 $
b110001100 >
#3990000
b10001101 $
b110001101 >
#4000000
b10001110 $
b110001110 >
#4010000
b10001111 $
b110001111 >
#4020000
b10010000 $
b110010000 >
#4030000
b10010001 $
b110010001 >
#4040000
b10010010 $
b110010010 >
#4050000
b10010011 $
b110010011 >
#4060000
b10010100 $
b110010100 >
#4070000
b10010101 $
b110010101 >
#4080000
b10010110 $
b110010110 >
#4090000
b10010111 $
b110010111 >
#4100000
b10011000 $
b110011000 >
#4110000
b10011001 $
b110011001 >
#4120000
b10011010 $
b110011010 >
#4130000
b10011011 $
b110011011 >
#4140000
b10011100 $
b110011100 >
#4150000
b10011101 $
b110011101 >
#4160000
b10011110 $
b110011110 >
#4170000
b10011111 $
b110011111 >
#4180000
b10100000 $
b110100000 >
#4190000
b10100001 $
b110100001 >
#4200000
b10100010 $
b110100010 >
#4210000
b10100011 $
b110100011 >
#4220000
b10100100 $
b110100100 >
#4230000
b10100101 $
b110100101 >
#4240000
b10100110 $
b110100110 >
#4250000
b10100111 $
b110100111 >
#4260000
b10101000 $
b110101000 >
#4270000
b10101001 $
b110101001 >
#4280000
b10101010 $
b110101010 >
#4290000
b10101011 $
b110101011 >
#4300000
b10101100 $
b110101100 >
#4310000
b10101101 $
b110101101 >
#4320000
b10101110 $
b110101110 >
#4330000
b10101111 $
b110101111 >
#4340000
b10110000 $
b110110000 >
#4350000
b10110001 $
b110110001 >
#4360000
b10110010 $
b110110010 >
#4370000
b10110011 $
b110110011 >
#4380000
b10110100 $
b110110100 >
#4390000
b10110101 $
b110110101 >
#4400000
b10110110 $
b110110110 >
#4410000
b10110111 $
b110110111 >
#4420000
b10111000 $
b110111000 >
#4430000
b10111001 $
b110111001 >
#4440000
b10111010 $
b110111010 >
#4450000
b10111011 $
b110111011 >
#4460000
b10111100 $
b110111100 >
#4470000
b10111101 $
b110111101 >
#4480000
b10111110 $
b110111110 >
#4490000
b10111111 $
b110111111 >
#4500000
b11000000 $
b111000000 >
#4510000
b11000001 $
b111000001 >
#4520000
b11000010 $
b111000010 >
#4530000
b11000011 $
b111000011 >
#4540000
b11000100 $
b111000100 >
#4550000
b11000101 $
b111000101 >
#4560000
b11000110 $
b111000110 >
#4570000
b11000111 $
b111000111 >
#4580000
b11001000 $
b111001000 >
#4590000
b11001001 $
b111001001 >
#4600000
b11001010 $
b111001010 >
#4610000
b11001011 $
b111001011 >
#4620000
b11001100 $
b111001100 >
#4630000
b11001101 $
b111001101 >
#4640000
b11001110 $
b111001110 >
#4650000
b11001111 $
b111001111 >
#4660000
b11010000 $
b111010000 >
#4670000
b11010001 $
b111010001 >
#4680000
b11010010 $
b111010010 >
#4690000
b11010011 $
b111010011 >
#4700000
b11010100 $
b111010100 >
#4710000
b11010101 $
b111010101 >
#4720000
b11010110 $
b111010110 >
#4730000
b11010111 $
b111010111 >
#4740000
b11011000 $
b111011000 >
#4750000
b11011001 $
b111011001 >
#4760000
b11011010 $
b111011010 >
#4770000
b11011011 $
b111011011 >
#4780000
b11011100 $
b111011100 >
#4790000
b11011101 $
b111011101 >
#4800000
b11011110 $
b111011110 >
#4810000
b11011111 $
b111011111 >
#4820000
b11100000 $
b111100000 >
#4830000
b11100001 $
b111100001 >
#4840000
b11100010 $
b111100010 >
#4850000
b11100011 $
b111100011 >
#4860000
b11100100 $
b111100100 >
#4870000
b11100101 $
b111100101 >
#4880000
b11100110 $
b111100110 >
#4890000
b11100111 $
b111100111 >
#4900000
b11101000 $
b111101000 >
#4910000
b11101001 $
b111101001 >
#4920000
b11101010 $
b111101010 >
#4930000
b11101011 $
b111101011 >
#4940000
b11101100 $
b111101100 >
#4950000
b11101101 $
b111101101 >
#4960000
b11101110 $
b111101110 >
#4970000
b11101111 $
b111101111 >
#4980000
b11110000 $
b111110000 >
#4990000
b11110001 $
b111110001 >
#5000000
b11110010 $
b111110010 >
#5010000
b11110011 $
b111110011 >
#5020000
b11110100 $
b111110100 >
#5030000
b11110101 $
b111110101 >
#5040000
b11110110 $
b111110110 >
#5050000
b11110111 $
b111110111 >
#5060000
b11111000 $
b111111000 >
#5070000
b11111001 $
b111111001 >
#5080000
b11111010 $
b111111010 >
#5090000
b11111011 $
b111111011 >
#5100000
b11111100 $
b111111100 >
#5110000
b11111101 $
b111111101 >
#5120000
b11111110 $
b111111110 >
#5130000
b11111111 $
b111111111 >
#5140000
b0 $
b1000000000 >
#5150000
b1 $
b1000000001 >
#5160000
b10 $
b1000000010 >
#5170000
b11 $
b1000000011 >
#5180000
b100 $
b1000000100 >
#5190000
b101 $
b1000000101 >
#5200000
b110 $
b1000000110 >
#5210000
b111 $
b1000000111 >
#5220000
b1000 $
b1000001000 >
#5230000
b1001 $
b1000001001 >
#5240000
b1010 $
b1000001010 >
#5250000
b1011 $
b1000001011 >
#5260000
b1100 $
b1000001100 >
#5270000
b1101 $
b1000001101 >
#5280000
b1110 $
b1000001110 >
#5290000
b1111 $
b1000001111 >
#5300000
b10000 $
b1000010000 >
#5310000
b10001 $
b1000010001 >
#5320000
b10010 $
b1000010010 >
#5330000
b10011 $
b1000010011 >
#5340000
b10100 $
b1000010100 >
#5350000
b10101 $
b1000010101 >
#5360000
b10110 $
b1000010110 >
#5370000
b10111 $
b1000010111 >
#5380000
b11000 $
b1000011000 >
#5390000
b11001 $
b1000011001 >
#5400000
b11010 $
b1000011010 >
#5410000
b11011 $
b1000011011 >
#5420000
b11100 $
b1000011100 >
#5430000
b11101 $
b1000011101 >
#5440000
b11110 $
b1000011110 >
#5450000
b11111 $
b1000011111 >
#5460000
b100000 $
b1000100000 >
#5470000
b100001 $
b1000100001 >
#5480000
b100010 $
b1000100010 >
#5490000
b100011 $
b1000100011 >
#5500000
b100100 $
b1000100100 >
#5510000
b100101 $
b1000100101 >
#5520000
b100110 $
b1000100110 >
#5530000
b100111 $
b1000100111 >
#5540000
b101000 $
b1000101000 >
#5550000
b101001 $
b1000101001 >
#5560000
b101010 $
b1000101010 >
#5570000
b101011 $
b1000101011 >
#5580000
b101100 $
b1000101100 >
#5590000
b101101 $
b1000101101 >
#5600000
b101110 $
b1000101110 >
#5610000
b101111 $
b1000101111 >
#5620000
b110000 $
b1000110000 >
#5630000
b110001 $
b1000110001 >
#5640000
b110010 $
b1000110010 >
#5650000
b110011 $
b1000110011 >
#5660000
b110100 $
b1000110100 >
#5670000
b110101 $
b1000110101 >
#5680000
b110110 $
b1000110110 >
#5690000
b110111 $
b1000110111 >
#5700000
b111000 $
b1000111000 >
#5710000
b111001 $
b1000111001 >
#5720000
b111010 $
b1000111010 >
#5730000
b111011 $
b1000111011 >
#5740000
b111100 $
b1000111100 >
#5750000
b111101 $
b1000111101 >
#5760000
b111110 $
b1000111110 >
#5770000
b111111 $
b1000111111 >
#5780000
b1000000 $
b1001000000 >
#5790000
b1000001 $
b1001000001 >
#5800000
b1000010 $
b1001000010 >
#5810000
b1000011 $
b1001000011 >
#5820000
b1000100 $
b1001000100 >
#5830000
b1000101 $
b1001000101 >
#5840000
b1000110 $
b1001000110 >
#5850000
b1000111 $
b1001000111 >
#5860000
b1001000 $
b1001001000 >
#5870000
b1001001 $
b1001001001 >
#5880000
b1001010 $
b1001001010 >
#5890000
b1001011 $
b1001001011 >
#5900000
b1001100 $
b1001001100 >
#5910000
b1001101 $
b1001001101 >
#5920000
b1001110 $
b1001001110 >
#5930000
b1001111 $
b1001001111 >
#5940000
b1010000 $
b1001010000 >
#5950000
b1010001 $
b1001010001 >
#5960000
b1010010 $
b1001010010 >
#5970000
b1010011 $
b1001010011 >
#5980000
b1010100 $
b1001010100 >
#5990000
b1010101 $
b1001010101 >
#6000000
b1010110 $
b1001010110 >
#6010000
b1010111 $
b1001010111 >
#6020000
b1011000 $
b1001011000 >
#6030000
b1011001 $
b1001011001 >
#6040000
b1011010 $
b1001011010 >
#6050000
b1011011 $
b1001011011 >
#6060000
b1011100 $
b1001011100 >
#6070000
b1011101 $
b1001011101 >
#6080000
b1011110 $
b1001011110 >
#6090000
b1011111 $
b1001011111 >
#6100000
b1100000 $
b1001100000 >
#6110000
b1100001 $
b1001100001 >
#6120000
b1100010 $
b1001100010 >
#6130000
b1100011 $
b1001100011 >
#6140000
b1100100 $
b1001100100 >
#6150000
b1100101 $
b1001100101 >
#6160000
b1100110 $
b1001100110 >
#6170000
b1100111 $
b1001100111 >
#6180000
b1101000 $
b1001101000 >
#6190000
b1101001 $
b1001101001 >
#6200000
b1101010 $
b1001101010 >
#6210000
b1101011 $
b1001101011 >
#6220000
b1101100 $
b1001101100 >
#6230000
b1101101 $
b1001101101 >
#6240000
b1101110 $
b1001101110 >
#6250000
b1101111 $
b1001101111 >
#6260000
b1110000 $
b1001110000 >
#6270000
b1110001 $
b1001110001 >
#6280000
b1110010 $
b1001110010 >
#6290000
b1110011 $
b1001110011 >
#6300000
b1110100 $
b1001110100 >
#6310000
b1110101 $
b1001110101 >
#6320000
b1110110 $
b1001110110 >
#6330000
b1110111 $
b1001110111 >
#6340000
b1111000 $
b1001111000 >
#6350000
b1111001 $
b1001111001 >
#6360000
b1111010 $
b1001111010 >
#6370000
b1111011 $
b1001111011 >
#6380000
b1111100 $
b1001111100 >
#6390000
b1111101 $
b1001111101 >
#6400000
b1111110 $
b1001111110 >
#6410000
b1111111 $
b1001111111 >
#6420000
b10000000 $
b1010000000 >
#6430000
b10000001 $
b1010000001 >
#6440000
b10000010 $
b1010000010 >
#6450000
b10000011 $
b1010000011 >
#6460000
b10000100 $
b1010000100 >
#6470000
b10000101 $
b1010000101 >
#6480000
b10000110 $
b1010000110 >
#6490000
b10000111 $
b1010000111 >
#6500000
b10001000 $
b1010001000 >
#6510000
b10001001 $
b1010001001 >
#6520000
b10001010 $
b1010001010 >
#6530000
b10001011 $
b1010001011 >
#6540000
b10001100 $
b1010001100 >
#6550000
b10001101 $
b1010001101 >
#6560000
b10001110 $
b1010001110 >
#6570000
b10001111 $
b1010001111 >
#6580000
b10010000 $
b1010010000 >
#6590000
b10010001 $
b1010010001 >
#6600000
b10010010 $
b1010010010 >
#6610000
b10010011 $
b1010010011 >
#6620000
b10010100 $
b1010010100 >
#6630000
b10010101 $
b1010010101 >
#6640000
b10010110 $
b1010010110 >
#6650000
b10010111 $
b1010010111 >
#6660000
b10011000 $
b1010011000 >
#6670000
b10011001 $
b1010011001 >
#6680000
b10011010 $
b1010011010 >
#6690000
b10011011 $
b1010011011 >
#6700000
b10011100 $
b1010011100 >
#6710000
b10011101 $
b1010011101 >
#6720000
b10011110 $
b1010011110 >
#6730000
b10011111 $
b1010011111 >
#6740000
b10100000 $
b1010100000 >
#6750000
b10100001 $
b1010100001 >
#6760000
b10100010 $
b1010100010 >
#6770000
b10100011 $
b1010100011 >
#6780000
b10100100 $
b1010100100 >
#6790000
b10100101 $
b1010100101 >
