Archives/Lab 3/hdl/current_counter.sv
`timescale 1ns / 1ps
`default_nettype none // prevents system from inferring an undeclared logic (good practice)
 
module current_counter
  ( input wire clk_in, //clock in
    input wire rst_in, //reset in
    input wire signal_in, //signal to be monitored
    output logic [31:0] tally_out //tally of how many cycles signal in has been at its current value
  );
  logic old_sig;
  always_ff @(posedge clk_in)begin
    old_sig <= signal_in;
    if (rst_in) begin
        tally_out <= 0;
    end else begin
        if (old_sig != signal_in)begin
            tally_out <= 0;
        end else begin
            tally_out <= tally_out + 1;
        end
    end
  end
endmodule
`default_nettype wire

Archives/Lab 3/sim/current_counter_tb.sv
`timescale 1ns / 1ps
`default_nettype none

module current_counter_tb();

  logic clk_in;
  logic rst_in;
  logic signal_in;
  logic [31:0] tally_out;

  current_counter uut
  (.clk_in(clk_in),
   .rst_in(rst_in),
   .signal_in(signal_in),
   .tally_out(tally_out)
  );

  always begin
      #5;  //every 5 ns switch...so period of clock is 10 ns...100 MHz clock
      clk_in = !clk_in;
  end
  //initial block...this is our test simulation
  initial begin
    $dumpfile("current_tb.vcd"); //file to store value change dump (vcd)
    $dumpvars(0,current_counter_tb);
    $display("Starting Sim"); //print nice message at start
    clk_in = 0;
    rst_in = 0;
    signal_in = 0;
    #6;
    rst_in = 1;
    #10;
    rst_in = 0;
    $display("Starting");
    #100;
    signal_in = 1;
    #200;
    signal_in = 0;
    #10;
    signal_in = 1;
    #10;
    signal_in = 0;
    #10;
    signal_in = 1;
    #1000;
    $display("Finishing");
    $finish;
  end
endmodule
`default_nettype wire

Archives/Lab 3/current_tb.vcd
$date
	Tue Sep 26 19:25:24 2023
$end
$version
	Icarus Verilog
$end
$timescale
	1ps
$end
$scope module current_counter_tb $end
$var wire 32 ! tally_out [31:0] $end
$var reg 1 " clk_in $end
$var reg 1 # rst_in $end
$var reg 1 $ signal_in $end
$scope module uut $end
$var wire 1 " clk_in $end
$var wire 1 # rst_in $end
$var wire 1 $ signal_in $end
$var reg 1 % old_sig $end
$var reg 32 & tally_out [31:0] $end
$upscope $end
$upscope $end
$enddefinitions $end
$comment Show the parameter values. $end
$dumpall
$end
#0
$dumpvars
bx &
x%
0$
0#
0"
bx !
$end
#5000
0%
1"
#6000
1#
#10000
0"
#15000
b0 !
b0 &
1"
#16000
0#
#20000
0"
#25000
b1 !
b1 &
1"
#30000
0"
#35000
b10 !
b10 &
1"
#40000
0"
#45000
b11 !
b11 &
1"
#50000
0"
#55000
b100 !
b100 &
1"
#60000
0"
#65000
b101 !
b101 &
1"
#70000
0"
#75000
b110 !
b110 &
1"
#80000
0"
#85000
b111 !
b111 &
1"
#90000
0"
#95000
b1000 !
b1000 &
1"
#100000
0"
#105000
b1001 !
b1001 &
1"
#110000
0"
#115000
b1010 !
b1010 &
1"
#116000
1$
#120000
0"
#125000
b0 !
b0 &
1%
1"
#130000
0"
#135000
b1 !
b1 &
1"
#140000
0"
#145000
b10 !
b10 &
1"
#150000
0"
#155000
b11 !
b11 &
1"
#160000
0"
#165000
b100 !
b100 &
1"
#170000
0"
#175000
b101 !
b101 &
1"
#180000
0"
#185000
b110 !
b110 &
1"
#190000
0"
#195000
b111 !
b111 &
1"
#200000
0"
#205000
b1000 !
b1000 &
1"
#210000
0"
#215000
b1001 !
b1001 &
1"
#220000
0"
#225000
b1010 !
b1010 &
1"
#230000
0"
#235000
b1011 !
b1011 &
1"
#240000
0"
#245000
b1100 !
b1100 &
1"
#250000
0"
#255000
b1101 !
b1101 &
1"
#260000
0"
#265000
b1110 !
b1110 &
1"
#270000
0"
#275000
b1111 !
b1111 &
1"
#280000
0"
#285000
b10000 !
b10000 &
1"
#290000
0"
#295000
b10001 !
b10001 &
1"
#300000
0"
#305000
b10010 !
b10010 &
1"
#310000
0"
#315000
b10011 !
b10011 &
1"
#316000
0$
#320000
0"
#325000
b0 !
b0 &
0%
1"
#326000
1$
#330000
0"
#335000
1%
1"
#336000
0$
#340000
0"
#345000
0%
1"
#346000
1$
#350000
0"
#355000
1%
1"
#360000
0"
#365000
b1 !
b1 &
1"
#370000
0"
#375000
b10 !
b10 &
1"
#380000
0"
#385000
b11 !
b11 &
1"
#390000
0"
#395000
b100 !
b100 &
1"
#400000
0"
#405000
b101 !
b101 &
1"
#410000
0"
#415000
b110 !
b110 &
1"
#420000
0"
#425000
b111 !
b111 &
1"
#430000
0"
#435000
b1000 !
b1000 &
1"
#440000
0"
#445000
b1001 !
b1001 &
1"
#450000
0"
#455000
b1010 !
b1010 &
1"
#460000
0"
#465000
b1011 !
b1011 &
1"
#470000
0"
#475000
b1100 !
b1100 &
1"
#480000
0"
#485000
b1101 !
b1101 &
1"
#490000
0"
#495000
b1110 !
b1110 &
1"
#500000
0"
#505000
b1111 !
b1111 &
1"
#510000
0"
#515000
b10000 !
b10000 &
1"
#520000
0"
#525000
b10001 !
b10001 &
1"
#530000
0"
#535000
b10010 !
b10010 &
1"
#540000
0"
#545000
b10011 !
b10011 &
1"
#550000
0"
#555000
b10100 !
b10100 &
1"
#560000
0"
#565000
b10101 !
b10101 &
1"
#570000
0"
#575000
b10110 !
b10110 &
1"
#580000
0"
#585000
b10111 !
b10111 &
1"
#590000
0"
#595000
b11000 !
b11000 &
1"
#600000
0"
#605000
b11001 !
b11001 &
1"
#610000
0"
#615000
b11010 !
b11010 &
1"
#620000
0"
#625000
b11011 !
b11011 &
1"
#630000
0"
#635000
b11100 !
b11100 &
1"
#640000
0"
#645000
b11101 !
b11101 &
1"
#650000
0"
#655000
b11110 !
b11110 &
1"
#660000
0"
#665000
b11111 !
b11111 &
1"
#670000
0"
#675000
b100000 !
b100000 &
1"
#680000
0"
#685000
b100001 !
b100001 &
1"
#690000
0"
#695000
b100010 !
b100010 &
1"
#700000
0"
#705000
b100011 !
b100011 &
1"
#710000
0"
#715000
b100100 !
b100100 &
1"
#720000
0"
#725000
b100101 !
b100101 &
1"
#730000
0"
#735000
b100110 !
b100110 &
1"
#740000
0"
#745000
b100111 !
b100111 &
1"
#750000
0"
#755000
b101000 !
b101000 &
1"
#760000
0"
#765000
b101001 !
b101001 &
1"
#770000
0"
#775000
b101010 !
b101010 &
1"
#780000
0"
#785000
b101011 !
b101011 &
1"
#790000
0"
#795000
b101100 !
b101100 &
1"
#800000
0"
#805000
b101101 !
b101101 &
1"
#810000
0"
#815000
b101110 !
b101110 &
1"
#820000
0"
#825000
b101111 !
b101111 &
1"
#830000
0"
#835000
b110000 !
b110000 &
1"
#840000
0"
#845000
b110001 !
b110001 &
1"
#850000
0"
#855000
b110010 !
b110010 &
1"
#860000
0"
#865000
b110011 !
b110011 &
1"
#870000
0"
#875000
b110100 !
b110100 &
1"
#880000
0"
#885000
b110101 !
b110101 &
1"
#890000
0"
#895000
b110110 !
b110110 &
1"
#900000
0"
#905000
b110111 !
b110111 &
1"
#910000
0"
#915000
b111000 !
b111000 &
1"
#920000
0"
#925000
b111001 !
b111001 &
1"
#930000
0"
#935000
b111010 !
b111010 &
1"
#940000
0"
#945000
b111011 !
b111011 &
1"
#950000
0"
#955000
b111100 !
b111100 &
1"
#960000
0"
#965000
b111101 !
b111101 &
1"
#970000
0"
#975000
b111110 !
b111110 &
1"
#980000
0"
#985000
b111111 !
b111111 &
1"
#990000
0"
#995000
b1000000 !
b1000000 &
1"
#1000000
0"
#1005000
b1000001 !
b1000001 &
1"
#1010000
0"
#1015000
b1000010 !
b1000010 &
1"
#1020000
0"
#1025000
b1000011 !
b1000011 &
1"
#1030000
0"
#1035000
b1000100 !
b1000100 &
1"
#1040000
0"
#1045000
b1000101 !
b1000101 &
1"
#1050000
0"
#1055000
b1000110 !
b1000110 &
1"
#1060000
0"
#1065000
b1000111 !
b1000111 &
1"
#1070000
0"
#1075000
b1001000 !
b1001000 &
1"
#1080000
0"
#1085000
b1001001 !
b1001001 &
1"
#1090000
0"
#1095000
b1001010 !
b1001010 &
1"
#1100000
0"
#1105000
b1001011 !
b1001011 &
1"
#1110000
0"
#1115000
b1001100 !
b1001100 &
1"
#1120000
0"
#1125000
b1001101 !
b1001101 &
1"
#1130000
0"
#1135000
b1001110 !
b1001110 &
1"
#1140000
0"
#1145000
b1001111 !
b1001111 &
1"
#1150000
0"
#1155000
b1010000 !
b1010000 &
1"
#1160000
0"
#1165000
b1010001 !
b1010001 &
1"
#1170000
0"
#1175000
b1010010 !
b1010010 &
1"
#1180000
0"
#1185000
b1010011 !
b1010011 &
1"
#1190000
0"
#1195000
b1010100 !
b1010100 &
1"
#1200000
0"
#1205000
b1010101 !
b1010101 &
1"
#1210000
0"
#1215000
b1010110 !
b1010110 &
1"
#1220000
0"
#1225000
b1010111 !
b1010111 &
1"
#1230000
0"
#1235000
b1011000 !
b1011000 &
1"
#1240000
0"
#1245000
b1011001 !
b1011001 &
1"
#1250000
0"
#1255000
b1011010 !
b1011010 &
1"
#1260000
0"
#1265000
b1011011 !
b1011011 &
1"
#1270000
0"
#1275000
b1011100 !
b1011100 &
1"
#1280000
0"
#1285000
b1011101 !
b1011101 &
1"
#1290000
0"
#1295000
b1011110 !
b1011110 &
1"
#1300000
0"
#1305000
b1011111 !
b1011111 &
1"
#1310000
0"
#1315000
b1100000 !
b1100000 &
1"
#1320000
0"
#1325000
b1100001 !
b1100001 &
1"
#1330000
0"
#1335000
b1100010 !
b1100010 &
1"
#1340000
0"
#1345000
b1100011 !
b1100011 &
1"
