Archives/Lab 3/hdl/pwm.sv
`timescale 1ns / 1ps
`default_nettype none
 
module  pwm
          (input wire clk_in,
            input wire rst_in,
            input wire [7:0] level_in,
            output logic pwm_out
          );
  //your code here
  logic [31:0] counter;
  always_ff @(posedge clk_in)begin
    if (rst_in) begin
        counter <= 0;
        pwm_out <= 0;
    end else begin
        counter <= counter + 1;
        if (counter == 31'd256 - level_in)begin
            pwm_out <= 1;
        end else if (counter == 31'd256)begin
            pwm_out <= 0;
            counter <= 0;
        end
    end
  end
endmodule
 
`default_nettype wire

Archives/Lab 3/sim/pwm_tb.sv
`timescale 1ns / 1ps
`default_nettype none

module pwm_tb;

  //make logics for inputs and outputs!
  logic clk_in;
  logic rst_in;
  logic [7:0] level_in;
  logic pwm_out;

  pwm pwm (.clk_in(clk_in),
            .rst_in(rst_in),
            .level_in(level_in),
            .pwm_out(pwm_out));
  always begin
    #5;  //every 5 ns switch...so period of clock is 10 ns...100 MHz clock
    clk_in = !clk_in;
  end

  //initial block...this is our test simulation
  initial begin
    $dumpfile("pwb.vcd"); //file to store value change dump (vcd)
    $dumpvars(0,pwm_tb); //store everything at the current level and below
    $display("Starting Sim"); //print nice message
    clk_in = 0; //initialize clk (super important)
    rst_in = 0; //initialize rst (super important)

    level_in = 100; //add different cases

    #10  //wait a little bit of time at beginning
    rst_in = 1; //reset system
    #10; //hold high for a few clock cycles
    rst_in=0;
    for (int i = 0; i<3000; i= i+1)begin
      //$display(pwm_out);
      #10;
    end
    level_in = 255; 
    for (int i = 0; i<3000; i= i+1)begin
      //$display(pwm_out);
      #10;
    end
    $finish;

  end
endmodule //counter_tb

`default_nettype wire

Archives/Lab 3/pwb.vcd
$date
	Wed Sep 27 16:23:00 2023
$end
$version
	Icarus Verilog
$end
$timescale
	1ps
$end
$scope module pwm_tb $end
$var wire 1 ! pwm_out $end
$var reg 1 " clk_in $end
$var reg 8 # level_in [7:0] $end
$var reg 1 $ rst_in $end
$scope module pwm $end
$var wire 1 " clk_in $end
$var wire 8 % level_in [7:0] $end
$var wire 1 $ rst_in $end
$var reg 32 & counter [31:0] $end
$var reg 1 ! pwm_out $end
$upscope $end
$scope begin $ivl_for_loop0 $end
$var integer 32 ' i [31:0] $end
$upscope $end
$scope begin $ivl_for_loop1 $end
$var integer 32 ( i [31:0] $end
$upscope $end
$upscope $end
$enddefinitions $end
$comment Show the parameter values. $end
$dumpall
$end
#0
$dumpvars
b0 (
b0 '
bx &
b1100100 %
0$
b1100100 #
0"
x!
$end
#5000
1"
#10000
0"
1$
#15000
0!
b0 &
1"
#20000
0"
0$
#25000
b1 &
1"
#30000
0"
b1 '
#35000
b10 &
1"
#40000
0"
b10 '
#45000
b11 &
1"
#50000
0"
b11 '
#55000
b100 &
1"
#60000
0"
b100 '
#65000
b101 &
1"
#70000
0"
b101 '
#75000
b110 &
1"
#80000
0"
b110 '
#85000
b111 &
1"
#90000
0"
b111 '
#95000
b1000 &
1"
#100000
0"
b1000 '
#105000
b1001 &
1"
#110000
0"
b1001 '
#115000
b1010 &
1"
#120000
0"
b1010 '
#125000
b1011 &
1"
#130000
0"
b1011 '
#135000
b1100 &
1"
#140000
0"
b1100 '
#145000
b1101 &
1"
#150000
0"
b1101 '
#155000
b1110 &
1"
#160000
0"
b1110 '
#165000
b1111 &
1"
#170000
0"
b1111 '
#175000
b10000 &
1"
#180000
0"
b10000 '
#185000
b10001 &
1"
#190000
0"
b10001 '
#195000
b10010 &
1"
#200000
0"
b10010 '
#205000
b10011 &
1"
#210000
0"
b10011 '
#215000
b10100 &
1"
#220000
0"
b10100 '
#225000
b10101 &
1"
#230000
0"
b10101 '
#235000
b10110 &
1"
#240000
0"
b10110 '
#245000
b10111 &
1"
#250000
0"
b10111 '
#255000
b11000 &
1"
#260000
0"
b11000 '
#265000
b11001 &
1"
#270000
0"
b11001 '
#275000
b11010 &
1"
#280000
0"
b11010 '
#285000
b11011 &
1"
#290000
0"
b11011 '
#295000
b11100 &
1"
#300000
0"
b11100 '
#305000
b11101 &
1"
#310000
0"
b11101 '
#315000
b11110 &
1"
#320000
0"
b11110 '
#325000
b11111 &
1"
#330000
0"
b11111 '
#335000
b100000 &
1"
#340000
0"
b100000 '
#345000
b100001 &
1"
#350000
0"
b100001 '
#355000
b100010 &
1"
#360000
0"
b100010 '
#365000
b100011 &
1"
#370000
0"
b100011 '
#375000
b100100 &
1"
#380000
0"
b100100 '
#385000
b100101 &
1"
#390000
0"
b100101 '
#395000
b100110 &
1"
#400000
0"
b100110 '
#405000
b100111 &
1"
#410000
0"
b100111 '
#415000
b101000 &
1"
#420000
0"
b101000 '
#425000
b101001 &
1"
#430000
0"
b101001 '
#435000
b101010 &
1"
#440000
0"
b101010 '
#445000
b101011 &
1"
#450000
0"
b101011 '
#455000
b101100 &
1"
#460000
0"
b101100 '
#465000
b101101 &
1"
#470000
0"
b101101 '
#475000
b101110 &
1"
#480000
0"
b101110 '
#485000
b101111 &
1"
#490000
0"
b101111 '
#495000
b110000 &
1"
#500000
0"
b110000 '
#505000
b110001 &
1"
#510000
0"
b110001 '
#515000
b110010 &
1"
#520000
0"
b110010 '
#525000
b110011 &
1"
#530000
0"
b110011 '
#535000
b110100 &
1"
#540000
0"
b110100 '
#545000
b110101 &
1"
#550000
0"
b110101 '
#555000
b110110 &
1"
#560000
0"
b110110 '
#565000
b110111 &
1"
#570000
0"
b110111 '
#575000
b111000 &
1"
#580000
0"
b111000 '
#585000
b111001 &
1"
#590000
0"
b111001 '
#595000
b111010 &
1"
#600000
0"
b111010 '
#605000
b111011 &
1"
#610000
0"
b111011 '
#615000
b111100 &
1"
#620000
0"
b111100 '
#625000
b111101 &
1"
#630000
0"
b111101 '
#635000
b111110 &
1"
#640000
0"
b111110 '
#645000
b111111 &
1"
#650000
0"
b111111 '
#655000
b1000000 &
1"
#660000
0"
b1000000 '
#665000
b1000001 &
1"
#670000
0"
b1000001 '
#675000
b1000010 &
1"
#680000
0"
b1000010 '
#685000
b1000011 &
1"
#690000
0"
b1000011 '
#695000
b1000100 &
1"
#700000
0"
b1000100 '
#705000
b1000101 &
1"
#710000
0"
b1000101 '
#715000
b1000110 &
1"
#720000
0"
b1000110 '
#725000
b1000111 &
1"
#730000
0"
b1000111 '
#735000
b1001000 &
1"
#740000
0"
b1001000 '
#745000
b1001001 &
1"
#750000
0"
b1001001 '
#755000
b1001010 &
1"
#760000
0"
b1001010 '
#765000
b1001011 &
1"
#770000
0"
b1001011 '
#775000
b1001100 &
1"
#780000
0"
b1001100 '
#785000
b1001101 &
1"
#790000
0"
b1001101 '
#795000
b1001110 &
1"
#800000
0"
b1001110 '
#805000
b1001111 &
1"
#810000
0"
b1001111 '
#815000
b1010000 &
1"
#820000
0"
b1010000 '
#825000
b1010001 &
1"
#830000
0"
b1010001 '
#835000
b1010010 &
1"
#840000
0"
b1010010 '
#845000
b1010011 &
1"
#850000
0"
b1010011 '
#855000
b1010100 &
1"
#860000
0"
b1010100 '
#865000
b1010101 &
1"
#870000
0"
b1010101 '
#875000
b1010110 &
1"
#880000
0"
b1010110 '
#885000
b1010111 &
1"
#890000
0"
b1010111 '
#895000
b1011000 &
1"
#900000
0"
b1011000 '
#905000
b1011001 &
1"
#910000
0"
b1011001 '
#915000
b1011010 &
1"
#920000
0"
b1011010 '
#925000
b1011011 &
1"
#930000
0"
b1011011 '
#935000
b1011100 &
1"
#940000
0"
b1011100 '
#945000
b1011101 &
1"
#950000
0"
b1011101 '
#955000
b1011110 &
1"
#960000
0"
b1011110 '
#965000
b1011111 &
1"
#970000
0"
b1011111 '
#975000
b1100000 &
1"
#980000
0"
b1100000 '
#985000
b1100001 &
1"
#990000
0"
b1100001 '
#995000
b1100010 &
1"
#1000000
0"
b1100010 '
#1005000
b1100011 &
1"
#1010000
0"
b1100011 '
#1015000
b1100100 &
1"
#1020000
0"
b1100100 '
#1025000
b1100101 &
1"
#1030000
0"
b1100101 '
#1035000
b1100110 &
1"
#1040000
0"
b1100110 '
#1045000
b1100111 &
1"
#1050000
0"
b1100111 '
#1055000
b1101000 &
1"
#1060000
0"
b1101000 '
#1065000
b1101001 &
1"
#1070000
0"
b1101001 '
#1075000
b1101010 &
1"
#1080000
0"
b1101010 '
#1085000
b1101011 &
1"
#1090000
0"
b1101011 '
#1095000
b1101100 &
1"
#1100000
0"
b1101100 '
#1105000
b1101101 &
1"
#1110000
0"
b1101101 '
#1115000
b1101110 &
1"
#1120000
0"
b1101110 '
#1125000
b1101111 &
1"
#1130000
0"
b1101111 '
#1135000
b1110000 &
1"
#1140000
0"
b1110000 '
#1145000
b1110001 &
1"
#1150000
0"
b1110001 '
#1155000
b1110010 &
1"
#1160000
0"
b1110010 '
#1165000
b1110011 &
1"
#1170000
0"
b1110011 '
#1175000
b1110100 &
1"
#1180000
0"
b1110100 '
#1185000
b1110101 &
1"
#1190000
0"
b1110101 '
#1195000
b1110110 &
1"
#1200000
0"
b1110110 '
#1205000
b1110111 &
1"
#1210000
0"
b1110111 '
#1215000
b1111000 &
1"
#1220000
0"
b1111000 '
#1225000
b1111001 &
1"
#1230000
0"
b1111001 '
#1235000
b1111010 &
1"
#1240000
0"
b1111010 '
#1245000
b1111011 &
1"
#1250000
0"
b1111011 '
#1255000
b1111100 &
1"
#1260000
0"
b1111100 '
#1265000
b1111101 &
1"
#1270000
0"
b1111101 '
#1275000
b1111110 &
1"
#1280000
0"
b1111110 '
#1285000
b1111111 &
1"
#1290000
0"
b1111111 '
#1295000
b10000000 &
1"
#1300000
0"
b10000000 '
#1305000
b10000001 &
1"
#1310000
0"
b10000001 '
#1315000
b10000010 &
1"
#1320000
0"
b10000010 '
#1325000
b10000011 &
1"
#1330000
0"
b10000011 '
#1335000
b10000100 &
1"
#1340000
0"
b10000100 '
#1345000
b10000101 &
1"
#1350000
0"
b10000101 '
#1355000
b10000110 &
1"
#1360000
0"
b10000110 '
#1365000
b10000111 &
1"
#1370000
0"
b10000111 '
#1375000
b10001000 &
1"
#1380000
0"
b10001000 '
#1385000
b10001001 &
1"
#1390000
0"
b10001001 '
#1395000
b10001010 &
1"
#1400000
0"
b10001010 '
#1405000
b10001011 &
1"
#1410000
0"
b10001011 '
#1415000
b10001100 &
1"
#1420000
0"
b10001100 '
#1425000
b10001101 &
1"
#1430000
0"
b10001101 '
#1435000
b10001110 &
1"
#1440000
0"
b10001110 '
#1445000
b10001111 &
1"
#1450000
0"
b10001111 '
#1455000
b10010000 &
1"
#1460000
0"
b10010000 '
#1465000
b10010001 &
1"
#1470000
0"
b10010001 '
#1475000
b10010010 &
1"
#1480000
0"
b10010010 '
#1485000
b10010011 &
1"
#1490000
0"
b10010011 '
#1495000
b10010100 &
1"
#1500000
0"
b10010100 '
#1505000
b10010101 &
1"
#1510000
0"
b10010101 '
#1515000
b10010110 &
1"
#1520000
0"
b10010110 '
#1525000
b10010111 &
1"
#1530000
0"
b10010111 '
#1535000
b10011000 &
1"
#1540000
0"
b10011000 '
#1545000
b10011001 &
1"
#1550000
0"
b10011001 '
#1555000
b10011010 &
1"
#1560000
0"
b10011010 '
#1565000
b10011011 &
1"
#1570000
0"
b10011011 '
#1575000
b10011100 &
1"
#1580000
0"
b10011100 '
#1585000
1!
b10011101 &
1"
#1590000
0"
b10011101 '
#1595000
b10011110 &
1"
#1600000
0"
b10011110 '
#1605000
b10011111 &
1"
#1610000
0"
b10011111 '
#1615000
b10100000 &
1"
#1620000
0"
b10100000 '
#1625000
b10100001 &
1"
#1630000
0"
b10100001 '
#1635000
b10100010 &
1"
#1640000
0"
b10100010 '
#1645000
b10100011 &
1"
#1650000
0"
b10100011 '
#1655000
b10100100 &
1"
#1660000
0"
b10100100 '
#1665000
b10100101 &
1"
#1670000
0"
b10100101 '
#1675000
b10100110 &
1"
#1680000
0"
b10100110 '
#1685000
b10100111 &
1"
#1690000
0"
b10100111 '
#1695000
b10101000 &
1"
#1700000
0"
b10101000 '
#1705000
b10101001 &
1"
#1710000
0"
b10101001 '
#1715000
b10101010 &
1"
#1720000
0"
b10101010 '
#1725000
b10101011 &
1"
#1730000
0"
b10101011 '
#1735000
b10101100 &
1"
#1740000
0"
b10101100 '
#1745000
b10101101 &
1"
#1750000
0"
b10101101 '
#1755000
b10101110 &
1"
#1760000
0"
b10101110 '
#1765000
b10101111 &
1"
#1770000
0"
b10101111 '
#1775000
b10110000 &
1"
#1780000
0"
b10110000 '
#1785000
b10110001 &
1"
#1790000
0"
b10110001 '
#1795000
b10110010 &
1"
#1800000
0"
b10110010 '
#1805000
b10110011 &
1"
#1810000
0"
b10110011 '
#1815000
b10110100 &
1"
#1820000
0"
b10110100 '
#1825000
b10110101 &
1"
#1830000
0"
b10110101 '
#1835000
b10110110 &
1"
#1840000
0"
b10110110 '
#1845000
b10110111 &
1"
#1850000
0"
b10110111 '
#1855000
b10111000 &
1"
#1860000
0"
b10111000 '
#1865000
b10111001 &
1"
#1870000
0"
b10111001 '
#1875000
b10111010 &
1"
#1880000
0"
b10111010 '
#1885000
b10111011 &
1"
#1890000
0"
b10111011 '
#1895000
b10111100 &
1"
#1900000
0"
b10111100 '
#1905000
b10111101 &
1"
#1910000
0"
b10111101 '
#1915000
b10111110 &
1"
#1920000
0"
b10111110 '
#1925000
b10111111 &
1"
#1930000
0"
b10111111 '
#1935000
b11000000 &
1"
#1940000
0"
b11000000 '
#1945000
b11000001 &
1"
#1950000
0"
b11000001 '
#1955000
b11000010 &
1"
#1960000
0"
b11000010 '
#1965000
b11000011 &
1"
#1970000
0"
b11000011 '
#1975000
b11000100 &
1"
#1980000
0"
b11000100 '
#1985000
b11000101 &
1"
#1990000
0"
b11000101 '
#1995000
b11000110 &
1"
#2000000
0"
b11000110 '
#2005000
b11000111 &
1"
#2010000
0"
b11000111 '
#2015000
b11001000 &
1"
#2020000
0"
b11001000 '
#2025000
b11001001 &
1"
#2030000
0"
b11001001 '
#2035000
b11001010 &
1"
#2040000
0"
b11001010 '
#2045000
b11001011 &
1"
#2050000
0"
b11001011 '
#2055000
b11001100 &
1"
#2060000
0"
b11001100 '
#2065000
b11001101 &
1"
#2070000
0"
b11001101 '
#2075000
b11001110 &
1"
#2080000
0"
b11001110 '
#2085000
b11001111 &
1"
#2090000
0"
b11001111 '
#2095000
b11010000 &
1"
#2100000
0"
b11010000 '
#2105000
b11010001 &
1"
#2110000
0"
b11010001 '
#2115000
b11010010 &
1"
#2120000
0"
b11010010 '
#2125000
b11010011 &
1"
#2130000
0"
b11010011 '
#2135000
b11010100 &
1"
#2140000
0"
b11010100 '
#2145000
b11010101 &
1"
#2150000
0"
b11010101 '
#2155000
b11010110 &
1"
#2160000
0"
b11010110 '
#2165000
b11010111 &
1"
#2170000
0"
b11010111 '
#2175000
b11011000 &
1"
#2180000
0"
b11011000 '
#2185000
b11011001 &
1"
#2190000
0"
b11011001 '
#2195000
b11011010 &
1"
#2200000
0"
b11011010 '
#2205000
b11011011 &
1"
#2210000
0"
b11011011 '
#2215000
b11011100 &
1"
#2220000
0"
b11011100 '
#2225000
b11011101 &
1"
#2230000
0"
b11011101 '
#2235000
b11011110 &
1"
#2240000
0"
b11011110 '
#2245000
b11011111 &
1"
#2250000
0"
b11011111 '
#2255000
b11100000 &
1"
#2260000
0"
b11100000 '
#2265000
b11100001 &
1"
#2270000
0"
b11100001 '
#2275000
b11100010 &
1"
#2280000
0"
b11100010 '
#2285000
b11100011 &
1"
#2290000
0"
b11100011 '
#2295000
b11100100 &
1"
#2300000
0"
b11100100 '
#2305000
b11100101 &
1"
#2310000
0"
b11100101 '
#2315000
b11100110 &
1"
#2320000
0"
b11100110 '
#2325000
b11100111 &
1"
#2330000
0"
b11100111 '
#2335000
b11101000 &
1"
#2340000
0"
b11101000 '
#2345000
b11101001 &
1"
#2350000
0"
b11101001 '
#2355000
b11101010 &
1"
#2360000
0"
b11101010 '
#2365000
b11101011 &
1"
#2370000
0"
b11101011 '
#2375000
b11101100 &
1"
#2380000
0"
b11101100 '
#2385000
b11101101 &
1"
#2390000
0"
b11101101 '
#2395000
b11101110 &
1"
#2400000
0"
b11101110 '
#2405000
b11101111 &
1"
#2410000
0"
b11101111 '
#2415000
b11110000 &
1"
#2420000
0"
b11110000 '
#2425000
b11110001 &
1"
#2430000
0"
b11110001 '
#2435000
b11110010 &
1"
#2440000
0"
b11110010 '
#2445000
b11110011 &
1"
#2450000
0"
b11110011 '
#2455000
b11110100 &
1"
#2460000
0"
b11110100 '
#2465000
b11110101 &
1"
#2470000
0"
b11110101 '
#2475000
b11110110 &
1"
#2480000
0"
b11110110 '
#2485000
b11110111 &
1"
#2490000
0"
b11110111 '
#2495000
b11111000 &
1"
#2500000
0"
b11111000 '
#2505000
b11111001 &
1"
#2510000
0"
b11111001 '
#2515000
b11111010 &
1"
#2520000
0"
b11111010 '
#2525000
b11111011 &
1"
#2530000
0"
b11111011 '
#2535000
b11111100 &
1"
#2540000
0"
b11111100 '
#2545000
b11111101 &
1"
#2550000
0"
b11111101 '
#2555000
b11111110 &
1"
#2560000
0"
b11111110 '
#2565000
b11111111 &
1"
#2570000
0"
b11111111 '
#2575000
b100000000 &
1"
#2580000
0"
b100000000 '
#2585000
0!
b0 &
1"
#2590000
0"
b100000001 '
#2595000
b1 &
1"
#2600000
0"
b100000010 '
#2605000
b10 &
1"
#2610000
0"
b100000011 '
#2615000
b11 &
1"
#2620000
0"
b100000100 '
#2625000
b100 &
1"
#2630000
0"
b100000101 '
#2635000
b101 &
1"
#2640000
0"
b100000110 '
#2645000
b110 &
1"
#2650000
0"
b100000111 '
#2655000
b111 &
1"
#2660000
0"
b100001000 '
#2665000
b1000 &
1"
#2670000
0"
b100001001 '
#2675000
b1001 &
1"
#2680000
0"
b100001010 '
#2685000
b1010 &
1"
#2690000
0"
b100001011 '
#2695000
b1011 &
1"
#2700000
0"
b100001100 '
#2705000
b1100 &
1"
#2710000
0"
b100001101 '
#2715000
b1101 &
1"
#2720000
0"
b100001110 '
#2725000
b1110 &
1"
#2730000
0"
b100001111 '
#2735000
b1111 &
1"
#2740000
0"
b100010000 '
#2745000
b10000 &
1"
#2750000
0"
b100010001 '
#2755000
b10001 &
1"
#2760000
0"
b100010010 '
#2765000
b10010 &
1"
#2770000
0"
b100010011 '
#2775000
b10011 &
1"
#2780000
0"
b100010100 '
#2785000
b10100 &
1"
#2790000
0"
b100010101 '
#2795000
b10101 &
1"
#2800000
0"
b100010110 '
#2805000
b10110 &
1"
#2810000
0"
b100010111 '
#2815000
b10111 &
1"
#2820000
0"
b100011000 '
#2825000
b11000 &
1"
#2830000
0"
b100011001 '
#2835000
b11001 &
1"
#2840000
0"
b100011010 '
#2845000
b11010 &
1"
#2850000
0"
b100011011 '
#2855000
b11011 &
1"
#2860000
0"
b100011100 '
#2865000
b11100 &
1"
#2870000
0"
b100011101 '
#2875000
b11101 &
1"
#2880000
0"
b100011110 '
#2885000
b11110 &
1"
#2890000
0"
b100011111 '
#2895000
b11111 &
1"
#2900000
0"
b100100000 '
#2905000
b100000 &
1"
#2910000
0"
b100100001 '
#2915000
b100001 &
1"
#2920000
0"
b100100010 '
#2925000
b100010 &
1"
#2930000
0"
b100100011 '
#2935000
b100011 &
1"
#2940000
0"
b100100100 '
#2945000
b100100 &
1"
#2950000
0"
b100100101 '
#2955000
b100101 &
1"
#2960000
0"
b100100110 '
#2965000
b100110 &
1"
#2970000
0"
b100100111 '
#2975000
b100111 &
1"
#2980000
0"
b100101000 '
#2985000
b101000 &
1"
#2990000
0"
b100101001 '
#2995000
b101001 &
1"
#3000000
0"
b100101010 '
#3005000
b101010 &
1"
#3010000
0"
b100101011 '
#3015000
b101011 &
1"
#3020000
0"
b100101100 '
#3025000
b101100 &
1"
#3030000
0"
b100101101 '
#3035000
b101101 &
1"
#3040000
0"
b100101110 '
#3045000
b101110 &
1"
#3050000
0"
b100101111 '
#3055000
b101111 &
1"
#3060000
0"
b100110000 '
#3065000
b110000 &
1"
#3070000
0"
b100110001 '
#3075000
b110001 &
1"
#3080000
0"
b100110010 '
#3085000
b110010 &
1"
#3090000
0"
b100110011 '
#3095000
b110011 &
1"
#3100000
0"
b100110100 '
#3105000
b110100 &
1"
#3110000
0"
b100110101 '
#3115000
b110101 &
1"
#3120000
0"
b100110110 '
#3125000
b110110 &
1"
#3130000
0"
b100110111 '
#3135000
b110111 &
1"
#3140000
0"
b100111000 '
#3145000
b111000 &
1"
#3150000
0"
b100111001 '
#3155000
b111001 &
1"
#3160000
0"
b100111010 '
#3165000
b111010 &
1"
#3170000
0"
b100111011 '
#3175000
b111011 &
1"
#3180000
0"
b100111100 '
#3185000
b111100 &
1"
#3190000
0"
b100111101 '
#3195000
b111101 &
1"
#3200000
0"
b100111110 '
#3205000
b111110 &
1"
#3210000
0"
b100111111 '
#3215000
b111111 &
1"
#3220000
0"
b101000000 '
#3225000
b1000000 &
1"
#3230000
0"
b101000001 '
#3235000
b1000001 &
1"
#3240000
0"
b101000010 '
#3245000
b1000010 &
1"
#3250000
0"
b101000011 '
#3255000
b1000011 &
1"
#3260000
0"
b101000100 '
#3265000
b1000100 &
1"
#3270000
0"
b101000101 '
#3275000
b1000101 &
1"
#3280000
0"
b101000110 '
#3285000
b1000110 &
1"
#3290000
0"
b101000111 '
#3295000
b1000111 &
1"
#3300000
0"
b101001000 '
#3305000
b1001000 &
1"
#3310000
0"
b101001001 '
#3315000
b1001001 &
1"
#3320000
0"
b101001010 '
#3325000
b1001010 &
1"
#3330000
0"
b101001011 '
#3335000
b1001011 &
1"
#3340000
0"
b101001100 '
#3345000
b1001100 &
1"
#3350000
0"
b101001101 '
#3355000
b1001101 &
1"
#3360000
0"
b101001110 '
#3365000
b1001110 &
1"
#3370000
0"
b101001111 '
#3375000
b1001111 &
1"
#3380000
0"
b101010000 '
#3385000
b1010000 &
1"
#3390000
0"
b101010001 '
#3395000
b1010001 &
1"
#3400000
0"
b101010010 '
#3405000
b1010010 &
1"
#3410000
0"
b101010011 '
#3415000
b1010011 &
1"
#3420000
0"
b101010100 '
#3425000
b1010100 &
1"
#3430000
0"
b101010101 '
#3435000
b1010101 &
1"
#3440000
0"
b101010110 '
#3445000
b1010110 &
1"
#3450000
0"
b101010111 '
#3455000
b1010111 &
1"
#3460000
0"
b101011000 '
#3465000
b1011000 &
1"
#3470000
0"
b101011001 '
#3475000
b1011001 &
1"
#3480000
0"
b101011010 '
#3485000
b1011010 &
1"
#3490000
0"
b101011011 '
#3495000
b1011011 &
1"
#3500000
0"
b101011100 '
#3505000
b1011100 &
1"
#3510000
0"
b101011101 '
#3515000
b1011101 &
1"
#3520000
0"
b101011110 '
#3525000
b1011110 &
1"
#3530000
0"
b101011111 '
#3535000
b1011111 &
1"
#3540000
0"
b101100000 '
#3545000
b1100000 &
1"
#3550000
0"
b101100001 '
#3555000
b1100001 &
1"
#3560000
0"
b101100010 '
#3565000
b1100010 &
1"
#3570000
0"
b101100011 '
#3575000
b1100011 &
1"
#3580000
0"
b101100100 '
#3585000
b1100100 &
1"
#3590000
0"
b101100101 '
#3595000
b1100101 &
1"
#3600000
0"
b101100110 '
#3605000
b1100110 &
1"
#3610000
0"
b101100111 '
#3615000
b1100111 &
1"
#3620000
0"
b101101000 '
#3625000
b1101000 &
1"
#3630000
0"
b101101001 '
#3635000
b1101001 &
1"
#3640000
0"
b101101010 '
#3645000
b1101010 &
1"
#3650000
0"
b101101011 '
#3655000
b1101011 &
1"
#3660000
0"
b101101100 '
#3665000
b1101100 &
1"
#3670000
0"
b101101101 '
#3675000
b1101101 &
1"
#3680000
0"
b101101110 '
#3685000
b1101110 &
1"
#3690000
0"
b101101111 '
#3695000
b1101111 &
1"
#3700000
0"
b101110000 '
#3705000
b1110000 &
1"
#3710000
0"
b101110001 '
#3715000
b1110001 &
1"
#3720000
0"
b101110010 '
#3725000
b1110010 &
1"
#3730000
0"
b101110011 '
#3735000
b1110011 &
1"
#3740000
0"
b101110100 '
#3745000
b1110100 &
1"
#3750000
0"
b101110101 '
#3755000
b1110101 &
1"
#3760000
0"
b101110110 '
#3765000
b1110110 &
1"
#3770000
0"
b101110111 '
#3775000
b1110111 &
1"
#3780000
0"
b101111000 '
#3785000
b1111000 &
1"
#3790000
0"
b101111001 '
#3795000
b1111001 &
1"
#3800000
0"
b101111010 '
#3805000
b1111010 &
1"
#3810000
0"
b101111011 '
#3815000
b1111011 &
1"
#3820000
0"
b101111100 '
#3825000
b1111100 &
1"
#3830000
0"
b101111101 '
#3835000
b1111101 &
1"
#3840000
0"
b101111110 '
#3845000
b1111110 &
1"
#3850000
0"
b101111111 '
#3855000
b1111111 &
1"
#3860000
0"
b110000000 '
#3865000
b10000000 &
1"
#3870000
0"
b110000001 '
#3875000
b10000001 &
1"
#3880000
0"
b110000010 '
#3885000
b10000010 &
1"
#3890000
0"
b110000011 '
#3895000
b10000011 &
1"
#3900000
0"
b110000100 '
#3905000
b10000100 &
1"
#3910000
0"
b110000101 '
#3915000
b10000101 &
1"
#3920000
0"
b110000110 '
#3925000
b10000110 &
1"
#3930000
0"
b110000111 '
#3935000
b10000111 &
1"
#3940000
0"
b110001000 '
#3945000
b10001000 &
1"
#3950000
0"
b110001001 '
#3955000
b10001001 &
1"
#3960000
0"
b110001010 '
#3965000
b10001010 &
1"
#3970000
0"
b110001011 '
#3975000
b10001011 &
1"
#3980000
0"
b110001100 '
#3985000
b10001100 &
1"
#3990000
0"
b110001101 '
#3995000
b10001101 &
1"
#4000000
0"
b110001110 '
#4005000
b10001110 &
1"
#4010000
0"
b110001111 '
#4015000
b10001111 &
1"
#4020000
0"
b110010000 '
#4025000
b10010000 &
1"
#4030000
0"
b110010001 '
#4035000
b10010001 &
1"
#4040000
0"
b110010010 '
#4045000
b10010010 &
1"
#4050000
0"
b110010011 '
#4055000
b10010011 &
1"
#4060000
0"
b110010100 '
#4065000
b10010100 &
1"
#4070000
0"
b110010101 '
#4075000
b10010101 &
1"
#4080000
0"
b110010110 '
#4085000
b10010110 &
1"
#4090000
0"
b110010111 '
#4095000
b10010111 &
1"
#4100000
0"
b110011000 '
#4105000
b10011000 &
1"
#4110000
0"
b110011001 '
#4115000
b10011001 &
1"
#4120000
0"
b110011010 '
#4125000
b10011010 &
1"
#4130000
0"
b110011011 '
#4135000
b10011011 &
1"
#4140000
0"
b110011100 '
#4145000
b10011100 &
1"
#4150000
0"
b110011101 '
#4155000
1!
b10011101 &
1"
#4160000
0"
b110011110 '
#4165000
b10011110 &
1"
#4170000
0"
b110011111 '
#4175000
b10011111 &
1"
#4180000
0"
b110100000 '
#4185000
b10100000 &
1"
#4190000
0"
b110100001 '
#4195000
b10100001 &
1"
#4200000
0"
b110100010 '
#4205000
b10100010 &
1"
#4210000
0"
b110100011 '
#4215000
b10100011 &
1"
#4220000
0"
b110100100 '
#4225000
b10100100 &
1"
#4230000
0"
b110100101 '
#4235000
b10100101 &
1"
#4240000
0"
b110100110 '
#4245000
b10100110 &
1"
#4250000
0"
b110100111 '
#4255000
b10100111 &
1"
#4260000
0"
b110101000 '
#4265000
b10101000 &
1"
#4270000
0"
b110101001 '
#4275000
b10101001 &
1"
#4280000
0"
b110101010 '
#4285000
b10101010 &
1"
#4290000
0"
b110101011 '
#4295000
b10101011 &
1"
#4300000
0"
b110101100 '
#4305000
b10101100 &
1"
#4310000
0"
b110101101 '
#4315000
b10101101 &
1"
#4320000
0"
b110101110 '
#4325000
b10101110 &
1"
#4330000
0"
b110101111 '
#4335000
b10101111 &
1"
#4340000
0"
b110110000 '
#4345000
b10110000 &
1"
#4350000
0"
b110110001 '
#4355000
b10110001 &
1"
#4360000
0"
b110110010 '
#4365000
b10110010 &
1"
#4370000
0"
b110110011 '
#4375000
b10110011 &
1"
#4380000
0"
b110110100 '
#4385000
b10110100 &
1"
#4390000
0"
b110110101 '
#4395000
b10110101 &
1"
#4400000
0"
b110110110 '
#4405000
b10110110 &
1"
#4410000
0"
b110110111 '
#4415000
b10110111 &
1"
#4420000
0"
b110111000 '
#4425000
b10111000 &
1"
#4430000
0"
b110111001 '
#4435000
b10111001 &
1"
#4440000
0"
b110111010 '
#4445000
b10111010 &
1"
#4450000
0"
b110111011 '
#4455000
b10111011 &
1"
#4460000
0"
b110111100 '
#4465000
b10111100 &
1"
#4470000
0"
b110111101 '
#4475000
b10111101 &
1"
#4480000
0"
b110111110 '
#4485000
b10111110 &
1"
#4490000
0"
b110111111 '
#4495000
b10111111 &
1"
#4500000
0"
b111000000 '
#4505000
b11000000 &
1"
#4510000
0"
b111000001 '
#4515000
b11000001 &
1"
#4520000
0"
b111000010 '
#4525000
b11000010 &
1"
#4530000
0"
b111000011 '
#4535000
b11000011 &
1"
#4540000
0"
b111000100 '
#4545000
b11000100 &
1"
#4550000
0"
b111000101 '
#4555000
b11000101 &
1"
#4560000
0"
b111000110 '
#4565000
b11000110 &
1"
#4570000
0"
b111000111 '
#4575000
b11000111 &
1"
#4580000
0"
b111001000 '
#4585000
b11001000 &
1"
#4590000
0"
b111001001 '
#4595000
b11001001 &
1"
#4600000
0"
b111001010 '
#4605000
b11001010 &
1"
#4610000
0"
b111001011 '
#4615000
b11001011 &
1"
#4620000
0"
b111001100 '
#4625000
b11001100 &
1"
#4630000
0"
b111001101 '
#4635000
b11001101 &
1"
#4640000
0"
b111001110 '
#4645000
b11001110 &
1"
#4650000
0"
b111001111 '
#4655000
b11001111 &
1"
#4660000
0"
b111010000 '
#4665000
b11010000 &
1"
#4670000
0"
b111010001 '
#4675000
b11010001 &
1"
#4680000
0"
b111010010 '
#4685000
b11010010 &
1"
#4690000
0"
b111010011 '
#4695000
b11010011 &
1"
#4700000
0"
b111010100 '
#4705000
b11010100 &
1"
#4710000
0"
b111010101 '
#4715000
b11010101 &
1"
