Archives/Week 2/lab02/hdl/spi_rx.sv
`timescale 1ns / 1ps
`default_nettype none // prevents system from inferring an undeclared logic (good practice)
module spi_rx
       #(  parameter DATA_WIDTH = 8
        )
        ( input wire clk_in,
          input wire rst_in,
          input wire data_in,
          input wire data_clk_in,
          input wire sel_in,
          output logic [DATA_WIDTH-1:0] data_out,
          output logic new_data_out
        );
  //your code here
  logic [31:0] counter;
  logic old_click;
  always_ff @(posedge clk_in)begin
    old_click <= data_clk_in;
    if (rst_in == 1)begin
        new_data_out <= 0;
        data_out <= 0;
        counter <= 0;
    end else begin
        new_data_out <= 0;
        if (sel_in == 1)begin
            data_out <= 0;
        end else begin
            if (counter < DATA_WIDTH) begin
                if (data_clk_in == 1)begin
                    if (old_click == 0) begin
                        data_out <= {data_out[DATA_WIDTH-2:0] , data_in};  
                        counter <= counter + 1;      
                        end 
                end 
            end else begin
                        new_data_out <= 1;
                        counter <= 0;
                end
            end
            end                                                      
        end

endmodule
`default_nettype wire // prevents system from inferring an undeclared logic (good practice)

Archives/Week 2/lab02/sim/spi_rx_tb.sv
`timescale 1ns / 1ps
`default_nettype none


module spi_rx_tb();
  localparam DATA_WIDTH = 16;

  logic clk_in;
  logic rst_in;
  logic [15:0] data_in;
  logic trigger_in;

  logic data_out, data_clk_out, sel_out;

  logic new_data_out;

  logic [DATA_WIDTH-1:0] rx_out;

  logic s_data_out;
  logic s_data_clk_out;
  logic s_sel_out;




  //why tf would I rewrite the logic for a SPI transmitter?
  //reuse your working SPI_TX module here to then test your
  //spi rx module
  
  spi_tx #(.DATA_WIDTH(DATA_WIDTH), .DATA_PERIOD(10)) uut
                  ( .clk_in(clk_in), .rst_in(rst_in),
                    .data_in(data_in),
                    .trigger_in(trigger_in),
                    .data_out(data_out),
                    .sel_out(sel_out),
                    .data_clk_out(data_clk_out));
  //run the signals through three synchronizers
  //this isn't needed, but included here to make sure the
  //synchronizers are working correctly.
  synchronizer s1
        ( .clk_in(clk_in),
          .rst_in(rst_in),
          .us_in(data_out),
          .s_out(s_data_out));
  synchronizer s2
        ( .clk_in(clk_in),
          .rst_in(rst_in),
          .us_in(data_clk_out),
          .s_out(s_data_clk_out));
  synchronizer s3
        ( .clk_in(clk_in),
          .rst_in(rst_in),
          .us_in(sel_out),
          .s_out(s_sel_out));
  // SPI_RX.
  spi_rx #(.DATA_WIDTH(DATA_WIDTH)) uut2
                  ( .clk_in(clk_in), .rst_in(rst_in),
                    .data_clk_in(s_data_clk_out),
                    .data_in(s_data_out),
                    .sel_in(s_sel_out),
                    .data_out(rx_out),
                    .new_data_out(new_data_out));

  always begin
      #5;  //every 5 ns switch...so period of clock is 10 ns...100 MHz clock
      clk_in = !clk_in;
  end
  //initial block...this is our test simulation
  initial begin
    $dumpfile("spi.vcd"); //file to store value change dump (vcd)
    $dumpvars(0,spi_rx_tb);
    $display("Starting Sim"); //print nice message at start
    clk_in = 0;
    rst_in = 0;
    trigger_in = 0;
    data_in = 16'hBEEF; //16 long message, 2-wide bit duration
    #10;
    rst_in = 1;
    #10;
    rst_in = 0;
    #500;
    trigger_in = 1;
    #10;
    trigger_in = 0;
    $display("data_in = %16b ",data_in);
    $display("trig data clk");
    for(int i=0; i<300; i=i+1)begin
      $display("%b   %b    %b",trigger_in, data_out, data_clk_out);
      #10;
    end
    data_in = 16'hFEED;
    trigger_in = 1;
    #10;
    trigger_in = 0;
    $display("trig data clk");
    for(int i=0; i<300; i=i+1)begin
      $display("%b   %b    %b",trigger_in, data_out, data_clk_out);
      #10;
    end
    $display("Finishing Sim"); //print nice message at end
    $finish;
  end
endmodule
module  synchronizer #(parameter SYNC_DEPTH = 2
                    ) (   input wire clk_in,
                          input wire rst_in,
                          input wire us_in, //unsync_in
                          output logic s_out); //sync_out

  logic [SYNC_DEPTH-1:0] sync;

  always_ff @(posedge clk_in)begin
    if (rst_in)begin
      sync <= {(SYNC_DEPTH){us_in}};
    end else begin
      sync[SYNC_DEPTH-1] <= us_in;
      for (int i=1; i<SYNC_DEPTH; i= i+1)begin
        sync[i-1] <= sync[i];
      end
    end
  end
  assign s_out = sync[0];
endmodule
module spi_tx
       #(   parameter DATA_WIDTH = 8,
            parameter DATA_PERIOD = 100
        )
        ( input wire clk_in,
          input wire rst_in,
          input wire [DATA_WIDTH-1:0] data_in,
          input wire trigger_in,
          output logic data_out,
          output logic data_clk_out,
          output logic sel_out
        );
  logic mode;
  localparam PERIOD = (DATA_PERIOD % 2 == 1) ? (DATA_PERIOD - 1): DATA_PERIOD;
  logic[31:0] count;
  logic[31:0] clock_counter;
  logic [DATA_WIDTH-1:0] data_buffer;
  always_ff @(posedge clk_in)begin
    if (rst_in == 1) begin
        sel_out <= 1;
        data_clk_out <= 0;
        data_out <= 0;
        mode <= 0;
        count <= 1;
        clock_counter <= 1;
        data_buffer <= 0;
        // Add any other variables that you are using in here 
    end else begin
        // All my jazz here
        if (mode == 1)begin
            clock_counter <= clock_counter + 1;
            if (count <= DATA_WIDTH)begin
                sel_out <= 0;
                if (clock_counter % (((PERIOD)/2)) == 0)begin
                  if (data_clk_out == 1)begin
                        count <= count + 1;
                        data_out <= data_buffer[DATA_WIDTH - 1 - count];
                        data_clk_out <= 0;
                    end else begin
                        data_clk_out <= 1;
                    end
                end 
            end else begin
                mode <= 0;
                data_out <= 0;
                count <= 1;
                sel_out <= 1;
            end
        end else begin
            if (trigger_in == 1)begin
                data_buffer <= data_in;
                sel_out <= 0;
                mode <= 1;
                count <= 1;
                data_out <= data_in[DATA_WIDTH-1];
            end else begin
                sel_out <= 1;
            end
        end 
    end
   end
endmodule
`default_nettype wire

Archives/Week 2/lab02/spi.vcd
$date
	Wed Sep 20 22:39:42 2023
$end
$version
	Icarus Verilog
$end
$timescale
	1ps
$end
$scope module spi_rx_tb $end
$var wire 1 ! sel_out $end
$var wire 1 " s_sel_out $end
$var wire 1 # s_data_out $end
$var wire 1 $ s_data_clk_out $end
$var wire 16 % rx_out [15:0] $end
$var wire 1 & new_data_out $end
$var wire 1 ' data_out $end
$var wire 1 ( data_clk_out $end
$var parameter 32 ) DATA_WIDTH $end
$var reg 1 * clk_in $end
$var reg 16 + data_in [15:0] $end
$var reg 1 , rst_in $end
$var reg 1 - trigger_in $end
$scope module s1 $end
$var wire 1 * clk_in $end
$var wire 1 , rst_in $end
$var wire 1 ' us_in $end
$var wire 1 # s_out $end
$var parameter 32 . SYNC_DEPTH $end
$var reg 2 / sync [1:0] $end
$scope begin $ivl_for_loop2 $end
$var integer 32 0 i [31:0] $end
$upscope $end
$upscope $end
$scope module s2 $end
$var wire 1 * clk_in $end
$var wire 1 , rst_in $end
$var wire 1 ( us_in $end
$var wire 1 $ s_out $end
$var parameter 32 1 SYNC_DEPTH $end
$var reg 2 2 sync [1:0] $end
$scope begin $ivl_for_loop2 $end
$var integer 32 3 i [31:0] $end
$upscope $end
$upscope $end
$scope module s3 $end
$var wire 1 * clk_in $end
$var wire 1 , rst_in $end
$var wire 1 ! us_in $end
$var wire 1 " s_out $end
$var parameter 32 4 SYNC_DEPTH $end
$var reg 2 5 sync [1:0] $end
$scope begin $ivl_for_loop2 $end
$var integer 32 6 i [31:0] $end
$upscope $end
$upscope $end
$scope module uut $end
$var wire 1 * clk_in $end
$var wire 16 7 data_in [15:0] $end
$var wire 1 , rst_in $end
$var wire 1 - trigger_in $end
$var parameter 32 8 DATA_PERIOD $end
$var parameter 32 9 DATA_WIDTH $end
$var parameter 33 : PERIOD $end
$var reg 32 ; clock_counter [31:0] $end
$var reg 32 < count [31:0] $end
$var reg 16 = data_buffer [15:0] $end
$var reg 1 ( data_clk_out $end
$var reg 1 ' data_out $end
$var reg 1 > mode $end
$var reg 1 ! sel_out $end
$upscope $end
$scope module uut2 $end
$var wire 1 * clk_in $end
$var wire 1 $ data_clk_in $end
$var wire 1 # data_in $end
$var wire 1 , rst_in $end
$var wire 1 " sel_in $end
$var parameter 32 ? DATA_WIDTH $end
$var reg 32 @ counter [31:0] $end
$var reg 16 A data_out [15:0] $end
$var reg 1 & new_data_out $end
$var reg 1 B old_click $end
$upscope $end
$scope begin $ivl_for_loop0 $end
$var integer 32 C i [31:0] $end
$upscope $end
$scope begin $ivl_for_loop1 $end
$var integer 32 D i [31:0] $end
$upscope $end
$upscope $end
$enddefinitions $end
$comment Show the parameter values. $end
$dumpall
b10000 ?
b1010 :
b10000 9
b1010 8
b10 4
b10 1
b10 .
b10000 )
$end
#0
$dumpvars
b0 D
b0 C
xB
bx A
bx @
x>
bx =
bx <
bx ;
b1011111011101111 7
b0 6
bx 5
b0 3
bx 2
b0 0
bx /
0-
0,
b1011111011101111 +
0*
x(
x'
x&
bx %
x$
x#
x"
x!
$end
#5000
1!
b0 @
1&
b10 6
b10 3
b10 0
1*
#10000
0*
1,
#15000
1"
b0 %
b0 A
0&
b0 =
b1 ;
b1 <
0>
0'
0(
b11 5
1*
#20000
0*
0,
#25000
b0x 2
b0x /
b10 0
b10 3
b10 6
1*
#30000
0*
#35000
0#
0$
b0 /
b0 2
b10 0
b10 3
b10 6
1*
#40000
0*
#45000
0B
b10 0
b10 3
b10 6
1*
#50000
0*
#55000
b10 0
b10 3
b10 6
1*
#60000
0*
#65000
b10 0
b10 3
b10 6
1*
#70000
0*
#75000
b10 0
b10 3
b10 6
1*
#80000
0*
#85000
b10 0
b10 3
b10 6
1*
#90000
0*
#95000
b10 0
b10 3
b10 6
1*
#100000
0*
#105000
b10 0
b10 3
b10 6
1*
#110000
0*
#115000
b10 0
b10 3
b10 6
1*
#120000
0*
#125000
b10 0
b10 3
b10 6
1*
#130000
0*
#135000
b10 0
b10 3
b10 6
1*
#140000
0*
#145000
b10 0
b10 3
b10 6
1*
#150000
0*
#155000
b10 0
b10 3
b10 6
1*
#160000
0*
#165000
b10 0
b10 3
b10 6
1*
#170000
0*
#175000
b10 0
b10 3
b10 6
1*
#180000
0*
#185000
b10 0
b10 3
b10 6
1*
#190000
0*
#195000
b10 0
b10 3
b10 6
1*
#200000
0*
#205000
b10 0
b10 3
b10 6
1*
#210000
0*
#215000
b10 0
b10 3
b10 6
1*
#220000
0*
#225000
b10 0
b10 3
b10 6
1*
#230000
0*
#235000
b10 0
b10 3
b10 6
1*
#240000
0*
#245000
b10 0
b10 3
b10 6
1*
#250000
0*
#255000
b10 0
b10 3
b10 6
1*
#260000
0*
#265000
b10 0
b10 3
b10 6
1*
#270000
0*
#275000
b10 0
b10 3
b10 6
1*
#280000
0*
#285000
b10 0
b10 3
b10 6
1*
#290000
0*
#295000
b10 0
b10 3
b10 6
1*
#300000
0*
#305000
b10 0
b10 3
b10 6
1*
#310000
0*
#315000
b10 0
b10 3
b10 6
1*
#320000
0*
#325000
b10 0
b10 3
b10 6
1*
#330000
0*
#335000
b10 0
b10 3
b10 6
1*
#340000
0*
#345000
b10 0
b10 3
b10 6
1*
#350000
0*
#355000
b10 0
b10 3
b10 6
1*
#360000
0*
#365000
b10 0
b10 3
b10 6
1*
#370000
0*
#375000
b10 0
b10 3
b10 6
1*
#380000
0*
#385000
b10 0
b10 3
b10 6
1*
#390000
0*
#395000
b10 0
b10 3
b10 6
1*
#400000
0*
#405000
b10 0
b10 3
b10 6
1*
#410000
0*
#415000
b10 0
b10 3
b10 6
1*
#420000
0*
#425000
b10 0
b10 3
b10 6
1*
#430000
0*
#435000
b10 0
b10 3
b10 6
1*
#440000
0*
#445000
b10 0
b10 3
b10 6
1*
#450000
0*
#455000
b10 0
b10 3
b10 6
1*
#460000
0*
#465000
b10 0
b10 3
b10 6
1*
#470000
0*
#475000
b10 0
b10 3
b10 6
1*
#480000
0*
#485000
b10 0
b10 3
b10 6
1*
#490000
0*
#495000
b10 0
b10 3
b10 6
1*
#500000
0*
#505000
b10 0
b10 3
b10 6
1*
#510000
0*
#515000
b10 0
b10 3
b10 6
1*
#520000
0*
1-
#525000
1'
1>
0!
b1011111011101111 =
b10 0
b10 3
b10 6
1*
#530000
0*
0-
#535000
b10 ;
b1 5
b10 /
b10 0
b10 3
b10 6
1*
#540000
0*
b1 C
#545000
1#
0"
b11 /
b0 5
b11 ;
b10 0
b10 3
b10 6
1*
#550000
0*
b10 C
#555000
b100 ;
b10 0
b10 3
b10 6
1*
#560000
0*
b11 C
#565000
b101 ;
b10 0
b10 3
b10 6
1*
#570000
0*
b100 C
#575000
1(
b110 ;
b10 0
b10 3
b10 6
1*
#580000
0*
b101 C
#585000
b111 ;
b10 2
b10 0
b10 3
b10 6
1*
#590000
0*
b110 C
#595000
1$
b11 2
b1000 ;
b10 0
b10 3
b10 6
1*
#600000
0*
b111 C
#605000
b1001 ;
b1 @
b1 %
b1 A
1B
b10 0
b10 3
b10 6
1*
#610000
0*
b1000 C
#615000
b1010 ;
b10 0
b10 3
b10 6
1*
#620000
0*
b1001 C
#625000
0(
0'
b10 <
b1011 ;
b10 0
b10 3
b10 6
1*
#630000
0*
b1010 C
#635000
b1100 ;
b1 2
b1 /
b10 0
b10 3
b10 6
1*
#640000
0*
b1011 C
#645000
0#
0$
b0 /
b0 2
b1101 ;
b10 0
b10 3
b10 6
1*
#650000
0*
b1100 C
#655000
0B
b1110 ;
b10 0
b10 3
b10 6
1*
#660000
0*
b1101 C
#665000
b1111 ;
b10 0
b10 3
b10 6
1*
#670000
0*
b1110 C
#675000
1(
b10000 ;
b10 0
b10 3
b10 6
1*
#680000
0*
b1111 C
#685000
b10001 ;
b10 2
b10 0
b10 3
b10 6
1*
#690000
0*
b10000 C
#695000
1$
b11 2
b10010 ;
b10 0
b10 3
b10 6
1*
#700000
0*
b10001 C
#705000
b10011 ;
b10 @
b10 %
b10 A
1B
b10 0
b10 3
b10 6
1*
#710000
0*
b10010 C
#715000
b10100 ;
b10 0
b10 3
b10 6
1*
#720000
0*
b10011 C
#725000
0(
1'
b11 <
b10101 ;
b10 0
b10 3
b10 6
1*
#730000
0*
b10100 C
#735000
b10110 ;
b1 2
b10 /
b10 0
b10 3
b10 6
1*
#740000
0*
b10101 C
#745000
1#
0$
b11 /
b0 2
b10111 ;
b10 0
b10 3
b10 6
1*
#750000
0*
b10110 C
#755000
0B
b11000 ;
b10 0
b10 3
b10 6
1*
#760000
0*
b10111 C
#765000
b11001 ;
b10 0
b10 3
b10 6
1*
#770000
0*
b11000 C
#775000
1(
b11010 ;
b10 0
b10 3
b10 6
1*
#780000
0*
b11001 C
#785000
b11011 ;
b10 2
b10 0
b10 3
b10 6
1*
#790000
0*
b11010 C
#795000
1$
b11 2
b11100 ;
b10 0
b10 3
b10 6
1*
#800000
0*
b11011 C
#805000
b11101 ;
b11 @
b101 %
b101 A
1B
b10 0
b10 3
b10 6
1*
#810000
0*
b11100 C
#815000
b11110 ;
b10 0
b10 3
b10 6
1*
#820000
0*
b11101 C
#825000
0(
b100 <
b11111 ;
b10 0
b10 3
b10 6
1*
#830000
0*
b11110 C
#835000
b100000 ;
b1 2
b10 0
b10 3
b10 6
1*
#840000
0*
b11111 C
#845000
0$
b0 2
b100001 ;
b10 0
b10 3
b10 6
1*
#850000
0*
b100000 C
#855000
0B
b100010 ;
b10 0
b10 3
b10 6
1*
#860000
0*
b100001 C
#865000
b100011 ;
b10 0
b10 3
b10 6
1*
#870000
0*
b100010 C
#875000
1(
b100100 ;
b10 0
b10 3
b10 6
1*
#880000
0*
b100011 C
#885000
b100101 ;
b10 2
b10 0
b10 3
b10 6
1*
#890000
0*
b100100 C
#895000
1$
b11 2
b100110 ;
b10 0
b10 3
b10 6
1*
#900000
0*
b100101 C
#905000
b100111 ;
b100 @
b1011 %
b1011 A
1B
b10 0
b10 3
b10 6
1*
#910000
0*
b100110 C
#915000
b101000 ;
b10 0
b10 3
b10 6
1*
#920000
0*
b100111 C
#925000
0(
b101 <
b101001 ;
b10 0
b10 3
b10 6
1*
#930000
0*
b101000 C
#935000
b101010 ;
b1 2
b10 0
b10 3
b10 6
1*
#940000
0*
b101001 C
#945000
0$
b0 2
b101011 ;
b10 0
b10 3
b10 6
1*
#950000
0*
b101010 C
#955000
0B
b101100 ;
b10 0
b10 3
b10 6
1*
#960000
0*
b101011 C
#965000
b101101 ;
b10 0
b10 3
b10 6
1*
#970000
0*
b101100 C
#975000
1(
b101110 ;
b10 0
b10 3
b10 6
1*
#980000
0*
b101101 C
#985000
b101111 ;
b10 2
b10 0
b10 3
b10 6
1*
#990000
0*
b101110 C
#995000
1$
b11 2
b110000 ;
b10 0
b10 3
b10 6
1*
#1000000
0*
b101111 C
#1005000
b110001 ;
b101 @
b10111 %
b10111 A
1B
b10 0
b10 3
b10 6
1*
#1010000
0*
b110000 C
#1015000
b110010 ;
b10 0
b10 3
b10 6
1*
#1020000
0*
b110001 C
#1025000
0(
b110 <
b110011 ;
b10 0
b10 3
b10 6
1*
#1030000
0*
b110010 C
#1035000
b110100 ;
b1 2
b10 0
b10 3
b10 6
1*
#1040000
0*
b110011 C
#1045000
0$
b0 2
b110101 ;
b10 0
b10 3
b10 6
1*
#1050000
0*
b110100 C
#1055000
0B
b110110 ;
b10 0
b10 3
b10 6
1*
#1060000
0*
b110101 C
#1065000
b110111 ;
b10 0
b10 3
b10 6
1*
#1070000
0*
b110110 C
#1075000
1(
b111000 ;
b10 0
b10 3
b10 6
1*
#1080000
0*
b110111 C
#1085000
b111001 ;
b10 2
b10 0
b10 3
b10 6
1*
#1090000
0*
b111000 C
#1095000
1$
b11 2
b111010 ;
b10 0
b10 3
b10 6
1*
#1100000
0*
b111001 C
#1105000
b111011 ;
b110 @
b101111 %
b101111 A
1B
b10 0
b10 3
b10 6
1*
#1110000
0*
b111010 C
#1115000
b111100 ;
b10 0
b10 3
b10 6
1*
#1120000
0*
b111011 C
#1125000
0(
b111 <
b111101 ;
b10 0
b10 3
b10 6
1*
#1130000
0*
b111100 C
#1135000
b111110 ;
b1 2
b10 0
b10 3
b10 6
1*
#1140000
0*
b111101 C
#1145000
0$
b0 2
b111111 ;
b10 0
b10 3
b10 6
1*
#1150000
0*
b111110 C
#1155000
0B
b1000000 ;
b10 0
b10 3
b10 6
1*
#1160000
0*
b111111 C
#1165000
b1000001 ;
b10 0
b10 3
b10 6
1*
#1170000
0*
b1000000 C
#1175000
1(
b1000010 ;
b10 0
b10 3
b10 6
1*
#1180000
0*
b1000001 C
#1185000
b1000011 ;
b10 2
b10 0
b10 3
b10 6
1*
#1190000
0*
b1000010 C
#1195000
1$
b11 2
b1000100 ;
b10 0
b10 3
b10 6
1*
#1200000
0*
b1000011 C
#1205000
b1000101 ;
b111 @
b1011111 %
b1011111 A
1B
b10 0
b10 3
b10 6
1*
#1210000
0*
b1000100 C
#1215000
b1000110 ;
b10 0
b10 3
b10 6
1*
#1220000
0*
b1000101 C
#1225000
0(
0'
b1000 <
b1000111 ;
b10 0
b10 3
b10 6
1*
#1230000
0*
b1000110 C
#1235000
b1001000 ;
b1 2
b1 /
b10 0
b10 3
b10 6
1*
#1240000
0*
b1000111 C
#1245000
0#
0$
b0 /
b0 2
b1001001 ;
b10 0
b10 3
b10 6
1*
#1250000
0*
b1001000 C
#1255000
0B
b1001010 ;
b10 0
b10 3
b10 6
1*
#1260000
0*
b1001001 C
#1265000
b1001011 ;
b10 0
b10 3
b10 6
1*
#1270000
0*
b1001010 C
#1275000
1(
b1001100 ;
b10 0
b10 3
b10 6
1*
#1280000
0*
b1001011 C
#1285000
b1001101 ;
b10 2
b10 0
b10 3
b10 6
1*
#1290000
0*
b1001100 C
#1295000
1$
b11 2
b1001110 ;
b10 0
b10 3
b10 6
1*
#1300000
0*
b1001101 C
#1305000
b1001111 ;
b1000 @
b10111110 %
b10111110 A
1B
b10 0
b10 3
b10 6
1*
#1310000
0*
b1001110 C
#1315000
b1010000 ;
b10 0
b10 3
b10 6
1*
#1320000
0*
b1001111 C
#1325000
0(
1'
b1001 <
b1010001 ;
b10 0
b10 3
b10 6
1*
#1330000
0*
b1010000 C
#1335000
b1010010 ;
b1 2
b10 /
b10 0
b10 3
b10 6
1*
#1340000
0*
b1010001 C
#1345000
1#
0$
b11 /
b0 2
b1010011 ;
b10 0
b10 3
b10 6
1*
#1350000
0*
b1010010 C
#1355000
0B
b1010100 ;
b10 0
b10 3
b10 6
1*
#1360000
0*
b1010011 C
#1365000
b1010101 ;
b10 0
b10 3
b10 6
1*
#1370000
0*
b1010100 C
#1375000
1(
b1010110 ;
b10 0
b10 3
b10 6
1*
#1380000
0*
b1010101 C
#1385000
b1010111 ;
b10 2
b10 0
b10 3
b10 6
1*
#1390000
0*
b1010110 C
#1395000
1$
b11 2
b1011000 ;
b10 0
b10 3
b10 6
1*
#1400000
0*
b1010111 C
#1405000
b1011001 ;
b1001 @
b101111101 %
b101111101 A
1B
b10 0
b10 3
b10 6
1*
#1410000
0*
b1011000 C
#1415000
b1011010 ;
b10 0
b10 3
b10 6
1*
#1420000
0*
b1011001 C
#1425000
0(
b1010 <
b1011011 ;
b10 0
b10 3
b10 6
1*
#1430000
0*
b1011010 C
#1435000
b1011100 ;
b1 2
b10 0
b10 3
b10 6
1*
#1440000
0*
b1011011 C
#1445000
0$
b0 2
b1011101 ;
b10 0
b10 3
b10 6
1*
#1450000
0*
b1011100 C
#1455000
0B
b1011110 ;
b10 0
b10 3
b10 6
1*
#1460000
0*
b1011101 C
#1465000
b1011111 ;
b10 0
b10 3
b10 6
1*
#1470000
0*
b1011110 C
#1475000
1(
b1100000 ;
b10 0
b10 3
b10 6
1*
#1480000
0*
b1011111 C
#1485000
b1100001 ;
b10 2
b10 0
b10 3
b10 6
1*
#1490000
0*
b1100000 C
#1495000
1$
b11 2
b1100010 ;
b10 0
b10 3
b10 6
1*
#1500000
0*
b1100001 C
#1505000
b1100011 ;
b1010 @
b1011111011 %
b1011111011 A
1B
b10 0
b10 3
b10 6
1*
#1510000
0*
b1100010 C
#1515000
b1100100 ;
b10 0
b10 3
b10 6
1*
#1520000
0*
b1100011 C
#1525000
0(
b1011 <
b1100101 ;
b10 0
b10 3
b10 6
1*
#1530000
0*
b1100100 C
#1535000
b1100110 ;
b1 2
b10 0
b10 3
b10 6
1*
#1540000
0*
b1100101 C
#1545000
0$
b0 2
b1100111 ;
b10 0
b10 3
b10 6
1*
#1550000
0*
b1100110 C
#1555000
0B
b1101000 ;
b10 0
b10 3
b10 6
1*
#1560000
0*
b1100111 C
#1565000
b1101001 ;
b10 0
b10 3
b10 6
1*
#1570000
0*
b1101000 C
#1575000
1(
b1101010 ;
b10 0
b10 3
b10 6
1*
#1580000
0*
b1101001 C
#1585000
b1101011 ;
b10 2
b10 0
b10 3
b10 6
1*
#1590000
0*
b1101010 C
#1595000
1$
b11 2
b1101100 ;
b10 0
b10 3
b10 6
1*
#1600000
0*
b1101011 C
#1605000
b1101101 ;
b1011 @
b10111110111 %
b10111110111 A
1B
b10 0
b10 3
b10 6
1*
#1610000
0*
b1101100 C
#1615000
b1101110 ;
b10 0
b10 3
b10 6
1*
#1620000
0*
b1101101 C
#1625000
0(
0'
b1100 <
b1101111 ;
b10 0
b10 3
b10 6
1*
#1630000
0*
b1101110 C
#1635000
b1110000 ;
b1 2
b1 /
b10 0
b10 3
b10 6
1*
#1640000
0*
b1101111 C
#1645000
0#
0$
b0 /
b0 2
b1110001 ;
b10 0
b10 3
b10 6
1*
#1650000
0*
b1110000 C
#1655000
0B
b1110010 ;
b10 0
b10 3
b10 6
1*
#1660000
0*
b1110001 C
#1665000
b1110011 ;
b10 0
b10 3
b10 6
1*
#1670000
0*
b1110010 C
#1675000
1(
b1110100 ;
b10 0
b10 3
b10 6
1*
#1680000
0*
b1110011 C
#1685000
b1110101 ;
b10 2
b10 0
b10 3
b10 6
1*
#1690000
0*
b1110100 C
#1695000
1$
b11 2
b1110110 ;
b10 0
b10 3
b10 6
1*
#1700000
0*
b1110101 C
#1705000
b1110111 ;
b1100 @
b101111101110 %
b101111101110 A
1B
b10 0
b10 3
b10 6
1*
#1710000
0*
b1110110 C
#1715000
b1111000 ;
b10 0
b10 3
b10 6
1*
#1720000
0*
b1110111 C
#1725000
0(
1'
b1101 <
b1111001 ;
b10 0
b10 3
b10 6
1*
#1730000
0*
b1111000 C
#1735000
b1111010 ;
b1 2
b10 /
b10 0
b10 3
b10 6
1*
#1740000
0*
b1111001 C
#1745000
1#
0$
b11 /
b0 2
b1111011 ;
b10 0
b10 3
b10 6
1*
#1750000
0*
b1111010 C
#1755000
0B
b1111100 ;
b10 0
b10 3
b10 6
1*
#1760000
0*
b1111011 C
#1765000
b1111101 ;
b10 0
b10 3
b10 6
1*
#1770000
0*
b1111100 C
#1775000
1(
b1111110 ;
b10 0
b10 3
b10 6
1*
#1780000
0*
b1111101 C
#1785000
b1111111 ;
b10 2
b10 0
b10 3
b10 6
1*
#1790000
0*
b1111110 C
#1795000
1$
b11 2
b10000000 ;
b10 0
b10 3
b10 6
1*
#1800000
0*
b1111111 C
#1805000
b10000001 ;
b1101 @
b1011111011101 %
b1011111011101 A
1B
b10 0
b10 3
b10 6
1*
#1810000
0*
b10000000 C
#1815000
b10000010 ;
b10 0
b10 3
b10 6
1*
#1820000
0*
b10000001 C
#1825000
0(
b1110 <
b10000011 ;
b10 0
b10 3
b10 6
1*
#1830000
0*
b10000010 C
#1835000
b10000100 ;
b1 2
b10 0
b10 3
b10 6
1*
#1840000
0*
b10000011 C
#1845000
0$
b0 2
b10000101 ;
b10 0
b10 3
b10 6
1*
#1850000
0*
b10000100 C
#1855000
0B
b10000110 ;
b10 0
b10 3
b10 6
1*
#1860000
0*
b10000101 C
#1865000
b10000111 ;
b10 0
b10 3
b10 6
1*
#1870000
0*
b10000110 C
#1875000
1(
b10001000 ;
b10 0
b10 3
b10 6
1*
#1880000
0*
b10000111 C
#1885000
b10001001 ;
b10 2
b10 0
b10 3
b10 6
1*
#1890000
0*
b10001000 C
#1895000
1$
b11 2
b10001010 ;
b10 0
b10 3
b10 6
1*
#1900000
0*
b10001001 C
#1905000
b10001011 ;
b1110 @
b10111110111011 %
b10111110111011 A
1B
b10 0
b10 3
b10 6
1*
#1910000
0*
b10001010 C
#1915000
b10001100 ;
b10 0
b10 3
b10 6
1*
#1920000
0*
b10001011 C
#1925000
0(
b1111 <
b10001101 ;
b10 0
b10 3
b10 6
1*
#1930000
0*
b10001100 C
#1935000
b10001110 ;
b1 2
b10 0
b10 3
b10 6
1*
#1940000
0*
b10001101 C
#1945000
0$
b0 2
b10001111 ;
b10 0
b10 3
b10 6
1*
#1950000
0*
b10001110 C
#1955000
0B
b10010000 ;
b10 0
b10 3
b10 6
1*
#1960000
0*
b10001111 C
#1965000
b10010001 ;
b10 0
b10 3
b10 6
1*
#1970000
0*
b10010000 C
#1975000
1(
b10010010 ;
b10 0
b10 3
b10 6
1*
#1980000
0*
b10010001 C
#1985000
b10010011 ;
b10 2
b10 0
b10 3
b10 6
1*
#1990000
0*
b10010010 C
#1995000
1$
b11 2
b10010100 ;
b10 0
b10 3
b10 6
1*
#2000000
0*
b10010011 C
#2005000
b10010101 ;
b1111 @
b101111101110111 %
b101111101110111 A
1B
b10 0
b10 3
b10 6
1*
#2010000
0*
b10010100 C
#2015000
b10010110 ;
b10 0
b10 3
b10 6
1*
#2020000
0*
b10010101 C
#2025000
0(
b10000 <
b10010111 ;
b10 0
b10 3
b10 6
1*
#2030000
0*
b10010110 C
#2035000
b10011000 ;
b1 2
b10 0
b10 3
b10 6
1*
#2040000
0*
b10010111 C
#2045000
0$
b0 2
b10011001 ;
b10 0
b10 3
b10 6
1*
#2050000
0*
b10011000 C
#2055000
0B
b10011010 ;
b10 0
b10 3
b10 6
1*
#2060000
0*
b10011001 C
#2065000
b10011011 ;
b10 0
b10 3
b10 6
1*
#2070000
0*
b10011010 C
#2075000
1(
b10011100 ;
b10 0
b10 3
b10 6
1*
#2080000
0*
b10011011 C
#2085000
b10011101 ;
b10 2
b10 0
b10 3
b10 6
1*
#2090000
0*
b10011100 C
#2095000
1$
b11 2
b10011110 ;
b10 0
b10 3
b10 6
1*
#2100000
0*
b10011101 C
#2105000
b10011111 ;
b10000 @
b1011111011101111 %
b1011111011101111 A
1B
b10 0
b10 3
b10 6
1*
#2110000
0*
b10011110 C
#2115000
b0 @
1&
b10100000 ;
b10 0
b10 3
b10 6
1*
#2120000
0*
b10011111 C
#2125000
0(
x'
b10001 <
b10100001 ;
0&
b10 0
b10 3
b10 6
1*
#2130000
0*
b10100000 C
#2135000
1!
b1 <
0'
0>
b10100010 ;
b1 2
bx1 /
b10 0
b10 3
b10 6
1*
#2140000
0*
b10100001 C
#2145000
x#
0$
b0 2
b10 5
b0x /
b10 0
b10 3
b10 6
1*
#2150000
0*
b10100010 C
#2155000
0#
1"
b0 /
b11 5
0B
b10 0
b10 3
b10 6
1*
#2160000
0*
b10100011 C
#2165000
b0 %
b0 A
b10 0
b10 3
b10 6
1*
#2170000
0*
b10100100 C
#2175000
b10 0
b10 3
b10 6
1*
#2180000
0*
b10100101 C
#2185000
b10 0
b10 3
b10 6
1*
#2190000
0*
b10100110 C
#2195000
b10 0
b10 3
b10 6
1*
#2200000
0*
b10100111 C
#2205000
b10 0
b10 3
b10 6
1*
#2210000
0*
b10101000 C
#2215000
b10 0
b10 3
b10 6
1*
#2220000
0*
b10101001 C
#2225000
b10 0
b10 3
b10 6
1*
#2230000
0*
b10101010 C
#2235000
b10 0
b10 3
b10 6
1*
#2240000
0*
b10101011 C
#2245000
b10 0
b10 3
b10 6
1*
#2250000
0*
b10101100 C
#2255000
b10 0
b10 3
b10 6
1*
#2260000
0*
b10101101 C
#2265000
b10 0
b10 3
b10 6
1*
#2270000
0*
b10101110 C
#2275000
b10 0
b10 3
b10 6
1*
#2280000
0*
b10101111 C
#2285000
b10 0
b10 3
b10 6
1*
#2290000
0*
b10110000 C
