Archives/Lab 5/hdl/divider.sv
`timescale 1ns / 1ps
`default_nettype none
module divider #(parameter WIDTH = 32) (input wire clk_in,
                input wire rst_in,
                input wire[WIDTH-1:0] dividend_in,
                input wire[WIDTH-1:0] divisor_in,
                input wire data_valid_in,
                output logic[WIDTH-1:0] quotient_out,
                output logic[WIDTH-1:0] remainder_out,
                output logic data_valid_out,
                output logic error_out,
                output logic busy_out);
  localparam RESTING = 0;
  localparam DIVIDING = 1;
  logic [WIDTH-1:0] quotient, dividend;
  logic [WIDTH-1:0] divisor;
  logic state;

  always_ff @(posedge clk_in)begin
    if (rst_in)begin
      quotient <= 0;
      dividend <= 0;
      divisor <= 0;
      remainder_out <= 0;
      busy_out <= 1'b0;
      error_out <= 1'b0;
      state <= RESTING;
      data_valid_out <= 1'b0;
    end else begin
      case (state)
        RESTING: begin
          if (data_valid_in)begin
            state <= DIVIDING;
            quotient <= 0;
            dividend <= dividend_in;
            divisor <= divisor_in;
            busy_out <= 1'b1;
            error_out <= 1'b0;
          end
          data_valid_out <= 1'b0;
        end
        DIVIDING: begin
          if (dividend<=0)begin
            state <= RESTING; //similar to return statement
            remainder_out <= dividend;
            quotient_out <= quotient;
            busy_out <= 1'b0; //tell outside world i'm done
            error_out <= 1'b0;
            data_valid_out <= 1'b1; //good stuff!
          end else if (divisor==0)begin
            state <= RESTING;
            remainder_out <= 0;
            quotient_out <= 0;
            busy_out <= 1'b0; //tell outside world i'm done
            error_out <= 1'b1; //ERROR
            data_valid_out <= 1'b1; //valid ERROR
          end else if (dividend < divisor) begin
            state <= RESTING;
            remainder_out <= dividend;
            quotient_out <= quotient;
            busy_out <= 1'b0;
            error_out <= 1'b0;
            data_valid_out <= 1'b1; //good stuff!
          end else begin
            //state staying in.
            state <= DIVIDING;
            quotient <= quotient + 1'b1;
            dividend <= dividend-divisor;
          end
        end
      endcase
    end
  end
endmodule
`default_nettype wire

hdl/hdmi_hdl/center_of_mass.sv
`timescale 1ns / 1ps
`default_nettype none

module center_of_mass (
                         input wire clk_in,
                         input wire rst_in,
                         input wire [10:0] x_in,
                         input wire [9:0]  y_in,
                         input wire valid_in,
                         input wire tabulate_in,
                         output logic [10:0] x_out,
                         output logic [9:0] y_out,
                         output logic valid_out);

  logic [31:0] x_count;
  logic [31:0] y_count;
  logic [31:0] total;
  logic [10:0] x_int;
  logic [9:0] y_int;
  logic [2:0] x_state;
  logic [2:0] y_state;
  logic [1:0] x_ready;
  logic [1:0] y_ready;
  logic x_fin;
  logic y_fin;
  logic tab;
  
  assign x_ready = x_state[0] == 1 && x_state[1] == 0 && x_state[2] == 0;
  assign y_ready = y_state[0] == 1 && y_state[1] == 0 && y_state[2] == 0;

  divider #(.WIDTH(32)) x_sum (.clk_in(clk_in),
                .rst_in(rst_in),
                .dividend_in(x_count),
                .divisor_in(total),
                .data_valid_in(tab),
                .quotient_out(x_int),
                .data_valid_out(x_state[0]),
                .error_out(x_state[1]),
                .busy_out(x_state[2]));
  divider #(.WIDTH(32)) y_sum (.clk_in(clk_in),
                .rst_in(rst_in),
                .dividend_in(y_count),
                .divisor_in(total),
                .data_valid_in(tab),
                .quotient_out(y_int),
                .data_valid_out(y_state[0]),
                .error_out(y_state[1]),
                .busy_out(y_state[2]));

  always_ff @(posedge clk_in)begin
    valid_out <= 0;
    x_out <= 0;       
    y_out <= 0;
    if (rst_in)begin
      x_out <= 0;
      y_out <= 0;
      x_count <= 0;
      y_count <= 0;
      total <= 0;
      x_fin <= 0;
      y_fin <= 0;
      tab <= 0;
    end else begin
      case(tab)
       1'b0: begin // Not Tabulating
        if(valid_in)begin
          y_count <= y_count + y_in;
          x_count <= x_count + x_in;
          total <= total + 1;
        end if (tabulate_in && (y_count > 0 || x_count > 0))begin
          tab <= 1;
        end
       end
       1'b1: begin // Tabulating
        if (x_count + y_count == 0)begin
          valid_out <= 0;
        end else if (x_fin && y_fin)begin
          valid_out <= 1;
          x_out <= x_int;       
          y_out <= y_int;
          x_count <= 0;
          y_count <= 0;
          x_fin <= 0;
          y_fin <= 0;
          total <= 0; 
          tab <= 0; 
        end else begin      // Check conditions on waveform
          if (x_ready)begin
            x_fin <= 1;
          end if (y_ready)begin
            y_fin <= 1;
          end
        end
       end
      endcase
      end
    end

/*

 always_ff @(posedge clk_in)begin
    valid_out <= 0;
    if (rst_in)begin
      x_out <= 0;
      y_out <= 0;
      x_count <= 0;
      y_count <= 0;
      total <= 0;
    end else begin
      if(valid_in)begin
          y_count <= y_count + y_in;
          x_count <= x_count + x_in;
          total <= total + 1;
        end
      end if (tabulate_in)begin
        if (x_ready[0])begin
          x_ready[1] <= 1;
        end 
        if (y_ready[0])begin
          y_ready[1] <= 1;
        end 
        
        if (x_count + y_count == 0)begin
          valid_out <= 0;
        end else if (x_ready[1] && y_ready[1])begin
          valid_out <= 1;
          x_out <= x_int;       
          y_out <= y_int;
          x_count <= 0;
          y_count <= 0;
          total <= 0;   
          y_ready[1] <= 0;
        end
      end
    end   
    */
endmodule
`default_nettype wire

Archives/Lab 5/sim/com_tb.sv
`timescale 1ns / 1ps
`default_nettype none

module com_tb;

    //make logics for inputs and outputs!
    logic clk_in;
    logic rst_in;
    logic [10:0] x_in;
    logic [9:0] y_in;
    logic valid_in;
    logic tabulate_in;
    logic [10:0] x_out;
    logic [9:0] y_out;
    logic valid_out;

    center_of_mass uut(.clk_in(clk_in), .rst_in(rst_in),
                         .x_in(x_in),
                         .y_in(y_in),
                         .valid_in(valid_in),
                         .tabulate_in(tabulate_in),
                         .x_out(x_out),
                         .y_out(y_out),
                         .valid_out(valid_out));
    always begin
        #5;  //every 5 ns switch...so period of clock is 10 ns...100 MHz clock
        clk_in = !clk_in;
    end

    //initial block...this is our test simulation
    initial begin
        $dumpfile("com.vcd"); //file to store value change dump (vcd)
        $dumpvars(0,com_tb); //store everything at the current level and below
        $display("Starting Sim"); //print nice message
        clk_in = 0; //initialize clk (super important)
        
        rst_in = 0; //initialize rst (super important)
        x_in = 11'b0;
        y_in = 10'b0;
        valid_in = 0;
        tabulate_in = 0;
        #10  //wait a little bit of time at beginning
        rst_in = 1; //reset system
        #10; //hold high for a few clock cycles
        rst_in=0;
        #10;

        for (int i = 0; i<1000; i= i+1)begin
          x_in = i;
          y_in = i/2;
          valid_in = 1;
          #10;
        end
        valid_in = 0;
        #100;
        tabulate_in = 1;
        #10000;
        tabulate_in = 0;
        

        // Case 2
        for (int i = 0; i<500; i= i+1)begin
          x_in = i;
          y_in = i/3;
          valid_in = 1;
          #10;
        end
        valid_in = 0;
        #100;
        tabulate_in = 1;
        #10000;
        tabulate_in = 0;
        
        // Case 3
        for (int i = 0; i<500; i= i+1)begin
          x_in = 0;
          y_in = 0;
          valid_in = 1;
          #10;
        end
        valid_in = 0;
        #100;
        tabulate_in = 1;
        #10000;
        

        

        $display("Finishing Sim"); //print nice message
        $finish;

    end
endmodule //counter_tb

`default_nettype wire

Archives/Lab 5/com.vcd
$date
	Wed Oct 18 21:11:02 2023
$end
$version
	Icarus Verilog
$end
$timescale
	1ps
$end
$scope module com_tb $end
$var wire 10 ! y_out [9:0] $end
$var wire 11 " x_out [10:0] $end
$var wire 1 # valid_out $end
$var reg 1 $ clk_in $end
$var reg 1 % rst_in $end
$var reg 1 & tabulate_in $end
$var reg 1 ' valid_in $end
$var reg 11 ( x_in [10:0] $end
$var reg 10 ) y_in [9:0] $end
$scope module uut $end
$var wire 1 $ clk_in $end
$var wire 1 % rst_in $end
$var wire 1 & tabulate_in $end
$var wire 1 ' valid_in $end
$var wire 11 * x_in [10:0] $end
$var wire 10 + y_in [9:0] $end
$var wire 3 , y_state [2:0] $end
$var wire 2 - y_ready [1:0] $end
$var wire 10 . y_int [9:0] $end
$var wire 3 / x_state [2:0] $end
$var wire 2 0 x_ready [1:0] $end
$var wire 11 1 x_int [10:0] $end
$var reg 1 2 tab $end
$var reg 32 3 total [31:0] $end
$var reg 1 # valid_out $end
$var reg 32 4 x_count [31:0] $end
$var reg 1 5 x_fin $end
$var reg 11 6 x_out [10:0] $end
$var reg 32 7 y_count [31:0] $end
$var reg 1 8 y_fin $end
$var reg 10 9 y_out [9:0] $end
$scope module x_sum $end
$var wire 1 $ clk_in $end
$var wire 1 2 data_valid_in $end
$var wire 32 : dividend_in [31:0] $end
$var wire 32 ; divisor_in [31:0] $end
$var wire 1 % rst_in $end
$var parameter 32 < DIVIDING $end
$var parameter 32 = RESTING $end
$var parameter 32 > WIDTH $end
$var reg 1 ? busy_out $end
$var reg 1 @ data_valid_out $end
$var reg 32 A dividend [31:0] $end
$var reg 32 B divisor [31:0] $end
$var reg 1 C error_out $end
$var reg 32 D quotient [31:0] $end
$var reg 32 E quotient_out [31:0] $end
$var reg 32 F remainder_out [31:0] $end
$var reg 1 G state $end
$upscope $end
$scope module y_sum $end
$var wire 1 $ clk_in $end
$var wire 1 2 data_valid_in $end
$var wire 32 H dividend_in [31:0] $end
$var wire 32 I divisor_in [31:0] $end
$var wire 1 % rst_in $end
$var parameter 32 J DIVIDING $end
$var parameter 32 K RESTING $end
$var parameter 32 L WIDTH $end
$var reg 1 M busy_out $end
$var reg 1 N data_valid_out $end
$var reg 32 O dividend [31:0] $end
$var reg 32 P divisor [31:0] $end
$var reg 1 Q error_out $end
$var reg 32 R quotient [31:0] $end
$var reg 32 S quotient_out [31:0] $end
$var reg 32 T remainder_out [31:0] $end
$var reg 1 U state $end
$upscope $end
$upscope $end
$scope begin $ivl_for_loop0 $end
$var integer 32 V i [31:0] $end
$upscope $end
$scope begin $ivl_for_loop1 $end
$var integer 32 W i [31:0] $end
$upscope $end
$scope begin $ivl_for_loop2 $end
$var integer 32 X i [31:0] $end
$upscope $end
$upscope $end
$enddefinitions $end
$comment Show the parameter values. $end
$dumpall
b100000 L
b0 K
b1 J
b100000 >
b0 =
b1 <
$end
#0
$dumpvars
b0 X
b0 W
b0 V
xU
bx T
bx S
bx R
xQ
bx P
bx O
xN
xM
bx I
bx H
xG
bx F
bx E
bx D
xC
bx B
bx A
x@
x?
bx ;
bx :
bx 9
x8
bx 7
bx 6
x5
bx 4
bx 3
x2
bx 1
b0x 0
bx /
bx .
b0x -
bx ,
b0 +
b0 *
b0 )
b0 (
0'
0&
0%
0$
x#
bx "
bx !
$end
#5000
b0 !
b0 9
b0 "
b0 6
0#
1$
#10000
0$
1%
#15000
b0 -
b0 0
02
08
05
b0 3
b0 ;
b0 I
b0 7
b0 H
b0 4
b0 :
0N
0U
0Q
b0 ,
0M
b0 T
b0 P
b0 O
b0 R
0@
0G
0C
b0 /
0?
b0 F
b0 B
b0 A
b0 D
1$
#20000
0$
0%
#25000
1$
#30000
0$
1'
#35000
b1 3
b1 ;
b1 I
1$
#40000
0$
b1 (
b1 *
b1 V
#45000
b10 3
b10 ;
b10 I
b1 4
b1 :
1$
#50000
0$
b1 )
b1 +
b10 (
b10 *
b10 V
#55000
b11 3
b11 ;
b11 I
b11 4
b11 :
b1 7
b1 H
1$
#60000
0$
b11 (
b11 *
b11 V
#65000
b100 3
b100 ;
b100 I
b110 4
b110 :
b10 7
b10 H
1$
#70000
0$
b10 )
b10 +
b100 (
b100 *
b100 V
#75000
b101 3
b101 ;
b101 I
b1010 4
b1010 :
b100 7
b100 H
1$
#80000
0$
b101 (
b101 *
b101 V
#85000
b110 3
b110 ;
b110 I
b1111 4
b1111 :
b110 7
b110 H
1$
#90000
0$
b11 )
b11 +
b110 (
b110 *
b110 V
#95000
b111 3
b111 ;
b111 I
b10101 4
b10101 :
b1001 7
b1001 H
1$
#100000
0$
b111 (
b111 *
b111 V
#105000
b1000 3
b1000 ;
b1000 I
b11100 4
b11100 :
b1100 7
b1100 H
1$
#110000
0$
b100 )
b100 +
b1000 (
b1000 *
b1000 V
#115000
b1001 3
b1001 ;
b1001 I
b100100 4
b100100 :
b10000 7
b10000 H
1$
#120000
0$
b1001 (
b1001 *
b1001 V
#125000
b1010 3
b1010 ;
b1010 I
b101101 4
b101101 :
b10100 7
b10100 H
1$
#130000
0$
b101 )
b101 +
b1010 (
b1010 *
b1010 V
#135000
b1011 3
b1011 ;
b1011 I
b110111 4
b110111 :
b11001 7
b11001 H
1$
#140000
0$
b1011 (
b1011 *
b1011 V
#145000
b1100 3
b1100 ;
b1100 I
b1000010 4
b1000010 :
b11110 7
b11110 H
1$
#150000
0$
b110 )
b110 +
b1100 (
b1100 *
b1100 V
#155000
b1101 3
b1101 ;
b1101 I
b1001110 4
b1001110 :
b100100 7
b100100 H
1$
#160000
0$
b1101 (
b1101 *
b1101 V
#165000
b1110 3
b1110 ;
b1110 I
b1011011 4
b1011011 :
b101010 7
b101010 H
1$
#170000
0$
b111 )
b111 +
b1110 (
b1110 *
b1110 V
#175000
b1111 3
b1111 ;
b1111 I
b1101001 4
b1101001 :
b110001 7
b110001 H
1$
#180000
0$
b1111 (
b1111 *
b1111 V
#185000
b10000 3
b10000 ;
b10000 I
b1111000 4
b1111000 :
b111000 7
b111000 H
1$
#190000
0$
b1000 )
b1000 +
b10000 (
b10000 *
b10000 V
#195000
b10001 3
b10001 ;
b10001 I
b10001000 4
b10001000 :
b1000000 7
b1000000 H
1$
#200000
0$
b10001 (
b10001 *
b10001 V
#205000
b10010 3
b10010 ;
b10010 I
b10011001 4
b10011001 :
b1001000 7
b1001000 H
1$
#210000
0$
b1001 )
b1001 +
b10010 (
b10010 *
b10010 V
#215000
b10011 3
b10011 ;
b10011 I
b10101011 4
b10101011 :
b1010001 7
b1010001 H
1$
#220000
0$
b10011 (
b10011 *
b10011 V
#225000
b10100 3
b10100 ;
b10100 I
b10111110 4
b10111110 :
b1011010 7
b1011010 H
1$
#230000
0$
b1010 )
b1010 +
b10100 (
b10100 *
b10100 V
#235000
b10101 3
b10101 ;
b10101 I
b11010010 4
b11010010 :
b1100100 7
b1100100 H
1$
#240000
0$
b10101 (
b10101 *
b10101 V
#245000
b10110 3
b10110 ;
b10110 I
b11100111 4
b11100111 :
b1101110 7
b1101110 H
1$
#250000
0$
b1011 )
b1011 +
b10110 (
b10110 *
b10110 V
#255000
b10111 3
b10111 ;
b10111 I
b11111101 4
b11111101 :
b1111001 7
b1111001 H
1$
#260000
0$
b10111 (
b10111 *
b10111 V
#265000
b11000 3
b11000 ;
b11000 I
b100010100 4
b100010100 :
b10000100 7
b10000100 H
1$
#270000
0$
b1100 )
b1100 +
b11000 (
b11000 *
b11000 V
#275000
b11001 3
b11001 ;
b11001 I
b100101100 4
b100101100 :
b10010000 7
b10010000 H
1$
#280000
0$
b11001 (
b11001 *
b11001 V
#285000
b11010 3
b11010 ;
b11010 I
b101000101 4
b101000101 :
b10011100 7
b10011100 H
1$
#290000
0$
b1101 )
b1101 +
b11010 (
b11010 *
b11010 V
#295000
b11011 3
b11011 ;
b11011 I
b101011111 4
b101011111 :
b10101001 7
b10101001 H
1$
#300000
0$
b11011 (
b11011 *
b11011 V
#305000
b11100 3
b11100 ;
b11100 I
b101111010 4
b101111010 :
b10110110 7
b10110110 H
1$
#310000
0$
b1110 )
b1110 +
b11100 (
b11100 *
b11100 V
#315000
b11101 3
b11101 ;
b11101 I
b110010110 4
b110010110 :
b11000100 7
b11000100 H
1$
#320000
0$
b11101 (
b11101 *
b11101 V
#325000
b11110 3
b11110 ;
b11110 I
b110110011 4
b110110011 :
b11010010 7
b11010010 H
1$
#330000
0$
b1111 )
b1111 +
b11110 (
b11110 *
b11110 V
#335000
b11111 3
b11111 ;
b11111 I
b111010001 4
b111010001 :
b11100001 7
b11100001 H
1$
#340000
0$
b11111 (
b11111 *
b11111 V
#345000
b100000 3
b100000 ;
b100000 I
b111110000 4
b111110000 :
b11110000 7
b11110000 H
1$
#350000
0$
b10000 )
b10000 +
b100000 (
b100000 *
b100000 V
#355000
b100001 3
b100001 ;
b100001 I
b1000010000 4
b1000010000 :
b100000000 7
b100000000 H
1$
#360000
0$
b100001 (
b100001 *
b100001 V
#365000
b100010 3
b100010 ;
b100010 I
b1000110001 4
b1000110001 :
b100010000 7
b100010000 H
1$
#370000
0$
b10001 )
b10001 +
b100010 (
b100010 *
b100010 V
#375000
b100011 3
b100011 ;
b100011 I
b1001010011 4
b1001010011 :
b100100001 7
b100100001 H
1$
#380000
0$
b100011 (
b100011 *
b100011 V
#385000
b100100 3
b100100 ;
b100100 I
b1001110110 4
b1001110110 :
b100110010 7
b100110010 H
1$
#390000
0$
b10010 )
b10010 +
b100100 (
b100100 *
b100100 V
#395000
b100101 3
b100101 ;
b100101 I
b1010011010 4
b1010011010 :
b101000100 7
b101000100 H
1$
#400000
0$
b100101 (
b100101 *
b100101 V
#405000
b100110 3
b100110 ;
b100110 I
b1010111111 4
b1010111111 :
b101010110 7
b101010110 H
1$
#410000
0$
b10011 )
b10011 +
b100110 (
b100110 *
b100110 V
#415000
b100111 3
b100111 ;
b100111 I
b1011100101 4
b1011100101 :
b101101001 7
b101101001 H
1$
#420000
0$
b100111 (
b100111 *
b100111 V
#425000
b101000 3
b101000 ;
b101000 I
b1100001100 4
b1100001100 :
b101111100 7
b101111100 H
1$
#430000
0$
b10100 )
b10100 +
b101000 (
b101000 *
b101000 V
#435000
b101001 3
b101001 ;
b101001 I
b1100110100 4
b1100110100 :
b110010000 7
b110010000 H
1$
#440000
0$
b101001 (
b101001 *
b101001 V
#445000
b101010 3
b101010 ;
b101010 I
b1101011101 4
b1101011101 :
b110100100 7
b110100100 H
1$
#450000
0$
b10101 )
b10101 +
b101010 (
b101010 *
b101010 V
#455000
b101011 3
b101011 ;
b101011 I
b1110000111 4
b1110000111 :
b110111001 7
b110111001 H
1$
#460000
0$
b101011 (
b101011 *
b101011 V
#465000
b101100 3
b101100 ;
b101100 I
b1110110010 4
b1110110010 :
b111001110 7
b111001110 H
1$
#470000
0$
b10110 )
b10110 +
b101100 (
b101100 *
b101100 V
#475000
b101101 3
b101101 ;
b101101 I
b1111011110 4
b1111011110 :
b111100100 7
b111100100 H
1$
#480000
0$
b101101 (
b101101 *
b101101 V
#485000
b101110 3
b101110 ;
b101110 I
b10000001011 4
b10000001011 :
b111111010 7
b111111010 H
1$
#490000
0$
b10111 )
b10111 +
b101110 (
b101110 *
b101110 V
#495000
b101111 3
b101111 ;
b101111 I
b10000111001 4
b10000111001 :
b1000010001 7
b1000010001 H
1$
#500000
0$
b101111 (
b101111 *
b101111 V
#505000
b110000 3
b110000 ;
b110000 I
b10001101000 4
b10001101000 :
b1000101000 7
b1000101000 H
1$
#510000
0$
b11000 )
b11000 +
b110000 (
b110000 *
b110000 V
#515000
b110001 3
b110001 ;
b110001 I
b10010011000 4
b10010011000 :
b1001000000 7
b1001000000 H
1$
#520000
0$
b110001 (
b110001 *
b110001 V
#525000
b110010 3
b110010 ;
b110010 I
b10011001001 4
b10011001001 :
b1001011000 7
b1001011000 H
1$
#530000
0$
b11001 )
b11001 +
b110010 (
b110010 *
b110010 V
#535000
b110011 3
b110011 ;
b110011 I
b10011111011 4
b10011111011 :
b1001110001 7
b1001110001 H
1$
#540000
0$
b110011 (
b110011 *
b110011 V
#545000
b110100 3
b110100 ;
b110100 I
b10100101110 4
b10100101110 :
b1010001010 7
b1010001010 H
1$
#550000
0$
b11010 )
b11010 +
b110100 (
b110100 *
b110100 V
#555000
b110101 3
b110101 ;
b110101 I
b10101100010 4
b10101100010 :
b1010100100 7
b1010100100 H
1$
#560000
0$
b110101 (
b110101 *
b110101 V
#565000
b110110 3
b110110 ;
b110110 I
b10110010111 4
b10110010111 :
b1010111110 7
b1010111110 H
1$
#570000
0$
b11011 )
b11011 +
b110110 (
b110110 *
b110110 V
#575000
b110111 3
b110111 ;
b110111 I
b10111001101 4
b10111001101 :
b1011011001 7
b1011011001 H
1$
#580000
0$
b110111 (
b110111 *
b110111 V
#585000
b111000 3
b111000 ;
b111000 I
b11000000100 4
b11000000100 :
b1011110100 7
b1011110100 H
1$
#590000
0$
b11100 )
b11100 +
b111000 (
b111000 *
b111000 V
#595000
b111001 3
b111001 ;
b111001 I
b11000111100 4
b11000111100 :
b1100010000 7
b1100010000 H
1$
#600000
0$
b111001 (
b111001 *
b111001 V
#605000
b111010 3
b111010 ;
b111010 I
b11001110101 4
b11001110101 :
b1100101100 7
b1100101100 H
1$
#610000
0$
b11101 )
b11101 +
b111010 (
b111010 *
b111010 V
#615000
b111011 3
b111011 ;
b111011 I
b11010101111 4
b11010101111 :
b1101001001 7
b1101001001 H
1$
#620000
0$
b111011 (
b111011 *
b111011 V
#625000
b111100 3
b111100 ;
b111100 I
b11011101010 4
b11011101010 :
b1101100110 7
b1101100110 H
1$
#630000
0$
b11110 )
b11110 +
b111100 (
b111100 *
b111100 V
#635000
b111101 3
b111101 ;
b111101 I
b11100100110 4
b11100100110 :
b1110000100 7
b1110000100 H
1$
#640000
0$
b111101 (
b111101 *
b111101 V
#645000
b111110 3
b111110 ;
b111110 I
b11101100011 4
b11101100011 :
b1110100010 7
b1110100010 H
1$
#650000
0$
b11111 )
b11111 +
b111110 (
b111110 *
b111110 V
#655000
b111111 3
b111111 ;
b111111 I
b11110100001 4
b11110100001 :
b1111000001 7
b1111000001 H
1$
#660000
0$
b111111 (
b111111 *
b111111 V
#665000
b1000000 3
b1000000 ;
b1000000 I
b11111100000 4
b11111100000 :
b1111100000 7
b1111100000 H
1$
#670000
0$
b100000 )
b100000 +
b1000000 (
b1000000 *
b1000000 V
#675000
b1000001 3
b1000001 ;
b1000001 I
b100000100000 4
b100000100000 :
b10000000000 7
b10000000000 H
1$
#680000
0$
b1000001 (
b1000001 *
b1000001 V
#685000
b1000010 3
b1000010 ;
b1000010 I
b100001100001 4
b100001100001 :
b10000100000 7
b10000100000 H
1$
#690000
0$
b100001 )
b100001 +
b1000010 (
b1000010 *
b1000010 V
#695000
b1000011 3
b1000011 ;
b1000011 I
b100010100011 4
b100010100011 :
b10001000001 7
b10001000001 H
1$
#700000
0$
b1000011 (
b1000011 *
b1000011 V
#705000
b1000100 3
b1000100 ;
b1000100 I
b100011100110 4
b100011100110 :
b10001100010 7
b10001100010 H
1$
#710000
0$
b100010 )
b100010 +
b1000100 (
b1000100 *
b1000100 V
#715000
b1000101 3
b1000101 ;
b1000101 I
b100100101010 4
b100100101010 :
b10010000100 7
b10010000100 H
1$
#720000
0$
b1000101 (
b1000101 *
b1000101 V
#725000
b1000110 3
b1000110 ;
b1000110 I
b100101101111 4
b100101101111 :
b10010100110 7
b10010100110 H
1$
#730000
0$
b100011 )
b100011 +
b1000110 (
b1000110 *
b1000110 V
#735000
b1000111 3
b1000111 ;
b1000111 I
b100110110101 4
b100110110101 :
b10011001001 7
b10011001001 H
1$
#740000
0$
b1000111 (
b1000111 *
b1000111 V
#745000
b1001000 3
b1001000 ;
b1001000 I
b100111111100 4
b100111111100 :
b10011101100 7
b10011101100 H
1$
#750000
0$
b100100 )
b100100 +
b1001000 (
b1001000 *
b1001000 V
#755000
b1001001 3
b1001001 ;
b1001001 I
b101001000100 4
b101001000100 :
b10100010000 7
b10100010000 H
1$
#760000
0$
b1001001 (
b1001001 *
b1001001 V
#765000
b1001010 3
b1001010 ;
b1001010 I
b101010001101 4
b101010001101 :
b10100110100 7
b10100110100 H
1$
#770000
0$
b100101 )
b100101 +
b1001010 (
b1001010 *
b1001010 V
#775000
b1001011 3
b1001011 ;
b1001011 I
b101011010111 4
b101011010111 :
b10101011001 7
b10101011001 H
1$
#780000
0$
b1001011 (
b1001011 *
b1001011 V
#785000
b1001100 3
b1001100 ;
b1001100 I
b101100100010 4
b101100100010 :
b10101111110 7
b10101111110 H
1$
#790000
0$
b100110 )
b100110 +
b1001100 (
b1001100 *
b1001100 V
#795000
b1001101 3
b1001101 ;
b1001101 I
b101101101110 4
b101101101110 :
b10110100100 7
b10110100100 H
1$
#800000
0$
b1001101 (
b1001101 *
b1001101 V
#805000
b1001110 3
b1001110 ;
b1001110 I
b101110111011 4
b101110111011 :
b10111001010 7
b10111001010 H
1$
#810000
0$
b100111 )
b100111 +
b1001110 (
b1001110 *
b1001110 V
#815000
b1001111 3
b1001111 ;
b1001111 I
b110000001001 4
b110000001001 :
b10111110001 7
b10111110001 H
1$
#820000
0$
b1001111 (
b1001111 *
b1001111 V
#825000
b1010000 3
b1010000 ;
b1010000 I
b110001011000 4
b110001011000 :
b11000011000 7
b11000011000 H
1$
#830000
0$
b101000 )
b101000 +
b1010000 (
b1010000 *
b1010000 V
#835000
b1010001 3
b1010001 ;
b1010001 I
b110010101000 4
b110010101000 :
b11001000000 7
b11001000000 H
1$
#840000
0$
b1010001 (
b1010001 *
b1010001 V
#845000
b1010010 3
b1010010 ;
b1010010 I
b110011111001 4
b110011111001 :
b11001101000 7
b11001101000 H
1$
#850000
0$
b101001 )
b101001 +
b1010010 (
b1010010 *
b1010010 V
#855000
b1010011 3
b1010011 ;
b1010011 I
b110101001011 4
b110101001011 :
b11010010001 7
b11010010001 H
1$
#860000
0$
b1010011 (
b1010011 *
b1010011 V
#865000
b1010100 3
b1010100 ;
b1010100 I
b110110011110 4
b110110011110 :
b11010111010 7
b11010111010 H
1$
#870000
0$
b101010 )
b101010 +
b1010100 (
b1010100 *
b1010100 V
#875000
b1010101 3
b1010101 ;
b1010101 I
b110111110010 4
b110111110010 :
b11011100100 7
b11011100100 H
1$
#880000
0$
b1010101 (
b1010101 *
b1010101 V
#885000
b1010110 3
b1010110 ;
b1010110 I
b111001000111 4
b111001000111 :
b11100001110 7
b11100001110 H
1$
#890000
0$
b101011 )
b101011 +
b1010110 (
b1010110 *
b1010110 V
#895000
b1010111 3
b1010111 ;
b1010111 I
b111010011101 4
b111010011101 :
b11100111001 7
b11100111001 H
1$
#900000
0$
b1010111 (
b1010111 *
b1010111 V
#905000
b1011000 3
b1011000 ;
b1011000 I
b111011110100 4
b111011110100 :
b11101100100 7
b11101100100 H
1$
#910000
0$
b101100 )
b101100 +
b1011000 (
b1011000 *
b1011000 V
#915000
b1011001 3
b1011001 ;
b1011001 I
b111101001100 4
b111101001100 :
b11110010000 7
b11110010000 H
1$
#920000
0$
b1011001 (
b1011001 *
b1011001 V
#925000
b1011010 3
b1011010 ;
b1011010 I
b111110100101 4
b111110100101 :
b11110111100 7
b11110111100 H
1$
#930000
0$
b101101 )
b101101 +
b1011010 (
b1011010 *
b1011010 V
#935000
b1011011 3
b1011011 ;
b1011011 I
b111111111111 4
b111111111111 :
b11111101001 7
b11111101001 H
1$
#940000
0$
b1011011 (
b1011011 *
b1011011 V
#945000
b1011100 3
b1011100 ;
b1011100 I
b1000001011010 4
b1000001011010 :
b100000010110 7
b100000010110 H
1$
#950000
0$
b101110 )
b101110 +
b1011100 (
b1011100 *
b1011100 V
#955000
b1011101 3
b1011101 ;
b1011101 I
b1000010110110 4
b1000010110110 :
b100001000100 7
b100001000100 H
1$
#960000
0$
b1011101 (
b1011101 *
b1011101 V
#965000
b1011110 3
b1011110 ;
b1011110 I
b1000100010011 4
b1000100010011 :
b100001110010 7
b100001110010 H
1$
#970000
0$
b101111 )
b101111 +
b1011110 (
b1011110 *
b1011110 V
#975000
b1011111 3
b1011111 ;
b1011111 I
b1000101110001 4
b1000101110001 :
b100010100001 7
b100010100001 H
1$
#980000
0$
b1011111 (
b1011111 *
b1011111 V
#985000
b1100000 3
b1100000 ;
b1100000 I
b1000111010000 4
b1000111010000 :
b100011010000 7
b100011010000 H
1$
#990000
0$
b110000 )
b110000 +
b1100000 (
b1100000 *
b1100000 V
#995000
b1100001 3
b1100001 ;
b1100001 I
b1001000110000 4
b1001000110000 :
b100100000000 7
b100100000000 H
1$
#1000000
0$
b1100001 (
b1100001 *
b1100001 V
#1005000
b1100010 3
b1100010 ;
b1100010 I
b1001010010001 4
b1001010010001 :
b100100110000 7
b100100110000 H
1$
#1010000
0$
b110001 )
b110001 +
b1100010 (
b1100010 *
b1100010 V
#1015000
b1100011 3
b1100011 ;
b1100011 I
b1001011110011 4
b1001011110011 :
b100101100001 7
b100101100001 H
1$
#1020000
0$
b1100011 (
b1100011 *
b1100011 V
#1025000
b1100100 3
b1100100 ;
b1100100 I
b1001101010110 4
b1001101010110 :
b100110010010 7
b100110010010 H
1$
#1030000
0$
b110010 )
b110010 +
b1100100 (
b1100100 *
b1100100 V
#1035000
b1100101 3
b1100101 ;
b1100101 I
b1001110111010 4
b1001110111010 :
b100111000100 7
b100111000100 H
1$
#1040000
0$
b1100101 (
b1100101 *
b1100101 V
#1045000
b1100110 3
b1100110 ;
b1100110 I
b1010000011111 4
b1010000011111 :
b100111110110 7
b100111110110 H
1$
#1050000
0$
b110011 )
b110011 +
b1100110 (
b1100110 *
b1100110 V
#1055000
b1100111 3
b1100111 ;
b1100111 I
b1010010000101 4
b1010010000101 :
b101000101001 7
b101000101001 H
1$
#1060000
0$
b1100111 (
b1100111 *
b1100111 V
#1065000
b1101000 3
b1101000 ;
b1101000 I
b1010011101100 4
b1010011101100 :
b101001011100 7
b101001011100 H
1$
#1070000
0$
b110100 )
b110100 +
b1101000 (
b1101000 *
b1101000 V
#1075000
b1101001 3
b1101001 ;
b1101001 I
b1010101010100 4
b1010101010100 :
b101010010000 7
b101010010000 H
1$
#1080000
0$
b1101001 (
b1101001 *
b1101001 V
#1085000
b1101010 3
b1101010 ;
b1101010 I
b1010110111101 4
b1010110111101 :
b101011000100 7
b101011000100 H
1$
#1090000
0$
b110101 )
b110101 +
b1101010 (
b1101010 *
b1101010 V
#1095000
b1101011 3
b1101011 ;
b1101011 I
b1011000100111 4
b1011000100111 :
b101011111001 7
b101011111001 H
1$
#1100000
0$
b1101011 (
b1101011 *
b1101011 V
#1105000
b1101100 3
b1101100 ;
b1101100 I
b1011010010010 4
b1011010010010 :
b101100101110 7
b101100101110 H
1$
