Archives/Lab 4/hdl/tm_choice.sv
module tm_choice (
  input wire [7:0] data_in,
  output logic [8:0] qm_out
  );
  logic [7:0] counter;
  logic [8:0] intermediate;
  always_comb begin  
    qm_out[0] = data_in[0];
    counter = 0;
    for (int i = 0; i < 8; i++) begin
        if (data_in[i] == 1)begin
            counter ++ ;            
        end
    end
    if (counter > 4 || (counter == 4 && data_in[0] == 0))begin
        for (int i = 0; i < 8; i++ ) begin
            qm_out[i+1] = ~(data_in[i+1] ^ qm_out[i]);
        end
        qm_out[8] = 0;   
    end else begin
        for (int i = 0; i < 8; i++ ) begin
            qm_out[i+1] = (data_in[i+1] ^ qm_out[i]);
        end
        qm_out[8] = 1;     
    end
end
endmodule

Archives/Lab 5/hdl/tmds_encoder.sv
module tmds_encoder(
  input wire clk_in,
  input wire rst_in,
  input wire [7:0] data_in,  // video data (red, green or blue)
  input wire [1:0] control_in, //for blue set to {vs,hs}, else will be 0
  input wire ve_in,  // video data enable, to choose between control or video signal
  output logic [9:0] tmds_out
);

  logic [8:0] q_m;
  //you can assume a functioning (version of tm_choice for you.)
  tm_choice mtm(
    .data_in(data_in),
    .qm_out(q_m));

  logic [4:0] tally;
  logic [8:0] counter;

  always_comb begin
    counter = q_m[0] + q_m[1] + q_m[2] + q_m[3] + q_m[4] + q_m[5] + q_m[6] + q_m[7];
  end

  always_ff @(posedge clk_in)begin
    if (rst_in)begin
        tally <= 0;
        tmds_out <= 0;    

    end else if (ve_in) begin
        if (tally == 0 || (counter == (8-counter)))begin
            tmds_out[9] <= ~q_m[8];
            tmds_out[8] <= q_m[8];
            tmds_out[7:0] <= (q_m[8] ? q_m[7:0] : ~q_m[7:0]);

            if (q_m[8] == 0)begin
                tally <= tally + (8 - counter - counter);
            end else begin
                tally <= tally + (counter - (8 - counter));
            end

        end else begin
            if ((tally[4] == 0 && counter > (8-counter)) || (tally[4] > 0 && counter < (8-counter)))begin
            tmds_out[9] <= 1;
            tmds_out[8] <= q_m[8];
            tmds_out[7:0] <= ~q_m[7:0];
            tally <= tally + {q_m[8], 1'b0} + (8 - counter - counter);


            end else begin
            tmds_out[9] <= 0;
            tmds_out[8] <= q_m[8];
            tmds_out[7:0] <= q_m[7:0];
            tally <= tally - {~q_m[8], 1'b0} + (counter - (8-counter));
            end
        end

    end else if (ve_in == 0) begin
        tally <= 0;
        if (control_in == 2'b00) begin
            tmds_out <= 10'b1101010100;
        end else if (control_in == 2'b01) begin
            tmds_out <= 10'b0010101011;
        end else if (control_in == 2'b10) begin
            tmds_out <= 10'b0101010100;
        end else if (control_in == 2'b11) begin
            tmds_out <= 10'b1010101011;
        end
    end
  end

endmodule //end tmds_encoder

Archives/Lab 4/sim/tmds_2_tb.sv

`timescale 1ns / 1ps
`default_nettype none


module tmds_2_tb();

  logic clk_in;
  logic rst_in;
	logic [7:0] data_in;
	logic [1:0] control_in;
	logic ve_in;
	logic [9:0] tmds_out;
  tmds_encoder uut(
  .clk_in(clk_in),
  .rst_in(rst_in),
  .data_in(data_in),  // video data (red, green or blue)
  .control_in(control_in),  // control data
  .ve_in(ve_in),  // video data enable, to choose between CD (when VDE=0) and VD (when VDE=1)
  .tmds_out(tmds_out)
  );

  always begin
      #5;  //every 5 ns switch...so period of clock is 10 ns...100 MHz clock
      clk_in = !clk_in;
  end
  //initial block...this is our test simulation
  initial begin
    $dumpfile("tmds_2_tb.vcd"); //file to store value change dump (vcd)
    $dumpvars(0,tmds_2_tb);
    $display("Starting Sim"); //print nice message at start
    clk_in = 0;
    rst_in = 1;
    control_in = 0;
    ve_in = 1;
    data_in = 0;;
    #10;
    rst_in=0;
    for(int i = 0; i<1024; i = i+1)begin
      data_in = i;
      #10;
    end
    control_in = 0;
    #100;
    control_in = 1;
    #100;
    control_in = 2;
    #100;
    control_in = 3;
    #100;
    ve_in = 0;
    control_in = 0;
    #100;
    control_in = 1;
    #100;
    control_in = 2;
    #100;
    control_in = 3;
    #100;
    ve_in = 1;
    #10;
    for(int i = 0; i<1024; i = i+1)begin
      data_in = 255-i;
      #10;
    end
    #500;
    $display("Finishing Sim"); //print nice message at end
    $finish;
  end
endmodule
`default_nettype wire

Archives/Lab 4/sim/tmds_2_tb.vcd
$date
	Thu Sep 28 16:11:44 2023
$end
$version
	Icarus Verilog
$end
$timescale
	1ps
$end
$scope module tmds_2_tb $end
$var wire 10 ! tmds_out [9:0] $end
$var reg 1 " clk_in $end
$var reg 2 # control_in [1:0] $end
$var reg 8 $ data_in [7:0] $end
$var reg 1 % rst_in $end
$var reg 1 & ve_in $end
$upscope $end
$enddefinitions $end
#0
$dumpvars
1&
1%
b0 $
b0 #
0"
bx !
$end
#5000
b0 !
1"
#10000
0"
0%
#15000
b100000000 !
1"
#20000
0"
b1 $
#25000
b111111111 !
1"
#30000
0"
b10 $
#35000
b111111110 !
1"
#40000
0"
b11 $
#45000
b100000001 !
1"
#50000
0"
b100 $
#55000
b111111100 !
1"
#60000
0"
b101 $
#65000
b100000011 !
1"
#70000
0"
b110 $
#75000
b100000010 !
1"
#80000
0"
b111 $
#85000
b111111101 !
1"
#90000
0"
b1000 $
#95000
b111111000 !
1"
#100000
0"
b1001 $
#105000
b100000111 !
1"
#110000
0"
b1010 $
#115000
b100000110 !
1"
#120000
0"
b1011 $
#125000
b111111001 !
1"
#130000
0"
b1100 $
#135000
b100000100 !
1"
#140000
0"
b1101 $
#145000
b111111011 !
1"
#150000
0"
b1110 $
#155000
b111111010 !
1"
#160000
0"
b1111 $
#165000
b100000101 !
1"
#170000
0"
b10000 $
#175000
b111110000 !
1"
#180000
0"
b10001 $
#185000
b100001111 !
1"
#190000
0"
b10010 $
#195000
b100001110 !
1"
#200000
0"
b10011 $
#205000
b111110001 !
1"
#210000
0"
b10100 $
#215000
b100001100 !
1"
#220000
0"
b10101 $
#225000
b111110011 !
1"
#230000
0"
b10110 $
#235000
b111110010 !
1"
#240000
0"
b10111 $
#245000
b100001101 !
1"
#250000
0"
b11000 $
#255000
b100001000 !
1"
#260000
0"
b11001 $
#265000
b111110111 !
1"
#270000
0"
b11010 $
#275000
b111110110 !
1"
#280000
0"
b11011 $
#285000
b100001001 !
1"
#290000
0"
b11100 $
#295000
b111110100 !
1"
#300000
0"
b11101 $
#305000
b100001011 !
1"
#310000
0"
b11110 $
#315000
b1001011111 !
1"
#320000
0"
b11111 $
#325000
b1010100000 !
1"
#330000
0"
b100000 $
#335000
b111100000 !
1"
#340000
0"
b100001 $
#345000
b100011111 !
1"
#350000
0"
b100010 $
#355000
b100011110 !
1"
#360000
0"
b100011 $
#365000
b111100001 !
1"
#370000
0"
b100100 $
#375000
b100011100 !
1"
#380000
0"
b100101 $
#385000
b111100011 !
1"
#390000
0"
b100110 $
#395000
b111100010 !
1"
#400000
0"
b100111 $
#405000
b100011101 !
1"
#410000
0"
b101000 $
#415000
b100011000 !
1"
#420000
0"
b101001 $
#425000
b111100111 !
1"
#430000
0"
b101010 $
#435000
b111100110 !
1"
#440000
0"
b101011 $
#445000
b100011001 !
1"
#450000
0"
b101100 $
#455000
b111100100 !
1"
#460000
0"
b101101 $
#465000
b100011011 !
1"
#470000
0"
b101110 $
#475000
b1001001111 !
1"
#480000
0"
b101111 $
#485000
b1010110000 !
1"
#490000
0"
b110000 $
#495000
b100010000 !
1"
#500000
0"
b110001 $
#505000
b111101111 !
1"
#510000
0"
b110010 $
#515000
b111101110 !
1"
#520000
0"
b110011 $
#525000
b100010001 !
1"
#530000
0"
b110100 $
#535000
b111101100 !
1"
#540000
0"
b110101 $
#545000
b100010011 !
1"
#550000
0"
b110110 $
#555000
b1001000111 !
1"
#560000
0"
b110111 $
#565000
b1010111000 !
1"
#570000
0"
b111000 $
#575000
b111101000 !
1"
#580000
0"
b111001 $
#585000
b100010111 !
1"
#590000
0"
b111010 $
#595000
b1001000011 !
1"
#600000
0"
b111011 $
#605000
b1010111100 !
1"
#610000
0"
b111100 $
#615000
b1001000001 !
1"
#620000
0"
b111101 $
#625000
b1010111110 !
1"
#630000
0"
b111110 $
#635000
b1010111111 !
1"
#640000
0"
b111111 $
#645000
b1001000000 !
1"
#650000
0"
b1000000 $
#655000
b111000000 !
1"
#660000
0"
b1000001 $
#665000
b100111111 !
1"
#670000
0"
b1000010 $
#675000
b100111110 !
1"
#680000
0"
b1000011 $
#685000
b111000001 !
1"
#690000
0"
b1000100 $
#695000
b100111100 !
1"
#700000
0"
b1000101 $
#705000
b111000011 !
1"
#710000
0"
b1000110 $
#715000
b111000010 !
1"
#720000
0"
b1000111 $
#725000
b100111101 !
1"
#730000
0"
b1001000 $
#735000
b100111000 !
1"
#740000
0"
b1001001 $
#745000
b111000111 !
1"
#750000
0"
b1001010 $
#755000
b111000110 !
1"
#760000
0"
b1001011 $
#765000
b100111001 !
1"
#770000
0"
b1001100 $
#775000
b111000100 !
1"
#780000
0"
b1001101 $
#785000
b100111011 !
1"
#790000
0"
b1001110 $
#795000
b1001101111 !
1"
#800000
0"
b1001111 $
#805000
b1010010000 !
1"
#810000
0"
b1010000 $
#815000
b100110000 !
1"
#820000
0"
b1010001 $
#825000
b111001111 !
1"
#830000
0"
b1010010 $
#835000
b111001110 !
1"
#840000
0"
b1010011 $
#845000
b100110001 !
1"
#850000
0"
b1010100 $
#855000
b111001100 !
1"
#860000
0"
b1010101 $
#865000
b100110011 !
1"
#870000
0"
b1010110 $
#875000
b1001100111 !
1"
#880000
0"
b1010111 $
#885000
b1010011000 !
1"
#890000
0"
b1011000 $
#895000
b111001000 !
1"
#900000
0"
b1011001 $
#905000
b100110111 !
1"
#910000
0"
b1011010 $
#915000
b1001100011 !
1"
#920000
0"
b1011011 $
#925000
b1010011100 !
1"
#930000
0"
b1011100 $
#935000
b1001100001 !
1"
#940000
0"
b1011101 $
#945000
b1010011110 !
1"
#950000
0"
b1011110 $
#955000
b1010011111 !
1"
#960000
0"
b1011111 $
#965000
b1001100000 !
1"
#970000
0"
b1100000 $
#975000
b100100000 !
1"
#980000
0"
b1100001 $
#985000
b111011111 !
1"
#990000
0"
b1100010 $
#995000
b111011110 !
1"
#1000000
0"
b1100011 $
#1005000
b100100001 !
1"
#1010000
0"
b1100100 $
#1015000
b111011100 !
1"
#1020000
0"
b1100101 $
#1025000
b100100011 !
1"
#1030000
0"
b1100110 $
#1035000
b1001110111 !
1"
#1040000
0"
b1100111 $
#1045000
b1010001000 !
1"
#1050000
0"
b1101000 $
#1055000
b111011000 !
1"
#1060000
0"
b1101001 $
#1065000
b100100111 !
1"
#1070000
0"
b1101010 $
#1075000
b1001110011 !
1"
#1080000
0"
b1101011 $
#1085000
b1010001100 !
1"
#1090000
0"
b1101100 $
#1095000
b1001110001 !
1"
#1100000
0"
b1101101 $
#1105000
b1010001110 !
1"
#1110000
0"
b1101110 $
#1115000
b1010001111 !
1"
#1120000
0"
b1101111 $
#1125000
b1001110000 !
1"
#1130000
0"
b1110000 $
#1135000
b111010000 !
1"
#1140000
0"
b1110001 $
#1145000
b100101111 !
1"
#1150000
0"
b1110010 $
#1155000
b1001111011 !
1"
#1160000
0"
b1110011 $
#1165000
b1010000100 !
1"
#1170000
0"
b1110100 $
#1175000
b1001111001 !
1"
#1180000
0"
b1110101 $
#1185000
b1010000110 !
1"
#1190000
0"
b1110110 $
#1195000
b1010000111 !
1"
#1200000
0"
b1110111 $
#1205000
b1001111000 !
1"
#1210000
0"
b1111000 $
#1215000
b1001111101 !
1"
#1220000
0"
b1111001 $
#1225000
b1010000010 !
1"
#1230000
0"
b1111010 $
#1235000
b1010000011 !
1"
#1240000
0"
b1111011 $
#1245000
b1001111100 !
1"
#1250000
0"
b1111100 $
#1255000
b1010000001 !
1"
#1260000
0"
b1111101 $
#1265000
b1001111110 !
1"
#1270000
0"
b1111110 $
#1275000
b1001111111 !
1"
#1280000
0"
b1111111 $
#1285000
b1010000000 !
1"
#1290000
0"
b10000000 $
#1295000
b110000000 !
1"
#1300000
0"
b10000001 $
#1305000
b101111111 !
1"
#1310000
0"
b10000010 $
#1315000
b101111110 !
1"
#1320000
0"
b10000011 $
#1325000
b110000001 !
1"
#1330000
0"
b10000100 $
#1335000
b101111100 !
1"
#1340000
0"
b10000101 $
#1345000
b110000011 !
1"
#1350000
0"
b10000110 $
#1355000
b110000010 !
1"
#1360000
0"
b10000111 $
#1365000
b101111101 !
1"
#1370000
0"
b10001000 $
#1375000
b101111000 !
1"
#1380000
0"
b10001001 $
#1385000
b110000111 !
1"
#1390000
0"
b10001010 $
#1395000
b110000110 !
1"
#1400000
0"
b10001011 $
#1405000
b101111001 !
1"
#1410000
0"
b10001100 $
#1415000
b110000100 !
1"
#1420000
0"
b10001101 $
#1425000
b101111011 !
1"
#1430000
0"
b10001110 $
#1435000
b1000101111 !
1"
#1440000
0"
b10001111 $
#1445000
b1011010000 !
1"
#1450000
0"
b10010000 $
#1455000
b101110000 !
1"
#1460000
0"
b10010001 $
#1465000
b110001111 !
1"
#1470000
0"
b10010010 $
#1475000
b110001110 !
1"
#1480000
0"
b10010011 $
#1485000
b101110001 !
1"
#1490000
0"
b10010100 $
#1495000
b110001100 !
1"
#1500000
0"
b10010101 $
#1505000
b101110011 !
1"
#1510000
0"
b10010110 $
#1515000
b1000100111 !
1"
#1520000
0"
b10010111 $
#1525000
b1011011000 !
1"
#1530000
0"
b10011000 $
#1535000
b110001000 !
1"
#1540000
0"
b10011001 $
#1545000
b101110111 !
1"
#1550000
0"
b10011010 $
#1555000
b1000100011 !
1"
#1560000
0"
b10011011 $
#1565000
b1011011100 !
1"
#1570000
0"
b10011100 $
#1575000
b1000100001 !
1"
#1580000
0"
b10011101 $
#1585000
b1011011110 !
1"
#1590000
0"
b10011110 $
#1595000
b1011011111 !
1"
#1600000
0"
b10011111 $
#1605000
b1000100000 !
1"
#1610000
0"
b10100000 $
#1615000
b101100000 !
1"
#1620000
0"
b10100001 $
#1625000
b110011111 !
1"
#1630000
0"
b10100010 $
#1635000
b110011110 !
1"
#1640000
0"
b10100011 $
#1645000
b101100001 !
1"
#1650000
0"
b10100100 $
#1655000
b110011100 !
1"
#1660000
0"
b10100101 $
#1665000
b101100011 !
1"
#1670000
0"
b10100110 $
#1675000
b1000110111 !
1"
#1680000
0"
b10100111 $
#1685000
b1011001000 !
1"
#1690000
0"
b10101000 $
#1695000
b110011000 !
1"
#1700000
0"
b10101001 $
#1705000
b101100111 !
1"
#1710000
0"
b10101010 $
#1715000
b1000110011 !
1"
#1720000
0"
b10101011 $
#1725000
b1011001100 !
1"
#1730000
0"
b10101100 $
#1735000
b1000110001 !
1"
#1740000
0"
b10101101 $
#1745000
b1011001110 !
1"
#1750000
0"
b10101110 $
#1755000
b1011001111 !
1"
#1760000
0"
b10101111 $
#1765000
b1000110000 !
1"
#1770000
0"
b10110000 $
#1775000
b110010000 !
1"
#1780000
0"
b10110001 $
#1785000
b101101111 !
1"
#1790000
0"
b10110010 $
#1795000
b1000111011 !
1"
#1800000
0"
b10110011 $
#1805000
b1011000100 !
1"
#1810000
0"
b10110100 $
#1815000
b1000111001 !
1"
#1820000
0"
b10110101 $
#1825000
b1011000110 !
1"
#1830000
0"
b10110110 $
#1835000
b1011000111 !
1"
#1840000
0"
b10110111 $
#1845000
b1000111000 !
1"
#1850000
0"
b10111000 $
#1855000
b1000111101 !
1"
#1860000
0"
b10111001 $
#1865000
b1011000010 !
1"
#1870000
0"
b10111010 $
#1875000
b1011000011 !
1"
#1880000
0"
b10111011 $
#1885000
b1000111100 !
1"
#1890000
0"
b10111100 $
#1895000
b1011000001 !
1"
#1900000
0"
b10111101 $
#1905000
b1000111110 !
1"
#1910000
0"
b10111110 $
#1915000
b1000111111 !
1"
#1920000
0"
b10111111 $
#1925000
b1011000000 !
1"
#1930000
0"
b11000000 $
#1935000
b101000000 !
1"
#1940000
0"
b11000001 $
#1945000
b110111111 !
1"
#1950000
0"
b11000010 $
#1955000
b110111110 !
1"
#1960000
0"
b11000011 $
#1965000
b101000001 !
1"
#1970000
0"
b11000100 $
#1975000
b110111100 !
1"
#1980000
0"
b11000101 $
#1985000
b101000011 !
1"
#1990000
0"
b11000110 $
#1995000
b1000010111 !
1"
#2000000
0"
b11000111 $
#2005000
b1011101000 !
1"
#2010000
0"
b11001000 $
#2015000
b110111000 !
1"
#2020000
0"
b11001001 $
#2025000
b101000111 !
1"
#2030000
0"
b11001010 $
#2035000
b1000010011 !
1"
#2040000
0"
b11001011 $
#2045000
b1011101100 !
1"
#2050000
0"
b11001100 $
#2055000
b1000010001 !
1"
#2060000
0"
b11001101 $
#2065000
b1011101110 !
1"
#2070000
0"
b11001110 $
#2075000
b1011101111 !
1"
#2080000
0"
b11001111 $
#2085000
b1000010000 !
1"
#2090000
0"
b11010000 $
#2095000
b110110000 !
1"
#2100000
0"
b11010001 $
#2105000
b101001111 !
1"
#2110000
0"
b11010010 $
#2115000
b1000011011 !
1"
#2120000
0"
b11010011 $
#2125000
b1011100100 !
1"
#2130000
0"
b11010100 $
#2135000
b1000011001 !
1"
#2140000
0"
b11010101 $
#2145000
b1011100110 !
1"
#2150000
0"
b11010110 $
#2155000
b1011100111 !
1"
#2160000
0"
b11010111 $
#2165000
b1000011000 !
1"
#2170000
0"
b11011000 $
#2175000
b1000011101 !
1"
#2180000
0"
b11011001 $
#2185000
b1011100010 !
1"
#2190000
0"
b11011010 $
#2195000
b1011100011 !
1"
#2200000
0"
b11011011 $
#2205000
b1000011100 !
1"
#2210000
0"
b11011100 $
#2215000
b1011100001 !
1"
#2220000
0"
b11011101 $
#2225000
b1000011110 !
1"
#2230000
0"
b11011110 $
#2235000
b1000011111 !
1"
#2240000
0"
b11011111 $
#2245000
b1011100000 !
1"
#2250000
0"
b11100000 $
#2255000
b110100000 !
1"
#2260000
0"
b11100001 $
#2265000
b101011111 !
1"
#2270000
0"
b11100010 $
#2275000
b1000001011 !
1"
#2280000
0"
b11100011 $
#2285000
b1011110100 !
1"
#2290000
0"
b11100100 $
#2295000
b1000001001 !
1"
#2300000
0"
b11100101 $
#2305000
b1011110110 !
1"
#2310000
0"
b11100110 $
#2315000
b1011110111 !
1"
#2320000
0"
b11100111 $
#2325000
b1000001000 !
1"
#2330000
0"
b11101000 $
#2335000
b1000001101 !
1"
#2340000
0"
b11101001 $
#2345000
b1011110010 !
1"
#2350000
0"
b11101010 $
#2355000
b1011110011 !
1"
#2360000
0"
b11101011 $
#2365000
b1000001100 !
1"
#2370000
0"
b11101100 $
#2375000
b1011110001 !
1"
#2380000
0"
b11101101 $
#2385000
b1000001110 !
1"
#2390000
0"
b11101110 $
#2395000
b1000001111 !
1"
#2400000
0"
b11101111 $
#2405000
b1011110000 !
1"
#2410000
0"
b11110000 $
#2415000
b1000000101 !
1"
#2420000
0"
b11110001 $
#2425000
b1011111010 !
1"
#2430000
0"
b11110010 $
#2435000
b1011111011 !
1"
#2440000
0"
b11110011 $
#2445000
b1000000100 !
1"
#2450000
0"
b11110100 $
#2455000
b1011111001 !
1"
#2460000
0"
b11110101 $
#2465000
b1000000110 !
1"
#2470000
0"
b11110110 $
#2475000
b1000000111 !
1"
#2480000
0"
b11110111 $
#2485000
b1011111000 !
1"
#2490000
0"
b11111000 $
#2495000
b1011111101 !
1"
#2500000
0"
b11111001 $
#2505000
b1000000010 !
1"
#2510000
0"
b11111010 $
#2515000
b1000000011 !
1"
#2520000
0"
b11111011 $
#2525000
b1011111100 !
1"
#2530000
0"
b11111100 $
#2535000
b1000000001 !
1"
#2540000
0"
b11111101 $
#2545000
b1011111110 !
1"
#2550000
0"
b11111110 $
#2555000
b1011111111 !
1"
#2560000
0"
b11111111 $
#2565000
b1000000000 !
1"
#2570000
0"
b0 $
#2575000
b100000000 !
1"
#2580000
0"
b1 $
#2585000
b111111111 !
1"
#2590000
0"
b10 $
#2595000
b111111110 !
1"
#2600000
0"
b11 $
#2605000
b100000001 !
1"
#2610000
0"
b100 $
#2615000
b111111100 !
1"
#2620000
0"
b101 $
#2625000
b100000011 !
1"
#2630000
0"
b110 $
#2635000
b100000010 !
1"
#2640000
0"
b111 $
#2645000
b111111101 !
1"
#2650000
0"
b1000 $
#2655000
b111111000 !
1"
#2660000
0"
b1001 $
#2665000
b100000111 !
1"
#2670000
0"
b1010 $
#2675000
b100000110 !
1"
#2680000
0"
b1011 $
#2685000
b111111001 !
1"
#2690000
0"
b1100 $
#2695000
b100000100 !
1"
#2700000
0"
b1101 $
#2705000
b111111011 !
1"
#2710000
0"
b1110 $
#2715000
b111111010 !
1"
#2720000
0"
b1111 $
#2725000
b100000101 !
1"
#2730000
0"
b10000 $
#2735000
b111110000 !
1"
#2740000
0"
b10001 $
#2745000
b100001111 !
1"
#2750000
0"
b10010 $
#2755000
b100001110 !
1"
#2760000
0"
b10011 $
#2765000
b111110001 !
1"
#2770000
0"
b10100 $
#2775000
b100001100 !
1"
#2780000
0"
b10101 $
#2785000
b111110011 !
1"
#2790000
0"
b10110 $
#2795000
b111110010 !
1"
#2800000
0"
b10111 $
#2805000
b100001101 !
1"
#2810000
0"
b11000 $
#2815000
b100001000 !
1"
#2820000
0"
b11001 $
#2825000
b111110111 !
1"
#2830000
0"
b11010 $
#2835000
b111110110 !
1"
#2840000
0"
b11011 $
#2845000
b100001001 !
1"
#2850000
0"
b11100 $
#2855000
b111110100 !
1"
#2860000
0"
b11101 $
#2865000
b100001011 !
1"
#2870000
0"
b11110 $
#2875000
b1001011111 !
1"
#2880000
0"
b11111 $
#2885000
b1010100000 !
1"
#2890000
0"
b100000 $
#2895000
b111100000 !
1"
#2900000
0"
b100001 $
#2905000
b100011111 !
1"
#2910000
0"
b100010 $
#2915000
b100011110 !
1"
#2920000
0"
b100011 $
#2925000
b111100001 !
1"
#2930000
0"
b100100 $
#2935000
b100011100 !
1"
#2940000
0"
b100101 $
#2945000
b111100011 !
1"
#2950000
0"
b100110 $
#2955000
b111100010 !
1"
#2960000
0"
b100111 $
#2965000
b100011101 !
1"
#2970000
0"
b101000 $
#2975000
b100011000 !
1"
#2980000
0"
b101001 $
#2985000
b111100111 !
1"
#2990000
0"
b101010 $
#2995000
b111100110 !
1"
#3000000
0"
b101011 $
#3005000
b100011001 !
1"
#3010000
0"
b101100 $
#3015000
b111100100 !
1"
#3020000
0"
b101101 $
#3025000
b100011011 !
1"
#3030000
0"
b101110 $
#3035000
b1001001111 !
1"
#3040000
0"
b101111 $
#3045000
b1010110000 !
1"
#3050000
0"
b110000 $
#3055000
b100010000 !
1"
#3060000
0"
b110001 $
#3065000
b111101111 !
1"
#3070000
0"
b110010 $
#3075000
b111101110 !
1"
#3080000
0"
b110011 $
#3085000
b100010001 !
1"
#3090000
0"
b110100 $
#3095000
b111101100 !
1"
#3100000
0"
b110101 $
#3105000
b100010011 !
1"
#3110000
0"
b110110 $
#3115000
b1001000111 !
1"
#3120000
0"
b110111 $
#3125000
b1010111000 !
1"
#3130000
0"
b111000 $
#3135000
b111101000 !
1"
#3140000
0"
b111001 $
#3145000
b100010111 !
1"
#3150000
0"
b111010 $
#3155000
b1001000011 !
1"
#3160000
0"
b111011 $
#3165000
b1010111100 !
1"
#3170000
0"
b111100 $
#3175000
b1001000001 !
1"
#3180000
0"
b111101 $
#3185000
b1010111110 !
1"
#3190000
0"
b111110 $
#3195000
b1010111111 !
1"
#3200000
0"
b111111 $
#3205000
b1001000000 !
1"
#3210000
0"
b1000000 $
#3215000
b111000000 !
1"
#3220000
0"
b1000001 $
#3225000
b100111111 !
1"
#3230000
0"
b1000010 $
#3235000
b100111110 !
1"
#3240000
0"
b1000011 $
#3245000
b111000001 !
1"
#3250000
0"
b1000100 $
#3255000
b100111100 !
1"
#3260000
0"
b1000101 $
#3265000
b111000011 !
1"
#3270000
0"
b1000110 $
#3275000
b111000010 !
1"
#3280000
0"
b1000111 $
#3285000
b100111101 !
1"
#3290000
0"
b1001000 $
#3295000
b100111000 !
1"
#3300000
0"
b1001001 $
#3305000
b111000111 !
1"
#3310000
0"
b1001010 $
#3315000
b111000110 !
1"
#3320000
0"
b1001011 $
#3325000
b100111001 !
1"
#3330000
0"
b1001100 $
#3335000
b111000100 !
1"
#3340000
0"
b1001101 $
#3345000
b100111011 !
1"
#3350000
0"
b1001110 $
#3355000
b1001101111 !
1"
#3360000
0"
b1001111 $
#3365000
b1010010000 !
1"
#3370000
0"
b1010000 $
#3375000
b100110000 !
1"
#3380000
0"
b1010001 $
#3385000
b111001111 !
1"
#3390000
0"
b1010010 $
#3395000
b111001110 !
1"
#3400000
0"
b1010011 $
#3405000
b100110001 !
1"
#3410000
0"
b1010100 $
#3415000
b111001100 !
1"
#3420000
0"
b1010101 $
#3425000
b100110011 !
1"
#3430000
0"
b1010110 $
#3435000
b1001100111 !
1"
#3440000
0"
b1010111 $
#3445000
b1010011000 !
1"
#3450000
0"
b1011000 $
#3455000
b111001000 !
1"
#3460000
0"
b1011001 $
#3465000
b100110111 !
1"
#3470000
0"
b1011010 $
#3475000
b1001100011 !
1"
#3480000
0"
b1011011 $
#3485000
b1010011100 !
1"
#3490000
0"
b1011100 $
#3495000
b1001100001 !
1"
#3500000
0"
b1011101 $
#3505000
b1010011110 !
1"
#3510000
0"
b1011110 $
#3515000
b1010011111 !
1"
#3520000
0"
b1011111 $
#3525000
b1001100000 !
1"
#3530000
0"
b1100000 $
#3535000
b100100000 !
1"
#3540000
0"
b1100001 $
#3545000
b111011111 !
1"
#3550000
0"
b1100010 $
#3555000
b111011110 !
1"
#3560000
0"
b1100011 $
#3565000
b100100001 !
1"
#3570000
0"
b1100100 $
#3575000
b111011100 !
1"
#3580000
0"
b1100101 $
#3585000
b100100011 !
1"
#3590000
0"
b1100110 $
#3595000
b1001110111 !
1"
#3600000
0"
b1100111 $
#3605000
b1010001000 !
1"
#3610000
0"
b1101000 $
#3615000
b111011000 !
1"
#3620000
0"
b1101001 $
#3625000
b100100111 !
1"
#3630000
0"
b1101010 $
#3635000
b1001110011 !
1"
#3640000
0"
b1101011 $
#3645000
b1010001100 !
1"
#3650000
0"
b1101100 $
#3655000
b1001110001 !
1"
#3660000
0"
b1101101 $
#3665000
b1010001110 !
1"
#3670000
0"
b1101110 $
#3675000
b1010001111 !
1"
#3680000
0"
b1101111 $
#3685000
b1001110000 !
1"
#3690000
0"
b1110000 $
#3695000
b111010000 !
1"
#3700000
0"
b1110001 $
#3705000
b100101111 !
1"
#3710000
0"
b1110010 $
#3715000
b1001111011 !
1"
#3720000
0"
b1110011 $
#3725000
b1010000100 !
1"
#3730000
0"
b1110100 $
#3735000
b1001111001 !
1"
#3740000
0"
b1110101 $
#3745000
b1010000110 !
1"
#3750000
0"
b1110110 $
#3755000
b1010000111 !
1"
#3760000
0"
b1110111 $
#3765000
b1001111000 !
1"
#3770000
0"
b1111000 $
#3775000
b1001111101 !
1"
#3780000
0"
b1111001 $
#3785000
b1010000010 !
1"
#3790000
0"
b1111010 $
#3795000
b1010000011 !
1"
#3800000
0"
b1111011 $
#3805000
b1001111100 !
1"
#3810000
0"
b1111100 $
#3815000
b1010000001 !
1"
#3820000
0"
b1111101 $
#3825000
b1001111110 !
1"
#3830000
0"
b1111110 $
#3835000
b1001111111 !
1"
#3840000
0"
b1111111 $
#3845000
b1010000000 !
1"
#3850000
0"
b10000000 $
#3855000
b110000000 !
1"
#3860000
0"
b10000001 $
#3865000
b101111111 !
1"
#3870000
0"
b10000010 $
#3875000
b101111110 !
1"
#3880000
0"
b10000011 $
#3885000
b110000001 !
1"
#3890000
0"
b10000100 $
#3895000
b101111100 !
1"
#3900000
0"
b10000101 $
#3905000
b110000011 !
1"
#3910000
0"
b10000110 $
#3915000
b110000010 !
1"
#3920000
0"
b10000111 $
#3925000
b101111101 !
1"
#3930000
0"
b10001000 $
#3935000
b101111000 !
1"
#3940000
0"
b10001001 $
#3945000
b110000111 !
1"
#3950000
0"
b10001010 $
#3955000
b110000110 !
1"
#3960000
0"
b10001011 $
#3965000
b101111001 !
1"
#3970000
0"
b10001100 $
#3975000
b110000100 !
1"
#3980000
0"
b10001101 $
#3985000
b101111011 !
1"
#3990000
0"
b10001110 $
#3995000
b1000101111 !
1"
#4000000
0"
b10001111 $
#4005000
b1011010000 !
1"
#4010000
0"
b10010000 $
#4015000
b101110000 !
1"
#4020000
0"
b10010001 $
#4025000
b110001111 !
1"
#4030000
0"
b10010010 $
#4035000
b110001110 !
1"
#4040000
0"
b10010011 $
#4045000
b101110001 !
1"
#4050000
0"
b10010100 $
#4055000
b110001100 !
1"
#4060000
0"
b10010101 $
#4065000
b101110011 !
1"
#4070000
0"
b10010110 $
#4075000
b1000100111 !
1"
#4080000
0"
b10010111 $
#4085000
b1011011000 !
1"
#4090000
0"
b10011000 $
#4095000
b110001000 !
1"
#4100000
0"
b10011001 $
#4105000
b101110111 !
1"
#4110000
0"
b10011010 $
#4115000
b1000100011 !
1"
#4120000
0"
b10011011 $
#4125000
b1011011100 !
1"
#4130000
0"
b10011100 $
#4135000
b1000100001 !
1"
#4140000
0"
b10011101 $
#4145000
b1011011110 !
1"
#4150000
0"
b10011110 $
#4155000
b1011011111 !
1"
#4160000
0"
b10011111 $
#4165000
b1000100000 !
1"
#4170000
0"
b10100000 $
#4175000
b101100000 !
1"
#4180000
0"
b10100001 $
#4185000
b110011111 !
1"
#4190000
0"
b10100010 $
#4195000
b110011110 !
1"
#4200000
0"
b10100011 $
#4205000
b101100001 !
1"
#4210000
0"
b10100100 $
#4215000
b110011100 !
1"
#4220000
0"
b10100101 $
#4225000
b101100011 !
1"
#4230000
0"
b10100110 $
#4235000
b1000110111 !
1"
#4240000
0"
b10100111 $
#4245000
b1011001000 !
1"
#4250000
0"
b10101000 $
#4255000
b110011000 !
1"
#4260000
0"
b10101001 $
#4265000
b101100111 !
1"
