.Xil/Vivado-4596-DESKTOP-89OFCK6/realtime/xfft_1_stub.v
// Copyright 1986-2022 Xilinx, Inc. All Rights Reserved.
// Copyright 2022-2023 Advanced Micro Devices, Inc. All Rights Reserved.

// This empty module with port declaration file causes synthesis tools to infer a black box for IP.
// Please paste the declaration into a Verilog source file or add the file as an additional source.
(* x_core_info = "xfft_v9_1_9,Vivado 2023.1" *)
module xfft_1(aclk, s_axis_config_tdata, 
  s_axis_config_tvalid, s_axis_config_tready, s_axis_data_tdata, s_axis_data_tvalid, 
  s_axis_data_tready, s_axis_data_tlast, m_axis_data_tdata, m_axis_data_tvalid, 
  m_axis_data_tready, m_axis_data_tlast, event_frame_started, event_tlast_unexpected, 
  event_tlast_missing, event_status_channel_halt, event_data_in_channel_halt, 
  event_data_out_channel_halt);
  input aclk /* synthesis syn_isclock = 1 */;
  input [15:0]s_axis_config_tdata;
  input s_axis_config_tvalid;
  output s_axis_config_tready;
  input [31:0]s_axis_data_tdata;
  input s_axis_data_tvalid;
  output s_axis_data_tready;
  input s_axis_data_tlast;
  output [31:0]m_axis_data_tdata;
  output m_axis_data_tvalid;
  input m_axis_data_tready;
  output m_axis_data_tlast;
  output event_frame_started;
  output event_tlast_unexpected;
  output event_tlast_missing;
  output event_status_channel_halt;
  output event_data_in_channel_halt;
  output event_data_out_channel_halt;
endmodule

sim/fft_tb.sv
`timescale 1ns / 1ps
`default_nettype none

module fft_tb();

  logic clk_in;
  logic rst_in;

  logic [31:0] fft_data;
  logic [31:0] fft_out_data;

  logic fft_valid; // used by the external master to signal that it is able to provide data (critical in pipelining)
  logic fft_last; // asserted by the external master on the last sample of the frame (can be used to regulate flow of data)
  logic fft_ready; // used by the core to signal that it is ready to accept data (can be used to begin recording)
  logic fft_out_last; // asserted by the core on the last sample of the frame (will begin reporting data)
  logic fft_out_valid; // asserted by the core to signal that it is able to provide status data
  logic fft_out_ready; // asserted by the external slave to signal that it is ready to accept data (critical in pipelining)

  logic [7:0] audio_data;
  logic [10:0] fft_data_count;

  
  xfft_1 fft(
    .aclk(clk_in),
    .s_axis_data_tvalid(fft_valid), .s_axis_data_tdata(fft_data),
    .s_axis_data_tlast(fft_last), .s_axis_data_tready(fft_ready), 
    .s_axis_config_tdata(0), .s_axis_config_tvalid(0), .s_axis_config_tready(),
    .m_axis_data_tdata(fft_out_data), .m_axis_data_tvalid(fft_out_valid),
    .m_axis_data_tlast(fft_out_last), .m_axis_data_tready(fft_out_ready),
    .event_frame_started(), .event_tlast_unexpected(), .event_tlast_missing(),
    .event_data_in_channel_halt(), .event_data_out_channel_halt());

  always begin // 100 MHz clock
      #5; 
      clk_in = !clk_in;
  end

  always begin  
      #10;
      fft_data = {audio_data,8'b0};
      fft_data_count = fft_data_count + 1;    
      fft_last = (fft_data_count == 2047); 
  end

  initial begin
    $dumpfile("fft_tb.vcd"); 
    $dumpvars(0,fft_tb);
    $display("Starting Sim");
    clk_in = 0;
    rst_in = 0;
    #10;
    // Reset all variables
    rst_in = 1;
    #5;
    fft_valid = 0;
    fft_data = 0;
    fft_last = 0;
    fft_ready = 0;
    fft_out_data = 0;
    fft_out_last = 0;
    fft_out_valid = 0;
    fft_out_ready = 0;
    fft_data_count = 0;    
    #10;
    // Begin Test
    #10;
    rst_in = 0; 
    /*
    for (int i = 0; i<100000; i=i+1)begin // Begin FFT Analysis
      if (fft_last)begin
        audio_valid_in = 0;
        dummy = i;
      end else if (audio_valid_in) begin
        audio_data = i; 
      end else begin
        audio_data = 0;
        if (i == dummy*2) begin // Switch with conditions for FFT to finish calculating
          audio_valid_in = 1;
        end
      end
      #5; // Check clock cycling
    end
    */

    for (int i = 0; i<33333; i=i+1)begin // Begin FFT Analysis
      if (fft_last)begin
        fft_out_ready = 1; // Check - holds last value of fft if not ready to get in more data! This is good! Control, FFT calculations
        fft_valid = 1; // Without valid in, FFT don't work.
      end
      audio_data = 8'b1111_1111; 
      #5; // Check clock cycling
    end
    for (int i = 0; i<33333; i=i+1)begin // Begin FFT Analysis
      audio_data = 8'b0000_1111; 
      #5; // Check clock cycling
    end
    for (int i = 0; i<33333; i=i+1)begin // Begin FFT Analysis
      audio_data = 8'b1000_1111; 
      #5; // Check clock cycling
    end

    $display("Simulation finished");
    $finish;
  end
endmodule
`default_nettype wire

ip_2_tb/ip_2_tb.sim/sim_1/behav/xsim/fft_tb.vcd
$date
   Mon Dec 11 22:32:19 2023
$end
$version
  2023.1
$end
$timescale
  1ps
$end
$scope module fft_tb $end
$var reg 1 ! clk_in $end
$var reg 1 " rst_in $end
$var reg 32 # fft_data [31:0] $end
$var reg 32 $ fft_out_data [31:0] $end
$var reg 1 % fft_valid $end
$var reg 1 & fft_last $end
$var reg 1 ' fft_ready $end
$var reg 1 ( fft_out_last $end
$var reg 1 ) fft_out_valid $end
$var reg 1 * fft_out_ready $end
$var reg 8 + audio_data [7:0] $end
$var reg 11 , fft_data_count [10:0] $end
$scope module fft $end
$var wire 1 - aclk $end
$var wire 16 . s_axis_config_tdata $end
$var wire 1 / s_axis_config_tvalid $end
$var wire 1 0 s_axis_config_tready $end
$var wire 32 1 s_axis_data_tdata $end
$var wire 1 2 s_axis_data_tvalid $end
$var wire 1 3 s_axis_data_tready $end
$var wire 1 4 s_axis_data_tlast $end
$var wire 32 5 m_axis_data_tdata $end
$var wire 1 6 m_axis_data_tvalid $end
$var wire 1 7 m_axis_data_tready $end
$var wire 1 8 m_axis_data_tlast $end
$var wire 1 9 event_frame_started $end
$var wire 1 : event_tlast_unexpected $end
$var wire 1 ; event_tlast_missing $end
$var wire 1 < event_status_channel_halt $end
$var wire 1 = event_data_in_channel_halt $end
$var wire 1 > event_data_out_channel_halt $end
$upscope $end
$scope begin Block85_3 $end
$var reg 32 ? i [31:0] $end
$upscope $end
$scope begin Block93_4 $end
$var reg 32 @ i [31:0] $end
$upscope $end
$scope begin Block97_5 $end
$var reg 32 A i [31:0] $end
$upscope $end
$upscope $end
$enddefinitions $end
#0
$dumpvars
0!
0"
bx #
b0 $
x%
x&
0'
0(
0)
x*
bx +
bx ,
0-
b0 .
0/
00
bx 1
x2
03
x4
b0 5
06
x7
08
09
0:
0;
0<
0=
0>
b0 ?
b0 @
b0 A
$end
#5000
1!
1'
1-
10
13
#10000
0!
1"
b0xxxxxxxx00000000 #
0-
b0xxxxxxxx00000000 1
#15000
1!
b0 #
0%
0&
0'
0*
b0 ,
1-
02
#20000
0!
b0xxxxxxxx00000000 #
b1 ,
0-
#25000
1!
1-
#30000
0!
b10 ,
0-
#35000
1!
0"
b11111111 +
1-
#40000
0!
b1111111100000000 #
b11 ,
0-
b1 ?
#45000
1!
1-
b10 ?
#50000
0!
b100 ,
0-
b11 ?
#55000
1!
1-
b100 ?
#60000
0!
b101 ,
0-
b101 ?
#65000
1!
1-
b110 ?
#70000
0!
b110 ,
0-
b111 ?
#75000
1!
1-
b1000 ?
#80000
0!
b111 ,
0-
b1001 ?
#85000
1!
1-
b1010 ?
#90000
0!
b1000 ,
0-
b1011 ?
#95000
1!
1-
b1100 ?
#100000
0!
b1001 ,
0-
b1101 ?
#105000
1!
1-
b1110 ?
#110000
0!
b1010 ,
0-
b1111 ?
#115000
1!
1-
b10000 ?
#120000
0!
b1011 ,
0-
b10001 ?
#125000
1!
1-
b10010 ?
#130000
0!
b1100 ,
0-
b10011 ?
#135000
1!
1-
b10100 ?
#140000
0!
b1101 ,
0-
b10101 ?
#145000
1!
1-
b10110 ?
#150000
0!
b1110 ,
0-
b10111 ?
#155000
1!
1-
b11000 ?
#160000
0!
b1111 ,
0-
b11001 ?
#165000
1!
1-
b11010 ?
#170000
0!
b10000 ,
0-
b11011 ?
#175000
1!
1-
b11100 ?
#180000
0!
b10001 ,
0-
b11101 ?
#185000
1!
1-
b11110 ?
#190000
0!
b10010 ,
0-
b11111 ?
#195000
1!
1-
b100000 ?
#200000
0!
b10011 ,
0-
b100001 ?
#205000
1!
1-
b100010 ?
#210000
0!
b10100 ,
0-
b100011 ?
#215000
1!
1-
b100100 ?
#220000
0!
b10101 ,
0-
b100101 ?
#225000
1!
1-
b100110 ?
#230000
0!
b10110 ,
0-
b100111 ?
#235000
1!
1-
b101000 ?
#240000
0!
b10111 ,
0-
b101001 ?
#245000
1!
1-
b101010 ?
#250000
0!
b11000 ,
0-
b101011 ?
#255000
1!
1-
b101100 ?
#260000
0!
b11001 ,
0-
b101101 ?
#265000
1!
1-
b101110 ?
#270000
0!
b11010 ,
0-
b101111 ?
#275000
1!
1-
b110000 ?
#280000
0!
b11011 ,
0-
b110001 ?
#285000
1!
1-
b110010 ?
#290000
0!
b11100 ,
0-
b110011 ?
#295000
1!
1-
b110100 ?
#300000
0!
b11101 ,
0-
b110101 ?
#305000
1!
1-
b110110 ?
#310000
0!
b11110 ,
0-
b110111 ?
#315000
1!
1-
b111000 ?
#320000
0!
b11111 ,
0-
b111001 ?
#325000
1!
1-
b111010 ?
#330000
0!
b100000 ,
0-
b111011 ?
#335000
1!
1-
b111100 ?
#340000
0!
b100001 ,
0-
b111101 ?
#345000
1!
1-
b111110 ?
#350000
0!
b100010 ,
0-
b111111 ?
#355000
1!
1-
b1000000 ?
#360000
0!
b100011 ,
0-
b1000001 ?
#365000
1!
1-
b1000010 ?
#370000
0!
b100100 ,
0-
b1000011 ?
#375000
1!
1-
b1000100 ?
#380000
0!
b100101 ,
0-
b1000101 ?
#385000
1!
1-
b1000110 ?
#390000
0!
b100110 ,
0-
b1000111 ?
#395000
1!
1-
b1001000 ?
#400000
0!
b100111 ,
0-
b1001001 ?
#405000
1!
1-
b1001010 ?
#410000
0!
b101000 ,
0-
b1001011 ?
#415000
1!
1-
b1001100 ?
#420000
0!
b101001 ,
0-
b1001101 ?
#425000
1!
1-
b1001110 ?
#430000
0!
b101010 ,
0-
b1001111 ?
#435000
1!
1-
b1010000 ?
#440000
0!
b101011 ,
0-
b1010001 ?
#445000
1!
1-
b1010010 ?
#450000
0!
b101100 ,
0-
b1010011 ?
#455000
1!
1-
b1010100 ?
#460000
0!
b101101 ,
0-
b1010101 ?
#465000
1!
1-
b1010110 ?
#470000
0!
b101110 ,
0-
b1010111 ?
#475000
1!
1-
b1011000 ?
#480000
0!
b101111 ,
0-
b1011001 ?
#485000
1!
1-
b1011010 ?
#490000
0!
b110000 ,
0-
b1011011 ?
#495000
1!
1-
b1011100 ?
#500000
0!
b110001 ,
0-
b1011101 ?
#505000
1!
1-
b1011110 ?
#510000
0!
b110010 ,
0-
b1011111 ?
#515000
1!
1-
b1100000 ?
#520000
0!
b110011 ,
0-
b1100001 ?
#525000
1!
1-
b1100010 ?
#530000
0!
b110100 ,
0-
b1100011 ?
#535000
1!
1-
b1100100 ?
#540000
0!
b110101 ,
0-
b1100101 ?
#545000
1!
1-
b1100110 ?
#550000
0!
b110110 ,
0-
b1100111 ?
#555000
1!
1-
b1101000 ?
#560000
0!
b110111 ,
0-
b1101001 ?
#565000
1!
1-
b1101010 ?
#570000
0!
b111000 ,
0-
b1101011 ?
#575000
1!
1-
b1101100 ?
#580000
0!
b111001 ,
0-
b1101101 ?
#585000
1!
1-
b1101110 ?
#590000
0!
b111010 ,
0-
b1101111 ?
#595000
1!
1-
b1110000 ?
#600000
0!
b111011 ,
0-
b1110001 ?
#605000
1!
1-
b1110010 ?
#610000
0!
b111100 ,
0-
b1110011 ?
#615000
1!
1-
b1110100 ?
#620000
0!
b111101 ,
0-
b1110101 ?
#625000
1!
1-
b1110110 ?
#630000
0!
b111110 ,
0-
b1110111 ?
#635000
1!
1-
b1111000 ?
#640000
0!
b111111 ,
0-
b1111001 ?
#645000
1!
1-
b1111010 ?
#650000
0!
b1000000 ,
0-
b1111011 ?
#655000
1!
1-
b1111100 ?
#660000
0!
b1000001 ,
0-
b1111101 ?
#665000
1!
1-
b1111110 ?
#670000
0!
b1000010 ,
0-
b1111111 ?
#675000
1!
1-
b10000000 ?
#680000
0!
b1000011 ,
0-
b10000001 ?
#685000
1!
1-
b10000010 ?
#690000
0!
b1000100 ,
0-
b10000011 ?
#695000
1!
1-
b10000100 ?
#700000
0!
b1000101 ,
0-
b10000101 ?
#705000
1!
1-
b10000110 ?
#710000
0!
b1000110 ,
0-
b10000111 ?
#715000
1!
1-
b10001000 ?
#720000
0!
b1000111 ,
0-
b10001001 ?
#725000
1!
1-
b10001010 ?
#730000
0!
b1001000 ,
0-
b10001011 ?
#735000
1!
1-
b10001100 ?
#740000
0!
b1001001 ,
0-
b10001101 ?
#745000
1!
1-
b10001110 ?
#750000
0!
b1001010 ,
0-
b10001111 ?
#755000
1!
1-
b10010000 ?
#760000
0!
b1001011 ,
0-
b10010001 ?
#765000
1!
1-
b10010010 ?
#770000
0!
b1001100 ,
0-
b10010011 ?
#775000
1!
1-
b10010100 ?
#780000
0!
b1001101 ,
0-
b10010101 ?
#785000
1!
1-
b10010110 ?
#790000
0!
b1001110 ,
0-
b10010111 ?
#795000
1!
1-
b10011000 ?
#800000
0!
b1001111 ,
0-
b10011001 ?
#805000
1!
1-
b10011010 ?
#810000
0!
b1010000 ,
0-
b10011011 ?
#815000
1!
1-
b10011100 ?
#820000
0!
b1010001 ,
0-
b10011101 ?
#825000
1!
1-
b10011110 ?
#830000
0!
b1010010 ,
0-
b10011111 ?
#835000
1!
1-
b10100000 ?
#840000
0!
b1010011 ,
0-
b10100001 ?
#845000
1!
1-
b10100010 ?
#850000
0!
b1010100 ,
0-
b10100011 ?
#855000
1!
1-
b10100100 ?
#860000
0!
b1010101 ,
0-
b10100101 ?
#865000
1!
1-
b10100110 ?
#870000
0!
b1010110 ,
0-
b10100111 ?
#875000
1!
1-
b10101000 ?
#880000
0!
b1010111 ,
0-
b10101001 ?
#885000
1!
1-
b10101010 ?
#890000
0!
b1011000 ,
0-
b10101011 ?
#895000
1!
1-
b10101100 ?
#900000
0!
b1011001 ,
0-
b10101101 ?
#905000
1!
1-
b10101110 ?
#910000
0!
b1011010 ,
0-
b10101111 ?
#915000
1!
1-
b10110000 ?
#920000
0!
b1011011 ,
0-
b10110001 ?
#925000
1!
1-
b10110010 ?
#930000
0!
b1011100 ,
0-
b10110011 ?
#935000
1!
1-
b10110100 ?
#940000
0!
b1011101 ,
0-
b10110101 ?
#945000
1!
1-
b10110110 ?
#950000
0!
b1011110 ,
0-
b10110111 ?
#955000
1!
1-
b10111000 ?
#960000
0!
b1011111 ,
0-
b10111001 ?
#965000
1!
1-
b10111010 ?
#970000
0!
b1100000 ,
0-
b10111011 ?
#975000
1!
1-
b10111100 ?
#980000
0!
b1100001 ,
0-
b10111101 ?
#985000
1!
1-
b10111110 ?
#990000
0!
b1100010 ,
0-
b10111111 ?
#995000
1!
1-
b11000000 ?
#1000000
0!
b1100011 ,
0-
b11000001 ?
