.Xil/Vivado-4596-DESKTOP-89OFCK6/realtime/xfft_1_stub.v
// Copyright 1986-2022 Xilinx, Inc. All Rights Reserved.
// Copyright 2022-2023 Advanced Micro Devices, Inc. All Rights Reserved.

// This empty module with port declaration file causes synthesis tools to infer a black box for IP.
// Please paste the declaration into a Verilog source file or add the file as an additional source.
(* x_core_info = "xfft_v9_1_9,Vivado 2023.1" *)
module xfft_1(aclk, s_axis_config_tdata, 
  s_axis_config_tvalid, s_axis_config_tready, s_axis_data_tdata, s_axis_data_tvalid, 
  s_axis_data_tready, s_axis_data_tlast, m_axis_data_tdata, m_axis_data_tvalid, 
  m_axis_data_tready, m_axis_data_tlast, event_frame_started, event_tlast_unexpected, 
  event_tlast_missing, event_status_channel_halt, event_data_in_channel_halt, 
  event_data_out_channel_halt);
  input aclk /* synthesis syn_isclock = 1 */;
  input [15:0]s_axis_config_tdata;
  input s_axis_config_tvalid;
  output s_axis_config_tready;
  input [31:0]s_axis_data_tdata;
  input s_axis_data_tvalid;
  output s_axis_data_tready;
  input s_axis_data_tlast;
  output [31:0]m_axis_data_tdata;
  output m_axis_data_tvalid;
  input m_axis_data_tready;
  output m_axis_data_tlast;
  output event_frame_started;
  output event_tlast_unexpected;
  output event_tlast_missing;
  output event_status_channel_halt;
  output event_data_in_channel_halt;
  output event_data_out_channel_halt;
endmodule

sim/fft_tb.sv
`timescale 1ns / 1ps
`default_nettype none

module fft_tb();

  logic clk_in;
  logic rst_in;

  logic fft_valid;
  logic [7:0] audio_data;
  logic [31:0] fft_data;
  logic fft_last;
  logic fft_ready;
  logic [31:0] fft_out_data;
  logic fft_out_last;
  logic fft_out_valid;
  logic fft_out_ready;


  xfft_1 fft(
    .aclk(clk_in),
    .s_axis_data_tvalid(fft_valid), .s_axis_data_tdata(fft_data),
    .s_axis_data_tlast(fft_last), .s_axis_data_tready(fft_ready), 
    .s_axis_config_tdata(0), .s_axis_config_tvalid(0), .s_axis_config_tready(),
    .m_axis_data_tdata(fft_out_data), .m_axis_data_tvalid(fft_out_valid),
    .m_axis_data_tlast(fft_out_last), .m_axis_data_tready(fft_out_ready),
    .event_frame_started(), .event_tlast_unexpected(), .event_tlast_missing(),
    .event_data_in_channel_halt(), .event_data_out_channel_halt());

  always begin // 100 MHz clock
      #5; 
      clk_in = !clk_in;
  end

  initial begin
    $dumpfile("fft_tb.vcd"); 
    $dumpvars(0,fft_tb);
    $display("Starting Sim");
    rst_in = 0;
    #10;
    rst_in = 1;
    fft_valid = 0;
    fft_data = 0;
    fft_last = 0;
    fft_ready = 0;
    fft_out_data = 0;
    fft_out_last = 0;
    fft_out_valid = 0;
    fft_out_ready = 0;
    audio_data = 0;
    #10;

    rst_in = 0;
    fft_valid = 1;
    fft_last = 1;

    for (int i = 0; i<10000; i=i+1)begin
      audio_data = i;
      #10;
    end

    $display("Simulation finished");
    $finish;
  end
endmodule
`default_nettype wire

ip_2_tb/ip_2_tb.sim/sim_1/behav/xsim/fft_tb.vcd
$date
   Mon Dec 11 15:24:31 2023
$end
$version
  2023.1
$end
$timescale
  1ps
$end
$scope module fft_tb $end
$var reg 1 ! clk_in $end
$var reg 1 " rst_in $end
$var reg 1 # fft_valid $end
$var reg 8 $ audio_data [7:0] $end
$var reg 32 % fft_data [31:0] $end
$var reg 1 & fft_last $end
$var reg 1 ' fft_ready $end
$var reg 32 ( fft_out_data [31:0] $end
$var reg 1 ) fft_out_last $end
$var reg 1 * fft_out_valid $end
$var reg 1 + fft_out_ready $end
$scope module fft $end
$var wire 1 , aclk $end
$var wire 16 - s_axis_config_tdata $end
$var wire 1 . s_axis_config_tvalid $end
$var wire 1 / s_axis_config_tready $end
$var wire 32 0 s_axis_data_tdata $end
$var wire 1 1 s_axis_data_tvalid $end
$var wire 1 2 s_axis_data_tready $end
$var wire 1 3 s_axis_data_tlast $end
$var wire 32 4 m_axis_data_tdata $end
$var wire 1 5 m_axis_data_tvalid $end
$var wire 1 6 m_axis_data_tready $end
$var wire 1 7 m_axis_data_tlast $end
$var wire 1 8 event_frame_started $end
$var wire 1 9 event_tlast_unexpected $end
$var wire 1 : event_tlast_missing $end
$var wire 1 ; event_status_channel_halt $end
$var wire 1 < event_data_in_channel_halt $end
$var wire 1 = event_data_out_channel_halt $end
$upscope $end
$scope begin Block57_2 $end
$var reg 32 > i [31:0] $end
$upscope $end
$upscope $end
$enddefinitions $end
#0
$dumpvars
x!
0"
x#
bx $
bx %
x&
0'
b0 (
0)
0*
x+
x,
b0 -
0.
0/
bx 0
x1
02
x3
b0 4
05
x6
07
08
09
0:
0;
0<
0=
b0 >
$end
#10000
1"
0#
b0 $
b0 %
0&
0+
b0 0
06
#20000
0"
1#
1&
11
13
#30000
b1 $
b1 >
#40000
b10 $
b10 >
#50000
b11 $
b11 >
#60000
b100 $
b100 >
#70000
b101 $
b101 >
#80000
b110 $
b110 >
#90000
b111 $
b111 >
#100000
b1000 $
b1000 >
#110000
b1001 $
b1001 >
#120000
b1010 $
b1010 >
#130000
b1011 $
b1011 >
#140000
b1100 $
b1100 >
#150000
b1101 $
b1101 >
#160000
b1110 $
b1110 >
#170000
b1111 $
b1111 >
#180000
b10000 $
b10000 >
#190000
b10001 $
b10001 >
#200000
b10010 $
b10010 >
#210000
b10011 $
b10011 >
#220000
b10100 $
b10100 >
#230000
b10101 $
b10101 >
#240000
b10110 $
b10110 >
#250000
b10111 $
b10111 >
#260000
b11000 $
b11000 >
#270000
b11001 $
b11001 >
#280000
b11010 $
b11010 >
#290000
b11011 $
b11011 >
#300000
b11100 $
b11100 >
#310000
b11101 $
b11101 >
#320000
b11110 $
b11110 >
#330000
b11111 $
b11111 >
#340000
b100000 $
b100000 >
#350000
b100001 $
b100001 >
#360000
b100010 $
b100010 >
#370000
b100011 $
b100011 >
#380000
b100100 $
b100100 >
#390000
b100101 $
b100101 >
#400000
b100110 $
b100110 >
#410000
b100111 $
b100111 >
#420000
b101000 $
b101000 >
#430000
b101001 $
b101001 >
#440000
b101010 $
b101010 >
#450000
b101011 $
b101011 >
#460000
b101100 $
b101100 >
#470000
b101101 $
b101101 >
#480000
b101110 $
b101110 >
#490000
b101111 $
b101111 >
#500000
b110000 $
b110000 >
#510000
b110001 $
b110001 >
#520000
b110010 $
b110010 >
#530000
b110011 $
b110011 >
#540000
b110100 $
b110100 >
#550000
b110101 $
b110101 >
#560000
b110110 $
b110110 >
#570000
b110111 $
b110111 >
#580000
b111000 $
b111000 >
#590000
b111001 $
b111001 >
#600000
b111010 $
b111010 >
#610000
b111011 $
b111011 >
#620000
b111100 $
b111100 >
#630000
b111101 $
b111101 >
#640000
b111110 $
b111110 >
#650000
b111111 $
b111111 >
#660000
b1000000 $
b1000000 >
#670000
b1000001 $
b1000001 >
#680000
b1000010 $
b1000010 >
#690000
b1000011 $
b1000011 >
#700000
b1000100 $
b1000100 >
#710000
b1000101 $
b1000101 >
#720000
b1000110 $
b1000110 >
#730000
b1000111 $
b1000111 >
#740000
b1001000 $
b1001000 >
#750000
b1001001 $
b1001001 >
#760000
b1001010 $
b1001010 >
#770000
b1001011 $
b1001011 >
#780000
b1001100 $
b1001100 >
#790000
b1001101 $
b1001101 >
#800000
b1001110 $
b1001110 >
#810000
b1001111 $
b1001111 >
#820000
b1010000 $
b1010000 >
#830000
b1010001 $
b1010001 >
#840000
b1010010 $
b1010010 >
#850000
b1010011 $
b1010011 >
#860000
b1010100 $
b1010100 >
#870000
b1010101 $
b1010101 >
#880000
b1010110 $
b1010110 >
#890000
b1010111 $
b1010111 >
#900000
b1011000 $
b1011000 >
#910000
b1011001 $
b1011001 >
#920000
b1011010 $
b1011010 >
#930000
b1011011 $
b1011011 >
#940000
b1011100 $
b1011100 >
#950000
b1011101 $
b1011101 >
#960000
b1011110 $
b1011110 >
#970000
b1011111 $
b1011111 >
#980000
b1100000 $
b1100000 >
#990000
b1100001 $
b1100001 >
#1000000
b1100010 $
b1100010 >
