Archives/Lab 4/hdl/tm_choice.sv
module tm_choice (
  input wire [7:0] data_in,
  output logic [8:0] qm_out
  );
  logic [7:0] counter;
  logic [8:0] intermediate;
  always_comb begin  
    qm_out[0] = data_in[0];
    counter = 0;
    for (int i = 0; i < 8; i++) begin
        if (data_in[i] == 1)begin
            counter ++ ;            
        end
    end
    if (counter > 4 || (counter == 4 && data_in[0] == 0))begin
        for (int i = 0; i < 8; i++ ) begin
            qm_out[i+1] = ~(data_in[i+1] ^ qm_out[i]);
        end
        qm_out[8] = 0;   
    end else begin
        for (int i = 0; i < 8; i++ ) begin
            qm_out[i+1] = (data_in[i+1] ^ qm_out[i]);
        end
        qm_out[8] = 1;     
    end
end
endmodule

Archives/Lab 5/hdl/tmds_encoder.sv
module tmds_encoder(
  input wire clk_in,
  input wire rst_in,
  input wire [7:0] data_in,  // video data (red, green or blue)
  input wire [1:0] control_in, //for blue set to {vs,hs}, else will be 0
  input wire ve_in,  // video data enable, to choose between control or video signal
  output logic [9:0] tmds_out
);

  logic [8:0] q_m;
  //you can assume a functioning (version of tm_choice for you.)
  tm_choice mtm(
    .data_in(data_in),
    .qm_out(q_m));

  logic [4:0] tally;
  logic [8:0] counter;

  always_comb begin
    counter = q_m[0] + q_m[1] + q_m[2] + q_m[3] + q_m[4] + q_m[5] + q_m[6] + q_m[7];
  end

  always_ff @(posedge clk_in)begin
    if (rst_in)begin
        tally <= 0;
        tmds_out <= 0;    

    end else if (ve_in) begin
        if (tally == 0 || (counter == (8-counter)))begin
            tmds_out[9] <= ~q_m[8];
            tmds_out[8] <= q_m[8];
            tmds_out[7:0] <= (q_m[8] ? q_m[7:0] : ~q_m[7:0]);

            if (q_m[8] == 0)begin
                tally <= tally + (8 - counter - counter);
            end else begin
                tally <= tally + (counter - (8 - counter));
            end

        end else begin
            if ((tally[4] == 0 && counter > (8-counter)) || (tally[4] > 0 && counter < (8-counter)))begin
            tmds_out[9] <= 1;
            tmds_out[8] <= q_m[8];
            tmds_out[7:0] <= ~q_m[7:0];
            tally <= tally + {q_m[8], 1'b0} + (8 - counter - counter);


            end else begin
            tmds_out[9] <= 0;
            tmds_out[8] <= q_m[8];
            tmds_out[7:0] <= q_m[7:0];
            tally <= tally - {~q_m[8], 1'b0} + (counter - (8-counter));
            end
        end

    end else if (ve_in == 0) begin
        tally <= 0;
        if (control_in == 2'b00) begin
            tmds_out <= 10'b1101010100;
        end else if (control_in == 2'b01) begin
            tmds_out <= 10'b0010101011;
        end else if (control_in == 2'b10) begin
            tmds_out <= 10'b0101010100;
        end else if (control_in == 2'b11) begin
            tmds_out <= 10'b1010101011;
        end
    end
  end

endmodule //end tmds_encoder

Archives/Lab 4/sim/tmds_2_tb.sv

`timescale 1ns / 1ps
`default_nettype none


module tmds_2_tb();

  logic clk_in;
  logic rst_in;
	logic [7:0] data_in;
	logic [1:0] control_in;
	logic ve_in;
	logic [9:0] tmds_out;
  tmds_encoder uut(
  .clk_in(clk_in),
  .rst_in(rst_in),
  .data_in(data_in),  // video data (red, green or blue)
  .control_in(control_in),  // control data
  .ve_in(ve_in),  // video data enable, to choose between CD (when VDE=0) and VD (when VDE=1)
  .tmds_out(tmds_out)
  );

  always begin
      #5;  //every 5 ns switch...so period of clock is 10 ns...100 MHz clock
      clk_in = !clk_in;
  end
  //initial block...this is our test simulation
  initial begin
    $dumpfile("tmds_2_tb.vcd"); //file to store value change dump (vcd)
    $dumpvars(0,tmds_2_tb);
    $display("Starting Sim"); //print nice message at start
    clk_in = 0;
    rst_in = 1;
    control_in = 0;
    ve_in = 1;
    data_in = 0;;
    #10;
    rst_in=0;
    for(int i = 0; i<1024; i = i+1)begin
      data_in = i;
      #10;
    end
    control_in = 0;
    #100;
    control_in = 1;
    #100;
    control_in = 2;
    #100;
    control_in = 3;
    #100;
    ve_in = 0;
    control_in = 0;
    #100;
    control_in = 1;
    #100;
    control_in = 2;
    #100;
    control_in = 3;
    #100;
    ve_in = 1;
    #10;
    for(int i = 0; i<1024; i = i+1)begin
      data_in = 255-i;
      #10;
    end
    #500;
    $display("Finishing Sim"); //print nice message at end
    $finish;
  end
endmodule
`default_nettype wire

Archives/Lab 4/tmds_2_tb.vcd
$date
	Wed Oct 04 21:18:17 2023
$end
$version
	Icarus Verilog
$end
$timescale
	1ps
$end
$scope module tmds_2_tb $end
$var wire 10 ! tmds_out [9:0] $end
$var reg 1 " clk_in $end
$var reg 2 # control_in [1:0] $end
$var reg 8 $ data_in [7:0] $end
$var reg 1 % rst_in $end
$var reg 1 & ve_in $end
$scope module uut $end
$var wire 1 " clk_in $end
$var wire 2 ' control_in [1:0] $end
$var wire 8 ( data_in [7:0] $end
$var wire 1 % rst_in $end
$var wire 1 & ve_in $end
$var wire 9 ) q_m [8:0] $end
$var reg 9 * counter [8:0] $end
$var reg 5 + tally [4:0] $end
$var reg 10 , tmds_out [9:0] $end
$scope module mtm $end
$var wire 8 - data_in [7:0] $end
$var reg 8 . counter [7:0] $end
$var reg 9 / qm_out [8:0] $end
$scope begin $ivl_for_loop2 $end
$var integer 32 0 i [31:0] $end
$upscope $end
$scope begin $ivl_for_loop3 $end
$var integer 32 1 i [31:0] $end
$upscope $end
$scope begin $ivl_for_loop4 $end
$var integer 32 2 i [31:0] $end
$upscope $end
$upscope $end
$upscope $end
$scope begin $ivl_for_loop0 $end
$var integer 32 3 i [31:0] $end
$upscope $end
$scope begin $ivl_for_loop1 $end
$var integer 32 4 i [31:0] $end
$upscope $end
$upscope $end
$enddefinitions $end
$comment Show the parameter values. $end
$dumpall
$end
#0
$dumpvars
b0 4
b0 3
b1000 2
b0 1
b1000 0
b100000000 /
b0 .
b0 -
bx ,
bx +
b0 *
b100000000 )
b0 (
b0 '
1&
1%
b0 $
b0 #
0"
bx !
$end
#5000
b0 !
b0 ,
b0 +
1"
#10000
0"
0%
#15000
b11000 +
b100000000 !
b100000000 ,
1"
#20000
b1000 *
b1000 2
b1 .
b1000 0
b111111111 )
b111111111 /
0"
b1 $
b1 (
b1 -
b1 3
#25000
b0 +
b111111111 !
b111111111 ,
1"
#30000
b111 *
b1000 2
b1000 0
b1 .
b111111110 )
b111111110 /
0"
b10 $
b10 (
b10 -
b10 3
#35000
b110 +
b111111110 !
b111111110 ,
1"
#40000
b1 *
b1000 2
b1000 0
b10 .
b100000001 )
b100000001 /
0"
b11 $
b11 (
b11 -
b11 3
#45000
b0 +
b100000001 !
b100000001 ,
1"
#50000
b110 *
b1000 2
b1000 0
b1 .
b111111100 )
b111111100 /
0"
b100 $
b100 (
b100 -
b100 3
#55000
b100 +
b111111100 !
b111111100 ,
1"
#60000
b10 *
b1000 2
b1000 0
b10 .
b100000011 )
b100000011 /
0"
b101 $
b101 (
b101 -
b101 3
#65000
b0 +
b100000011 !
b100000011 ,
1"
#70000
b1 *
b1000 2
b1000 0
b10 .
b100000010 )
b100000010 /
0"
b110 $
b110 (
b110 -
b110 3
#75000
b11010 +
b100000010 !
b100000010 ,
1"
#80000
b111 *
b1000 2
b1000 0
b11 .
b111111101 )
b111111101 /
0"
b111 $
b111 (
b111 -
b111 3
#85000
b0 +
b111111101 !
b111111101 ,
1"
#90000
b101 *
b1000 2
b1000 0
b1 .
b111111000 )
b111111000 /
0"
b1000 $
b1000 (
b1000 -
b1000 3
#95000
b10 +
b111111000 !
b111111000 ,
1"
#100000
b11 *
b1000 2
b1000 0
b10 .
b100000111 )
b100000111 /
0"
b1001 $
b1001 (
b1001 -
b1001 3
#105000
b0 +
b100000111 !
b100000111 ,
1"
#110000
b10 *
b1000 2
b1000 0
b10 .
b100000110 )
b100000110 /
0"
b1010 $
b1010 (
b1010 -
b1010 3
#115000
b11100 +
b100000110 !
b100000110 ,
1"
#120000
b110 *
b1000 2
b1000 0
b11 .
b111111001 )
b111111001 /
0"
b1011 $
b1011 (
b1011 -
b1011 3
#125000
b0 +
b111111001 !
b111111001 ,
1"
#130000
b1 *
b1000 2
b1000 0
b10 .
b100000100 )
b100000100 /
0"
b1100 $
b1100 (
b1100 -
b1100 3
#135000
b11010 +
b100000100 !
b100000100 ,
1"
#140000
b111 *
b1000 2
b1000 0
b11 .
b111111011 )
b111111011 /
0"
b1101 $
b1101 (
b1101 -
b1101 3
#145000
b0 +
b111111011 !
b111111011 ,
1"
#150000
b110 *
b1000 2
b1000 0
b11 .
b111111010 )
b111111010 /
0"
b1110 $
b1110 (
b1110 -
b1110 3
#155000
b100 +
b111111010 !
b111111010 ,
1"
#160000
b10 *
b1000 2
b1000 0
b100 .
b100000101 )
b100000101 /
0"
b1111 $
b1111 (
b1111 -
b1111 3
#165000
b0 +
b100000101 !
b100000101 ,
1"
#170000
b100 *
b1000 2
b1000 0
b1 .
b111110000 )
b111110000 /
0"
b10000 $
b10000 (
b10000 -
b10000 3
#175000
b111110000 !
b111110000 ,
1"
#180000
b1000 2
b1000 0
b10 .
b100001111 )
b100001111 /
0"
b10001 $
b10001 (
b10001 -
b10001 3
#185000
b100001111 !
b100001111 ,
1"
#190000
b11 *
b1000 2
b1000 0
b10 .
b100001110 )
b100001110 /
0"
b10010 $
b10010 (
b10010 -
b10010 3
#195000
b11110 +
b100001110 !
b100001110 ,
1"
#200000
b101 *
b1000 2
b1000 0
b11 .
b111110001 )
b111110001 /
0"
b10011 $
b10011 (
b10011 -
b10011 3
#205000
b0 +
b111110001 !
b111110001 ,
1"
#210000
b10 *
b1000 2
b1000 0
b10 .
b100001100 )
b100001100 /
0"
b10100 $
b10100 (
b10100 -
b10100 3
#215000
b11100 +
b100001100 !
b100001100 ,
1"
#220000
b110 *
b1000 2
b1000 0
b11 .
b111110011 )
b111110011 /
0"
b10101 $
b10101 (
b10101 -
b10101 3
#225000
b0 +
b111110011 !
b111110011 ,
1"
#230000
b101 *
b1000 2
b1000 0
b11 .
b111110010 )
b111110010 /
0"
b10110 $
b10110 (
b10110 -
b10110 3
#235000
b10 +
b111110010 !
b111110010 ,
1"
#240000
b11 *
b1000 2
b1000 0
b100 .
b100001101 )
b100001101 /
0"
b10111 $
b10111 (
b10111 -
b10111 3
#245000
b0 +
b100001101 !
b100001101 ,
1"
#250000
b1 *
b1000 2
b1000 0
b10 .
b100001000 )
b100001000 /
0"
b11000 $
b11000 (
b11000 -
b11000 3
#255000
b11010 +
b100001000 !
b100001000 ,
1"
#260000
b111 *
b1000 2
b1000 0
b11 .
b111110111 )
b111110111 /
0"
b11001 $
b11001 (
b11001 -
b11001 3
#265000
b0 +
b111110111 !
b111110111 ,
1"
#270000
b110 *
b1000 2
b1000 0
b11 .
b111110110 )
b111110110 /
0"
b11010 $
b11010 (
b11010 -
b11010 3
#275000
b100 +
b111110110 !
b111110110 ,
1"
#280000
b10 *
b1000 2
b1000 0
b100 .
b100001001 )
b100001001 /
0"
b11011 $
b11011 (
b11011 -
b11011 3
#285000
b0 +
b100001001 !
b100001001 ,
1"
#290000
b101 *
b1000 2
b1000 0
b11 .
b111110100 )
b111110100 /
0"
b11100 $
b11100 (
b11100 -
b11100 3
#295000
b10 +
b111110100 !
b111110100 ,
1"
#300000
b11 *
b1000 2
b1000 0
b100 .
b100001011 )
b100001011 /
0"
b11101 $
b11101 (
b11101 -
b11101 3
#305000
b0 +
b100001011 !
b100001011 ,
1"
#310000
b10 *
b1000 1
b1000 0
b100 .
b10100000 )
b10100000 /
0"
b11110 $
b11110 (
b11110 -
b11110 3
#315000
b100 +
b1001011111 !
b1001011111 ,
1"
#320000
b110 *
b1000 1
b1000 0
b101 .
b1011111 )
b1011111 /
0"
b11111 $
b11111 (
b11111 -
b11111 3
#325000
b0 +
b1010100000 !
b1010100000 ,
1"
#330000
b11 *
b1000 2
b1000 0
b1 .
b111100000 )
b111100000 /
0"
b100000 $
b100000 (
b100000 -
b100000 3
#335000
b11110 +
b111100000 !
b111100000 ,
1"
#340000
b101 *
b1000 2
b1000 0
b10 .
b100011111 )
b100011111 /
0"
b100001 $
b100001 (
b100001 -
b100001 3
#345000
b0 +
b100011111 !
b100011111 ,
1"
#350000
b100 *
b1000 2
b1000 0
b10 .
b100011110 )
b100011110 /
0"
b100010 $
b100010 (
b100010 -
b100010 3
#355000
b100011110 !
b100011110 ,
1"
#360000
b1000 2
b1000 0
b11 .
b111100001 )
b111100001 /
0"
b100011 $
b100011 (
b100011 -
b100011 3
#365000
b111100001 !
b111100001 ,
1"
#370000
b11 *
b1000 2
b1000 0
b10 .
b100011100 )
b100011100 /
0"
b100100 $
b100100 (
b100100 -
b100100 3
#375000
b11110 +
b100011100 !
b100011100 ,
1"
#380000
b101 *
b1000 2
b1000 0
b11 .
b111100011 )
b111100011 /
0"
b100101 $
b100101 (
b100101 -
b100101 3
#385000
b0 +
b111100011 !
b111100011 ,
1"
#390000
b100 *
b1000 2
b1000 0
b11 .
b111100010 )
b111100010 /
0"
b100110 $
b100110 (
b100110 -
b100110 3
#395000
b111100010 !
b111100010 ,
1"
#400000
b1000 2
b1000 0
b100 .
b100011101 )
b100011101 /
0"
b100111 $
b100111 (
b100111 -
b100111 3
#405000
b100011101 !
b100011101 ,
1"
#410000
b10 *
b1000 2
b1000 0
b10 .
b100011000 )
b100011000 /
0"
b101000 $
b101000 (
b101000 -
b101000 3
#415000
b11100 +
b100011000 !
b100011000 ,
1"
#420000
b110 *
b1000 2
b1000 0
b11 .
b111100111 )
b111100111 /
0"
b101001 $
b101001 (
b101001 -
b101001 3
#425000
b0 +
b111100111 !
b111100111 ,
1"
#430000
b101 *
b1000 2
b1000 0
b11 .
b111100110 )
b111100110 /
0"
b101010 $
b101010 (
b101010 -
b101010 3
#435000
b10 +
b111100110 !
b111100110 ,
1"
#440000
b11 *
b1000 2
b1000 0
b100 .
b100011001 )
b100011001 /
0"
b101011 $
b101011 (
b101011 -
b101011 3
#445000
b0 +
b100011001 !
b100011001 ,
1"
#450000
b100 *
b1000 2
b1000 0
b11 .
b111100100 )
b111100100 /
0"
b101100 $
b101100 (
b101100 -
b101100 3
#455000
b111100100 !
b111100100 ,
1"
#460000
b1000 2
b1000 0
b100 .
b100011011 )
b100011011 /
0"
b101101 $
b101101 (
b101101 -
b101101 3
#465000
b100011011 !
b100011011 ,
1"
#470000
b11 *
b1000 1
b1000 0
b100 .
b10110000 )
b10110000 /
0"
b101110 $
b101110 (
b101110 -
b101110 3
#475000
b10 +
b1001001111 !
b1001001111 ,
1"
#480000
b101 *
b1000 1
b1000 0
b101 .
b1001111 )
b1001111 /
0"
b101111 $
b101111 (
b101111 -
b101111 3
#485000
b0 +
b1010110000 !
b1010110000 ,
1"
#490000
b1 *
b1000 2
b1000 0
b10 .
b100010000 )
b100010000 /
0"
b110000 $
b110000 (
b110000 -
b110000 3
#495000
b11010 +
b100010000 !
b100010000 ,
1"
#500000
b111 *
b1000 2
b1000 0
b11 .
b111101111 )
b111101111 /
0"
b110001 $
b110001 (
b110001 -
b110001 3
#505000
b0 +
b111101111 !
b111101111 ,
1"
#510000
b110 *
b1000 2
b1000 0
b11 .
b111101110 )
b111101110 /
0"
b110010 $
b110010 (
b110010 -
b110010 3
#515000
b100 +
b111101110 !
b111101110 ,
1"
#520000
b10 *
b1000 2
b1000 0
b100 .
b100010001 )
b100010001 /
0"
b110011 $
b110011 (
b110011 -
b110011 3
#525000
b0 +
b100010001 !
b100010001 ,
1"
#530000
b101 *
b1000 2
b1000 0
b11 .
b111101100 )
b111101100 /
0"
b110100 $
b110100 (
b110100 -
b110100 3
#535000
b10 +
b111101100 !
b111101100 ,
1"
#540000
b11 *
b1000 2
b1000 0
b100 .
b100010011 )
b100010011 /
0"
b110101 $
b110101 (
b110101 -
b110101 3
#545000
b0 +
b100010011 !
b100010011 ,
1"
#550000
b100 *
b1000 1
b1000 0
b100 .
b10111000 )
b10111000 /
0"
b110110 $
b110110 (
b110110 -
b110110 3
#555000
b1001000111 !
b1001000111 ,
1"
#560000
b1000 1
b1000 0
b101 .
b1000111 )
b1000111 /
0"
b110111 $
b110111 (
b110111 -
b110111 3
#565000
b1010111000 !
b1010111000 ,
1"
#570000
b1000 2
b1000 0
b11 .
b111101000 )
b111101000 /
0"
b111000 $
b111000 (
b111000 -
b111000 3
#575000
b111101000 !
b111101000 ,
1"
#580000
b1000 2
b1000 0
b100 .
b100010111 )
b100010111 /
0"
b111001 $
b111001 (
b111001 -
b111001 3
#585000
b100010111 !
b100010111 ,
1"
#590000
b101 *
b1000 1
b1000 0
b100 .
b10111100 )
b10111100 /
0"
b111010 $
b111010 (
b111010 -
b111010 3
#595000
b11110 +
b1001000011 !
b1001000011 ,
1"
#600000
b11 *
b1000 1
b1000 0
b101 .
b1000011 )
b1000011 /
0"
b111011 $
b111011 (
b111011 -
b111011 3
#605000
b0 +
b1010111100 !
b1010111100 ,
1"
#610000
b110 *
b1000 1
b1000 0
b100 .
b10111110 )
b10111110 /
0"
b111100 $
b111100 (
b111100 -
b111100 3
#615000
b11100 +
b1001000001 !
b1001000001 ,
1"
#620000
b10 *
b1000 1
b1000 0
b101 .
b1000001 )
b1000001 /
0"
b111101 $
b111101 (
b111101 -
b111101 3
#625000
b0 +
b1010111110 !
b1010111110 ,
1"
#630000
b1 *
b1000 1
b1000 0
b101 .
b1000000 )
b1000000 /
0"
b111110 $
b111110 (
b111110 -
b111110 3
#635000
b110 +
b1010111111 !
b1010111111 ,
1"
#640000
b111 *
b1000 1
b1000 0
b110 .
b10111111 )
b10111111 /
0"
b111111 $
b111111 (
b111111 -
b111111 3
#645000
b0 +
b1001000000 !
b1001000000 ,
1"
#650000
b10 *
b1000 2
b1000 0
b1 .
b111000000 )
b111000000 /
0"
b1000000 $
b1000000 (
b1000000 -
b1000000 3
#655000
b11100 +
b111000000 !
b111000000 ,
1"
#660000
b110 *
b1000 2
b1000 0
b10 .
b100111111 )
b100111111 /
0"
b1000001 $
b1000001 (
b1000001 -
b1000001 3
#665000
b0 +
b100111111 !
b100111111 ,
1"
#670000
b101 *
b1000 2
b1000 0
b10 .
b100111110 )
b100111110 /
0"
b1000010 $
b1000010 (
b1000010 -
b1000010 3
#675000
b10 +
b100111110 !
b100111110 ,
1"
#680000
b11 *
b1000 2
b1000 0
b11 .
b111000001 )
b111000001 /
0"
b1000011 $
b1000011 (
b1000011 -
b1000011 3
#685000
b0 +
b111000001 !
b111000001 ,
1"
#690000
b100 *
b1000 2
b1000 0
b10 .
b100111100 )
b100111100 /
0"
b1000100 $
b1000100 (
b1000100 -
b1000100 3
#695000
b100111100 !
b100111100 ,
1"
#700000
b1000 2
b1000 0
b11 .
b111000011 )
b111000011 /
0"
b1000101 $
b1000101 (
b1000101 -
b1000101 3
#705000
b111000011 !
b111000011 ,
1"
#710000
b11 *
b1000 2
b1000 0
b11 .
b111000010 )
b111000010 /
0"
b1000110 $
b1000110 (
b1000110 -
b1000110 3
#715000
b11110 +
b111000010 !
b111000010 ,
1"
#720000
b101 *
b1000 2
b1000 0
b100 .
b100111101 )
b100111101 /
0"
b1000111 $
b1000111 (
b1000111 -
b1000111 3
#725000
b0 +
b100111101 !
b100111101 ,
1"
#730000
b11 *
b1000 2
b1000 0
b10 .
b100111000 )
b100111000 /
0"
b1001000 $
b1001000 (
b1001000 -
b1001000 3
#735000
b11110 +
b100111000 !
b100111000 ,
1"
#740000
b101 *
b1000 2
b1000 0
b11 .
b111000111 )
b111000111 /
0"
b1001001 $
b1001001 (
b1001001 -
b1001001 3
#745000
b0 +
b111000111 !
b111000111 ,
1"
#750000
b100 *
b1000 2
b1000 0
b11 .
b111000110 )
b111000110 /
0"
b1001010 $
b1001010 (
b1001010 -
b1001010 3
#755000
b111000110 !
b111000110 ,
1"
#760000
b1000 2
b1000 0
b100 .
b100111001 )
b100111001 /
0"
b1001011 $
b1001011 (
b1001011 -
b1001011 3
#765000
b100111001 !
b100111001 ,
1"
#770000
b11 *
b1000 2
b1000 0
b11 .
b111000100 )
b111000100 /
0"
b1001100 $
b1001100 (
b1001100 -
b1001100 3
#775000
b11110 +
b111000100 !
b111000100 ,
1"
#780000
b101 *
b1000 2
b1000 0
b100 .
b100111011 )
b100111011 /
0"
b1001101 $
b1001101 (
b1001101 -
b1001101 3
#785000
b0 +
b100111011 !
b100111011 ,
1"
#790000
b10 *
b1000 1
b1000 0
b100 .
b10010000 )
b10010000 /
0"
b1001110 $
b1001110 (
b1001110 -
b1001110 3
#795000
b100 +
b1001101111 !
b1001101111 ,
1"
#800000
b110 *
b1000 1
b1000 0
b101 .
b1101111 )
b1101111 /
0"
b1001111 $
b1001111 (
b1001111 -
b1001111 3
#805000
b0 +
b1010010000 !
b1010010000 ,
1"
#810000
b10 *
b1000 2
b1000 0
b10 .
b100110000 )
b100110000 /
0"
b1010000 $
b1010000 (
b1010000 -
b1010000 3
#815000
b11100 +
b100110000 !
b100110000 ,
1"
#820000
b110 *
b1000 2
b1000 0
b11 .
b111001111 )
b111001111 /
0"
b1010001 $
b1010001 (
b1010001 -
b1010001 3
#825000
b0 +
b111001111 !
b111001111 ,
1"
#830000
b101 *
b1000 2
b1000 0
b11 .
b111001110 )
b111001110 /
0"
b1010010 $
b1010010 (
b1010010 -
b1010010 3
#835000
b10 +
b111001110 !
b111001110 ,
1"
#840000
b11 *
b1000 2
b1000 0
b100 .
b100110001 )
b100110001 /
0"
b1010011 $
b1010011 (
b1010011 -
b1010011 3
#845000
b0 +
b100110001 !
b100110001 ,
1"
#850000
b100 *
b1000 2
b1000 0
b11 .
b111001100 )
b111001100 /
0"
b1010100 $
b1010100 (
b1010100 -
b1010100 3
#855000
b111001100 !
b111001100 ,
1"
#860000
b1000 2
b1000 0
b100 .
b100110011 )
b100110011 /
0"
b1010101 $
b1010101 (
b1010101 -
b1010101 3
#865000
b100110011 !
b100110011 ,
1"
#870000
b11 *
b1000 1
b1000 0
b100 .
b10011000 )
b10011000 /
0"
b1010110 $
b1010110 (
b1010110 -
b1010110 3
#875000
b10 +
b1001100111 !
b1001100111 ,
1"
#880000
b101 *
b1000 1
b1000 0
b101 .
b1100111 )
b1100111 /
0"
b1010111 $
b1010111 (
b1010111 -
b1010111 3
#885000
b0 +
b1010011000 !
b1010011000 ,
1"
#890000
b11 *
b1000 2
b1000 0
b11 .
b111001000 )
b111001000 /
0"
b1011000 $
b1011000 (
b1011000 -
b1011000 3
#895000
b11110 +
b111001000 !
b111001000 ,
1"
#900000
b101 *
b1000 2
b1000 0
b100 .
b100110111 )
b100110111 /
0"
b1011001 $
b1011001 (
b1011001 -
b1011001 3
#905000
b0 +
b100110111 !
b100110111 ,
1"
#910000
b100 *
b1000 1
b1000 0
b100 .
b10011100 )
b10011100 /
0"
b1011010 $
b1011010 (
b1011010 -
b1011010 3
#915000
b1001100011 !
b1001100011 ,
1"
#920000
b1000 1
b1000 0
b101 .
b1100011 )
b1100011 /
0"
b1011011 $
b1011011 (
b1011011 -
b1011011 3
#925000
b1010011100 !
b1010011100 ,
1"
#930000
b101 *
b1000 1
b1000 0
b100 .
b10011110 )
b10011110 /
0"
b1011100 $
b1011100 (
b1011100 -
b1011100 3
#935000
b11110 +
b1001100001 !
b1001100001 ,
1"
#940000
b11 *
b1000 1
b1000 0
b101 .
b1100001 )
b1100001 /
0"
b1011101 $
b1011101 (
b1011101 -
b1011101 3
#945000
b0 +
b1010011110 !
b1010011110 ,
1"
#950000
b10 *
b1000 1
b1000 0
b101 .
b1100000 )
b1100000 /
0"
b1011110 $
b1011110 (
b1011110 -
b1011110 3
#955000
b100 +
b1010011111 !
b1010011111 ,
1"
#960000
b110 *
b1000 1
b1000 0
b110 .
b10011111 )
b10011111 /
0"
b1011111 $
b1011111 (
b1011111 -
b1011111 3
#965000
b0 +
b1001100000 !
b1001100000 ,
1"
#970000
b1 *
b1000 2
b1000 0
b10 .
b100100000 )
b100100000 /
0"
b1100000 $
b1100000 (
b1100000 -
b1100000 3
#975000
b11010 +
b100100000 !
b100100000 ,
1"
#980000
b111 *
b1000 2
b1000 0
b11 .
b111011111 )
b111011111 /
0"
b1100001 $
b1100001 (
b1100001 -
b1100001 3
#985000
b0 +
b111011111 !
b111011111 ,
1"
#990000
b110 *
b1000 2
b1000 0
b11 .
b111011110 )
b111011110 /
0"
b1100010 $
b1100010 (
b1100010 -
b1100010 3
#995000
b100 +
b111011110 !
b111011110 ,
1"
#1000000
b10 *
b1000 2
b1000 0
b100 .
b100100001 )
b100100001 /
0"
b1100011 $
b1100011 (
b1100011 -
b1100011 3
#1005000
b0 +
b100100001 !
b100100001 ,
1"
#1010000
b101 *
b1000 2
b1000 0
b11 .
b111011100 )
b111011100 /
0"
b1100100 $
b1100100 (
b1100100 -
b1100100 3
#1015000
b10 +
b111011100 !
b111011100 ,
1"
#1020000
b11 *
b1000 2
b1000 0
b100 .
b100100011 )
b100100011 /
0"
b1100101 $
b1100101 (
b1100101 -
b1100101 3
#1025000
b0 +
b100100011 !
b100100011 ,
1"
#1030000
b10 *
b1000 1
b1000 0
b100 .
b10001000 )
b10001000 /
0"
b1100110 $
b1100110 (
b1100110 -
b1100110 3
#1035000
b100 +
b1001110111 !
b1001110111 ,
1"
#1040000
b110 *
b1000 1
b1000 0
b101 .
b1110111 )
b1110111 /
0"
b1100111 $
b1100111 (
b1100111 -
b1100111 3
#1045000
b0 +
b1010001000 !
b1010001000 ,
1"
#1050000
b100 *
b1000 2
b1000 0
b11 .
b111011000 )
b111011000 /
0"
b1101000 $
b1101000 (
b1101000 -
b1101000 3
#1055000
b111011000 !
b111011000 ,
1"
#1060000
b1000 2
b1000 0
b100 .
b100100111 )
b100100111 /
0"
b1101001 $
b1101001 (
b1101001 -
b1101001 3
#1065000
b100100111 !
b100100111 ,
1"
#1070000
b11 *
b1000 1
b1000 0
b100 .
b10001100 )
b10001100 /
0"
b1101010 $
b1101010 (
b1101010 -
b1101010 3
#1075000
b10 +
b1001110011 !
b1001110011 ,
1"
#1080000
b101 *
b1000 1
b1000 0
b101 .
b1110011 )
b1110011 /
0"
b1101011 $
b1101011 (
b1101011 -
b1101011 3
#1085000
b0 +
b1010001100 !
b1010001100 ,
1"
#1090000
b100 *
b1000 1
b1000 0
b100 .
b10001110 )
b10001110 /
0"
b1101100 $
b1101100 (
b1101100 -
b1101100 3
#1095000
b1001110001 !
b1001110001 ,
1"
#1100000
b1000 1
b1000 0
b101 .
b1110001 )
b1110001 /
0"
b1101101 $
b1101101 (
b1101101 -
b1101101 3
#1105000
b1010001110 !
b1010001110 ,
1"
#1110000
b11 *
b1000 1
b1000 0
b101 .
b1110000 )
b1110000 /
0"
b1101110 $
b1101110 (
b1101110 -
b1101110 3
#1115000
b10 +
b1010001111 !
b1010001111 ,
1"
#1120000
b101 *
b1000 1
b1000 0
b110 .
b10001111 )
b10001111 /
0"
b1101111 $
b1101111 (
b1101111 -
b1101111 3
#1125000
b0 +
b1001110000 !
b1001110000 ,
1"
#1130000
b11 *
b1000 2
b1000 0
b11 .
b111010000 )
b111010000 /
0"
b1110000 $
b1110000 (
b1110000 -
b1110000 3
#1135000
b11110 +
b111010000 !
b111010000 ,
1"
#1140000
b101 *
b1000 2
b1000 0
b100 .
b100101111 )
b100101111 /
0"
b1110001 $
b1110001 (
b1110001 -
b1110001 3
#1145000
b0 +
b100101111 !
b100101111 ,
1"
#1150000
b10 *
b1000 1
b1000 0
b100 .
b10000100 )
b10000100 /
0"
b1110010 $
b1110010 (
b1110010 -
b1110010 3
#1155000
b100 +
b1001111011 !
b1001111011 ,
1"
#1160000
b110 *
b1000 1
b1000 0
b101 .
b1111011 )
b1111011 /
0"
b1110011 $
b1110011 (
b1110011 -
b1110011 3
#1165000
b0 +
b1010000100 !
b1010000100 ,
1"
#1170000
b11 *
b1000 1
b1000 0
b100 .
b10000110 )
b10000110 /
0"
b1110100 $
b1110100 (
b1110100 -
b1110100 3
#1175000
b10 +
b1001111001 !
b1001111001 ,
1"
#1180000
b101 *
b1000 1
b1000 0
b101 .
b1111001 )
b1111001 /
0"
b1110101 $
b1110101 (
b1110101 -
b1110101 3
#1185000
b0 +
b1010000110 !
b1010000110 ,
1"
#1190000
b100 *
b1000 1
b1000 0
b101 .
b1111000 )
b1111000 /
0"
b1110110 $
b1110110 (
b1110110 -
b1110110 3
#1195000
b1010000111 !
b1010000111 ,
1"
#1200000
b1000 1
b1000 0
b110 .
b10000111 )
b10000111 /
0"
b1110111 $
b1110111 (
b1110111 -
b1110111 3
#1205000
b1001111000 !
b1001111000 ,
1"
#1210000
b10 *
b1000 1
b1000 0
b100 .
b10000010 )
b10000010 /
0"
b1111000 $
b1111000 (
b1111000 -
b1111000 3
#1215000
b100 +
b1001111101 !
b1001111101 ,
1"
#1220000
b110 *
b1000 1
b1000 0
b101 .
b1111101 )
b1111101 /
0"
b1111001 $
b1111001 (
b1111001 -
b1111001 3
#1225000
b0 +
b1010000010 !
b1010000010 ,
1"
#1230000
b101 *
b1000 1
b1000 0
b101 .
b1111100 )
b1111100 /
0"
b1111010 $
b1111010 (
b1111010 -
b1111010 3
#1235000
b11110 +
b1010000011 !
b1010000011 ,
1"
#1240000
b11 *
b1000 1
b1000 0
b110 .
b10000011 )
b10000011 /
0"
b1111011 $
b1111011 (
b1111011 -
b1111011 3
#1245000
b0 +
b1001111100 !
b1001111100 ,
1"
#1250000
b110 *
b1000 1
b1000 0
b101 .
b1111110 )
b1111110 /
0"
b1111100 $
b1111100 (
b1111100 -
b1111100 3
#1255000
b11100 +
b1010000001 !
b1010000001 ,
1"
#1260000
b10 *
b1000 1
b1000 0
b110 .
b10000001 )
b10000001 /
0"
b1111101 $
b1111101 (
b1111101 -
b1111101 3
#1265000
b0 +
b1001111110 !
b1001111110 ,
1"
#1270000
b1 *
b1000 1
b1000 0
b110 .
b10000000 )
b10000000 /
0"
b1111110 $
b1111110 (
b1111110 -
b1111110 3
