.Xil/Vivado-21936-DESKTOP-M3QN9GM/realtime/div_gen_0_stub.v
// Copyright 1986-2022 Xilinx, Inc. All Rights Reserved.
// Copyright 2022-2023 Advanced Micro Devices, Inc. All Rights Reserved.

// This empty module with port declaration file causes synthesis tools to infer a black box for IP.
// Please paste the declaration into a Verilog source file or add the file as an additional source.
(* x_core_info = "div_gen_v5_1_19,Vivado 2023.1" *)
module div_gen_0(aclk, s_axis_divisor_tvalid, 
  s_axis_divisor_tdata, s_axis_dividend_tvalid, s_axis_dividend_tdata, 
  m_axis_dout_tvalid, m_axis_dout_tdata);
  input aclk /* synthesis syn_isclock = 1 */;
  input s_axis_divisor_tvalid;
  input [31:0]s_axis_divisor_tdata;
  input s_axis_dividend_tvalid;
  input [31:0]s_axis_dividend_tdata;
  output m_axis_dout_tvalid;
  output [63:0]m_axis_dout_tdata;
endmodule

sim/div_tb.sv
`timescale 1ns / 1ps
`default_nettype none

module div_tb();

  logic clk_in;
  logic rst_in;
  logic signed [31:0] fft_data_reg_1; // used by the external master to signal that it is able to provide data (critical in pipelining)
  logic signed [31:0] change_1; // asserted by the external master on the last sample of the frame (can be used to regulate flow of data)
  logic signed [61:0] sig_1; // used by the external master to signal that it is able to provide data (critical in pipelining)  
  logic signed [31:0] out_actual;
  div_gen_0 testing_div(
    .aclk(clk_in),
    .s_axis_divisor_tvalid(1),
    .s_axis_divisor_tdata(fft_data_reg_1),
    .s_axis_dividend_tdata(change_1),
    .m_axis_dout_tvalid(),
    .m_axis_dout_tdata(sig_1));

  always begin // 100 MHz clock
      #5; 
      clk_in = !clk_in;
      out_actual = sig_1[61:32];
  end

  initial begin
    $dumpfile("div_tb.vcd"); 
    $dumpvars(0,div_tb);
    $display("Starting Sim");
    clk_in = 0;
    rst_in = 0;
    out_actual = 0;
    #10;
    // Reset all variables
    rst_in = 1;
    #5;
    
    #10;
    // Begin Test
    #10;
    rst_in = 0; 
    
    
    for (int i = 0; i<10000; i=i+1)begin // Begin FFT Analysis
     #5; // Check clock cycling
     change_1 = 32'b1111_1111_1111_1111;
     fft_data_reg_1 = 32'b0000_0000_1001;
    end
    for (int i = 0; i<10000; i=i+1)begin // Begin FFT Analysis
      change_1 = 32'd9;
      fft_data_reg_1 = 32'd3;
      #5; // Check clock cycling
    end
    for (int i = 0; i<10000; i=i+1)begin // Begin FFT Analysis
      change_1 = 32'd1111;
      fft_data_reg_1 = 32'b0000_0000_0000;
      #5; // Check clock cycling
    end

    $display("Simulation finished");
    $finish;
  end
endmodule
`default_nettype wire

// WRONG IP - GIVES REMAINDER

VCD/divider.vcd
$date
   Tue Dec 12 10:52:20 2023
$end
$version
  2023.1
$end
$timescale
  1ps
$end
$scope module div_tb $end
$var reg 1 ! clk_in $end
$var reg 1 " rst_in $end
$var reg 32 # fft_data_reg_1 [31:0] $end
$var reg 32 $ change_1 [31:0] $end
$var reg 62 % sig_1 [61:0] $end
$var reg 32 & out_actual [31:0] $end
$scope module testing_div $end
$var wire 1 ' aclk $end
$var wire 1 ( s_axis_divisor_tvalid $end
$var wire 32 ) s_axis_divisor_tdata $end
$var wire 1 * s_axis_dividend_tvalid $end
$var wire 32 + s_axis_dividend_tdata $end
$var wire 1 , m_axis_dout_tvalid $end
$var wire 64 - m_axis_dout_tdata $end
$upscope $end
$scope begin Block44_2 $end
$var reg 32 . i [31:0] $end
$upscope $end
$scope begin Block49_3 $end
$var reg 32 / i [31:0] $end
$upscope $end
$scope begin Block54_4 $end
$var reg 32 0 i [31:0] $end
$upscope $end
$upscope $end
$enddefinitions $end
#0
$dumpvars
0!
0"
bx #
bx $
b0 %
b0 &
0'
1(
bx )
x*
bx +
0,
b0 -
b0 .
b0 /
b0 0
$end
#5000
1!
1'
#10000
0!
1"
0'
#15000
1!
1'
#20000
0!
0'
#25000
1!
1'
#30000
0!
0'
#35000
1!
0"
1'
#40000
0!
b1001 #
b1111111111111111 $
0'
b1001 )
b1111111111111111 +
b1 .
#45000
1!
1'
b10 .
#50000
0!
0'
b11 .
#55000
1!
1'
b100 .
#60000
0!
0'
b101 .
#65000
1!
1'
b110 .
#70000
0!
0'
b111 .
#75000
1!
1'
b1000 .
#80000
0!
0'
b1001 .
#85000
1!
1'
b1010 .
#90000
0!
0'
b1011 .
#95000
1!
1'
b1100 .
#100000
0!
0'
b1101 .
#105000
1!
1'
b1110 .
#110000
0!
0'
b1111 .
#115000
1!
1'
b10000 .
#120000
0!
0'
b10001 .
#125000
1!
1'
b10010 .
#130000
0!
0'
b10011 .
#135000
1!
1'
b10100 .
#140000
0!
0'
b10101 .
#145000
1!
1'
b10110 .
#150000
0!
0'
b10111 .
#155000
1!
1'
b11000 .
#160000
0!
0'
b11001 .
#165000
1!
1'
b11010 .
#170000
0!
0'
b11011 .
#175000
1!
1'
b11100 .
#180000
0!
0'
b11101 .
#185000
1!
1'
b11110 .
#190000
0!
0'
b11111 .
#195000
1!
1'
b100000 .
#200000
0!
0'
b100001 .
#205000
1!
1'
b100010 .
#210000
0!
0'
b100011 .
#215000
1!
1'
b100100 .
#220000
0!
0'
b100101 .
#225000
1!
1'
b100110 .
#230000
0!
0'
b100111 .
#235000
1!
1'
b101000 .
#240000
0!
0'
b101001 .
#245000
1!
1'
b101010 .
#250000
0!
0'
b101011 .
#255000
1!
1'
b101100 .
#260000
0!
0'
b101101 .
#265000
1!
1'
b101110 .
#270000
0!
0'
b101111 .
#275000
1!
1'
b110000 .
#280000
0!
0'
b110001 .
#285000
1!
1'
b110010 .
#290000
0!
0'
b110011 .
#295000
1!
1'
b110100 .
#300000
0!
0'
b110101 .
#305000
1!
1'
b110110 .
#310000
0!
0'
b110111 .
#315000
1!
1'
b111000 .
#320000
0!
0'
b111001 .
#325000
1!
1'
b111010 .
#330000
0!
0'
b111011 .
#335000
1!
1'
b111100 .
#340000
0!
0'
b111101 .
#345000
1!
1'
b111110 .
#350000
0!
0'
b111111 .
#355000
1!
1'
b1000000 .
#360000
0!
0'
b1000001 .
#365000
1!
1'
b1000010 .
#370000
0!
0'
b1000011 .
#375000
1!
1'
b1000100 .
#380000
0!
0'
b1000101 .
#385000
1!
1'
b1000110 .
#390000
0!
0'
b1000111 .
#395000
1!
1'
b1001000 .
#400000
0!
0'
b1001001 .
#405000
1!
1'
b1001010 .
#410000
0!
0'
b1001011 .
#415000
1!
1'
b1001100 .
#420000
0!
0'
b1001101 .
#425000
1!
1'
b1001110 .
#430000
0!
0'
b1001111 .
#435000
1!
1'
b1010000 .
#440000
0!
0'
b1010001 .
#445000
1!
1'
b1010010 .
#450000
0!
0'
b1010011 .
#455000
1!
1'
b1010100 .
#460000
0!
0'
b1010101 .
#465000
1!
1'
b1010110 .
#470000
0!
0'
b1010111 .
#475000
1!
1'
b1011000 .
#480000
0!
0'
b1011001 .
#485000
1!
1'
b1011010 .
#490000
0!
0'
b1011011 .
#495000
1!
1'
b1011100 .
#500000
0!
0'
b1011101 .
#505000
1!
1'
b1011110 .
#510000
0!
0'
b1011111 .
#515000
1!
1'
b1100000 .
#520000
0!
0'
b1100001 .
#525000
1!
1'
b1100010 .
#530000
0!
0'
b1100011 .
#535000
1!
1'
b1100100 .
#540000
0!
0'
b1100101 .
#545000
1!
1'
b1100110 .
#550000
0!
0'
b1100111 .
#555000
1!
1'
b1101000 .
#560000
0!
0'
b1101001 .
#565000
1!
1'
b1101010 .
#570000
0!
0'
b1101011 .
#575000
1!
1'
b1101100 .
#580000
0!
0'
b1101101 .
#585000
1!
1'
b1101110 .
#590000
0!
0'
b1101111 .
#595000
1!
1'
b1110000 .
#600000
0!
0'
b1110001 .
#605000
1!
1'
b1110010 .
#610000
0!
0'
b1110011 .
#615000
1!
1'
b1110100 .
#620000
0!
0'
b1110101 .
#625000
1!
1'
b1110110 .
#630000
0!
0'
b1110111 .
#635000
1!
1'
b1111000 .
#640000
0!
0'
b1111001 .
#645000
1!
1'
b1111010 .
#650000
0!
0'
b1111011 .
#655000
1!
1'
b1111100 .
#660000
0!
0'
b1111101 .
#665000
1!
1'
b1111110 .
#670000
0!
0'
b1111111 .
#675000
1!
bx %
1'
bx -
b10000000 .
#680000
0!
b0xxxxxxxxxxxxxxxxxxxxxxxxxxxxxx &
0'
b10000001 .
#685000
1!
1'
b10000010 .
#690000
0!
0'
b10000011 .
#695000
1!
1'
b10000100 .
#700000
0!
0'
b10000101 .
#705000
1!
1'
b10000110 .
#710000
0!
0'
b10000111 .
#715000
1!
b111000111000101010101010101010101010101010101 %
1'
b111000111000101010101010101010101010101010101 -
b10001000 .
#720000
0!
b1110001110001 &
0'
b10001001 .
#725000
1!
1'
b10001010 .
#730000
0!
0'
b10001011 .
#735000
1!
1'
b10001100 .
#740000
0!
0'
b10001101 .
#745000
1!
1'
b10001110 .
#750000
0!
0'
b10001111 .
#755000
1!
1'
b10010000 .
#760000
0!
0'
b10010001 .
#765000
1!
1'
b10010010 .
#770000
0!
0'
b10010011 .
#775000
1!
1'
b10010100 .
#780000
0!
0'
b10010101 .
#785000
1!
1'
b10010110 .
#790000
0!
0'
b10010111 .
#795000
1!
1'
b10011000 .
#800000
0!
0'
b10011001 .
#805000
1!
1'
b10011010 .
#810000
0!
0'
b10011011 .
#815000
1!
1'
b10011100 .
#820000
0!
0'
b10011101 .
#825000
1!
1'
b10011110 .
#830000
0!
0'
b10011111 .
#835000
1!
1'
b10100000 .
#840000
0!
0'
b10100001 .
#845000
1!
1'
b10100010 .
#850000
0!
0'
b10100011 .
#855000
1!
1'
b10100100 .
#860000
0!
0'
b10100101 .
#865000
1!
1'
b10100110 .
#870000
0!
0'
b10100111 .
#875000
1!
1'
b10101000 .
#880000
0!
0'
b10101001 .
#885000
1!
1'
b10101010 .
#890000
0!
0'
b10101011 .
#895000
1!
1'
b10101100 .
#900000
0!
0'
b10101101 .
#905000
1!
1'
b10101110 .
#910000
0!
0'
b10101111 .
#915000
1!
1'
b10110000 .
#920000
0!
0'
b10110001 .
#925000
1!
1'
b10110010 .
#930000
0!
0'
b10110011 .
#935000
1!
1'
b10110100 .
#940000
0!
0'
b10110101 .
#945000
1!
1'
b10110110 .
#950000
0!
0'
b10110111 .
#955000
1!
1'
b10111000 .
#960000
0!
0'
b10111001 .
#965000
1!
1'
b10111010 .
#970000
0!
0'
b10111011 .
#975000
1!
1'
b10111100 .
#980000
0!
0'
b10111101 .
#985000
1!
1'
b10111110 .
#990000
0!
0'
b10111111 .
#995000
1!
1'
b11000000 .
#1000000
0!
0'
b11000001 .
#1005000
1!
1'
b11000010 .
#1010000
0!
0'
b11000011 .
#1015000
1!
1'
b11000100 .
#1020000
0!
0'
b11000101 .
#1025000
1!
1'
b11000110 .
#1030000
0!
0'
b11000111 .
#1035000
1!
1'
b11001000 .
#1040000
0!
0'
b11001001 .
#1045000
1!
1'
b11001010 .
#1050000
0!
0'
b11001011 .
#1055000
1!
1'
b11001100 .
#1060000
0!
0'
b11001101 .
#1065000
1!
1'
b11001110 .
#1070000
0!
0'
b11001111 .
#1075000
1!
1'
b11010000 .
#1080000
0!
0'
b11010001 .
#1085000
1!
1'
b11010010 .
#1090000
0!
0'
b11010011 .
#1095000
1!
1'
b11010100 .
#1100000
0!
0'
b11010101 .
#1105000
1!
1'
b11010110 .
#1110000
0!
0'
b11010111 .
#1115000
1!
1'
b11011000 .
#1120000
0!
0'
b11011001 .
#1125000
1!
1'
b11011010 .
#1130000
0!
0'
b11011011 .
#1135000
1!
1'
b11011100 .
#1140000
0!
0'
b11011101 .
#1145000
1!
1'
b11011110 .
#1150000
0!
0'
b11011111 .
#1155000
1!
1'
b11100000 .
#1160000
0!
0'
b11100001 .
#1165000
1!
1'
b11100010 .
#1170000
0!
0'
b11100011 .
#1175000
1!
1'
b11100100 .
#1180000
0!
0'
b11100101 .
#1185000
1!
1'
b11100110 .
#1190000
0!
0'
b11100111 .
#1195000
1!
1'
b11101000 .
#1200000
0!
0'
b11101001 .
#1205000
1!
1'
b11101010 .
#1210000
0!
0'
b11101011 .
#1215000
1!
1'
b11101100 .
#1220000
0!
0'
b11101101 .
#1225000
1!
1'
b11101110 .
#1230000
0!
0'
b11101111 .
#1235000
1!
1'
b11110000 .
#1240000
0!
0'
b11110001 .
#1245000
1!
1'
b11110010 .
#1250000
0!
0'
b11110011 .
#1255000
1!
1'
b11110100 .
#1260000
0!
0'
b11110101 .
#1265000
1!
1'
b11110110 .
#1270000
0!
0'
b11110111 .
#1275000
1!
1'
b11111000 .
#1280000
0!
0'
b11111001 .
#1285000
1!
1'
b11111010 .
#1290000
0!
0'
b11111011 .
#1295000
1!
1'
b11111100 .
#1300000
0!
0'
b11111101 .
#1305000
1!
1'
b11111110 .
#1310000
0!
0'
b11111111 .
#1315000
1!
1'
b100000000 .
#1320000
0!
0'
b100000001 .
#1325000
1!
1'
b100000010 .
#1330000
0!
0'
b100000011 .
#1335000
1!
1'
b100000100 .
#1340000
0!
0'
b100000101 .
#1345000
1!
1'
b100000110 .
#1350000
0!
0'
b100000111 .
#1355000
1!
1'
b100001000 .
#1360000
0!
0'
b100001001 .
#1365000
1!
1'
b100001010 .
#1370000
0!
0'
b100001011 .
#1375000
1!
1'
b100001100 .
#1380000
0!
0'
b100001101 .
#1385000
1!
1'
b100001110 .
#1390000
0!
0'
b100001111 .
#1395000
1!
1'
b100010000 .
#1400000
0!
0'
b100010001 .
#1405000
1!
1'
b100010010 .
#1410000
0!
0'
b100010011 .
#1415000
1!
1'
b100010100 .
#1420000
0!
0'
b100010101 .
#1425000
1!
1'
b100010110 .
#1430000
0!
0'
b100010111 .
#1435000
1!
1'
b100011000 .
#1440000
0!
0'
b100011001 .
#1445000
1!
1'
b100011010 .
#1450000
0!
0'
b100011011 .
#1455000
1!
1'
b100011100 .
#1460000
0!
0'
b100011101 .
#1465000
1!
1'
b100011110 .
#1470000
0!
0'
b100011111 .
#1475000
1!
1'
b100100000 .
#1480000
0!
0'
b100100001 .
#1485000
1!
1'
b100100010 .
#1490000
0!
0'
b100100011 .
#1495000
1!
1'
b100100100 .
#1500000
0!
0'
b100100101 .
#1505000
1!
1'
b100100110 .
#1510000
0!
0'
b100100111 .
#1515000
1!
1'
b100101000 .
#1520000
0!
0'
b100101001 .
#1525000
1!
1'
b100101010 .
#1530000
0!
0'
b100101011 .
#1535000
1!
1'
b100101100 .
#1540000
0!
0'
b100101101 .
#1545000
1!
1'
b100101110 .
#1550000
0!
0'
b100101111 .
#1555000
1!
1'
b100110000 .
#1560000
0!
0'
b100110001 .
#1565000
1!
1'
b100110010 .
#1570000
0!
0'
b100110011 .
#1575000
1!
1'
b100110100 .
#1580000
0!
0'
b100110101 .
#1585000
1!
1'
b100110110 .
#1590000
0!
0'
b100110111 .
#1595000
1!
1'
b100111000 .
#1600000
0!
0'
b100111001 .
#1605000
1!
1'
b100111010 .
#1610000
0!
0'
b100111011 .
#1615000
1!
1'
b100111100 .
#1620000
0!
0'
b100111101 .
#1625000
1!
1'
b100111110 .
#1630000
0!
0'
b100111111 .
#1635000
1!
1'
b101000000 .
#1640000
0!
0'
b101000001 .
#1645000
1!
1'
b101000010 .
#1650000
0!
0'
b101000011 .
#1655000
1!
1'
b101000100 .
#1660000
0!
0'
b101000101 .
#1665000
1!
1'
b101000110 .
#1670000
0!
0'
b101000111 .
#1675000
1!
1'
b101001000 .
#1680000
0!
0'
b101001001 .
#1685000
1!
1'
b101001010 .
#1690000
0!
0'
b101001011 .
#1695000
1!
1'
b101001100 .
#1700000
0!
0'
b101001101 .
#1705000
1!
1'
b101001110 .
#1710000
0!
0'
b101001111 .
#1715000
1!
1'
b101010000 .
#1720000
0!
0'
b101010001 .
#1725000
1!
1'
b101010010 .
#1730000
0!
0'
b101010011 .
#1735000
1!
1'
b101010100 .
#1740000
0!
0'
b101010101 .
#1745000
1!
1'
b101010110 .
#1750000
0!
0'
b101010111 .
#1755000
1!
1'
b101011000 .
#1760000
0!
0'
b101011001 .
#1765000
1!
1'
b101011010 .
#1770000
0!
0'
b101011011 .
#1775000
1!
1'
b101011100 .
#1780000
0!
0'
b101011101 .
#1785000
1!
1'
b101011110 .
#1790000
0!
0'
b101011111 .
#1795000
1!
1'
b101100000 .
#1800000
0!
0'
b101100001 .
#1805000
1!
1'
b101100010 .
#1810000
0!
0'
b101100011 .
#1815000
1!
1'
b101100100 .
#1820000
0!
0'
b101100101 .
#1825000
1!
1'
b101100110 .
#1830000
0!
0'
b101100111 .
#1835000
1!
1'
b101101000 .
#1840000
0!
0'
b101101001 .
#1845000
1!
1'
b101101010 .
#1850000
0!
0'
b101101011 .
#1855000
1!
1'
b101101100 .
#1860000
0!
0'
b101101101 .
#1865000
1!
1'
b101101110 .
#1870000
0!
0'
b101101111 .
#1875000
1!
1'
b101110000 .
#1880000
0!
0'
b101110001 .
#1885000
1!
1'
b101110010 .
#1890000
0!
0'
b101110011 .
#1895000
1!
1'
b101110100 .
#1900000
0!
0'
b101110101 .
#1905000
1!
1'
b101110110 .
#1910000
0!
0'
b101110111 .
#1915000
1!
1'
b101111000 .
#1920000
0!
0'
b101111001 .
#1925000
1!
1'
b101111010 .
#1930000
0!
0'
b101111011 .
#1935000
1!
1'
b101111100 .
#1940000
0!
0'
b101111101 .
#1945000
1!
1'
b101111110 .
#1950000
0!
0'
b101111111 .
#1955000
1!
1'
b110000000 .
#1960000
0!
0'
b110000001 .
#1965000
1!
1'
b110000010 .
#1970000
0!
0'
b110000011 .
#1975000
1!
1'
b110000100 .
#1980000
0!
0'
b110000101 .
#1985000
1!
1'
b110000110 .
#1990000
0!
0'
b110000111 .
#1995000
1!
1'
b110001000 .
#2000000
0!
0'
b110001001 .
#2005000
1!
1'
b110001010 .
#2010000
0!
0'
b110001011 .
#2015000
1!
1'
b110001100 .
#2020000
0!
0'
b110001101 .
#2025000
1!
1'
b110001110 .
#2030000
0!
0'
b110001111 .
#2035000
1!
1'
b110010000 .
#2040000
0!
0'
b110010001 .
#2045000
1!
1'
b110010010 .
#2050000
0!
0'
b110010011 .
#2055000
1!
1'
b110010100 .
#2060000
0!
0'
b110010101 .
#2065000
1!
1'
b110010110 .
#2070000
0!
0'
b110010111 .
#2075000
1!
1'
b110011000 .
#2080000
0!
0'
b110011001 .
#2085000
1!
1'
b110011010 .
#2090000
0!
0'
b110011011 .
#2095000
1!
1'
b110011100 .
#2100000
0!
0'
b110011101 .
#2105000
1!
1'
b110011110 .
#2110000
0!
0'
b110011111 .
#2115000
1!
1'
b110100000 .
#2120000
0!
0'
b110100001 .
#2125000
1!
1'
b110100010 .
#2130000
0!
0'
b110100011 .
#2135000
1!
1'
b110100100 .
#2140000
0!
0'
b110100101 .
#2145000
1!
1'
b110100110 .
#2150000
0!
0'
b110100111 .
#2155000
1!
1'
b110101000 .
#2160000
0!
0'
b110101001 .
#2165000
1!
1'
b110101010 .
#2170000
0!
0'
b110101011 .
#2175000
1!
1'
b110101100 .
#2180000
0!
0'
b110101101 .
#2185000
1!
1'
b110101110 .
#2190000
0!
0'
b110101111 .
#2195000
1!
1'
b110110000 .
#2200000
0!
0'
b110110001 .
#2205000
1!
1'
b110110010 .
#2210000
0!
0'
b110110011 .
#2215000
1!
1'
b110110100 .
#2220000
0!
0'
b110110101 .
#2225000
1!
1'
b110110110 .
#2230000
0!
0'
b110110111 .
#2235000
1!
1'
b110111000 .
#2240000
0!
0'
b110111001 .
#2245000
1!
1'
b110111010 .
#2250000
0!
0'
b110111011 .
#2255000
1!
1'
b110111100 .
#2260000
0!
0'
b110111101 .
#2265000
1!
1'
b110111110 .
#2270000
0!
0'
b110111111 .
#2275000
1!
1'
b111000000 .
#2280000
0!
0'
b111000001 .
#2285000
1!
1'
b111000010 .
#2290000
0!
0'
b111000011 .
#2295000
1!
1'
b111000100 .
#2300000
0!
0'
b111000101 .
#2305000
1!
1'
b111000110 .
#2310000
0!
0'
b111000111 .
#2315000
1!
1'
b111001000 .
#2320000
0!
0'
b111001001 .
#2325000
1!
1'
b111001010 .
#2330000
0!
0'
b111001011 .
#2335000
1!
1'
b111001100 .
#2340000
0!
0'
b111001101 .
#2345000
1!
1'
b111001110 .
#2350000
0!
0'
b111001111 .
#2355000
1!
1'
b111010000 .
#2360000
0!
0'
b111010001 .
#2365000
1!
1'
b111010010 .
#2370000
0!
0'
b111010011 .
#2375000
1!
1'
b111010100 .
#2380000
0!
0'
b111010101 .
#2385000
1!
1'
b111010110 .
#2390000
0!
0'
b111010111 .
#2395000
1!
1'
b111011000 .
#2400000
0!
0'
b111011001 .
#2405000
1!
1'
b111011010 .
#2410000
0!
0'
b111011011 .
#2415000
1!
1'
b111011100 .
#2420000
0!
0'
b111011101 .
#2425000
1!
1'
b111011110 .
#2430000
0!
0'
b111011111 .
#2435000
1!
1'
b111100000 .
#2440000
0!
0'
b111100001 .
#2445000
1!
1'
b111100010 .
#2450000
0!
0'
b111100011 .
#2455000
1!
1'
b111100100 .
#2460000
0!
0'
b111100101 .
#2465000
1!
1'
b111100110 .
#2470000
0!
0'
b111100111 .
#2475000
1!
1'
b111101000 .
#2480000
0!
0'
b111101001 .
#2485000
1!
1'
b111101010 .
#2490000
0!
0'
b111101011 .
#2495000
1!
1'
b111101100 .
#2500000
0!
0'
b111101101 .
#2505000
1!
1'
b111101110 .
#2510000
0!
0'
b111101111 .
#2515000
1!
1'
b111110000 .
#2520000
0!
0'
b111110001 .
#2525000
1!
1'
b111110010 .
#2530000
0!
0'
b111110011 .
#2535000
1!
1'
b111110100 .
#2540000
0!
0'
b111110101 .
#2545000
1!
1'
b111110110 .
#2550000
0!
0'
b111110111 .
#2555000
1!
1'
b111111000 .
#2560000
0!
0'
b111111001 .
#2565000
1!
1'
b111111010 .
#2570000
0!
0'
b111111011 .
#2575000
1!
1'
b111111100 .
#2580000
0!
0'
b111111101 .
#2585000
1!
1'
b111111110 .
#2590000
0!
0'
b111111111 .
#2595000
1!
1'
b1000000000 .
#2600000
0!
0'
b1000000001 .
#2605000
1!
1'
b1000000010 .
#2610000
0!
0'
b1000000011 .
#2615000
1!
1'
b1000000100 .
#2620000
0!
0'
b1000000101 .
#2625000
1!
1'
b1000000110 .
#2630000
0!
0'
b1000000111 .
#2635000
1!
1'
b1000001000 .
#2640000
0!
0'
b1000001001 .
#2645000
1!
1'
b1000001010 .
#2650000
0!
0'
b1000001011 .
#2655000
1!
1'
b1000001100 .
#2660000
0!
0'
b1000001101 .
#2665000
1!
1'
b1000001110 .
#2670000
0!
0'
b1000001111 .
#2675000
1!
1'
b1000010000 .
#2680000
0!
0'
b1000010001 .
#2685000
1!
1'
b1000010010 .
#2690000
0!
0'
b1000010011 .
#2695000
1!
1'
b1000010100 .
#2700000
0!
0'
b1000010101 .
#2705000
1!
1'
b1000010110 .
#2710000
0!
0'
b1000010111 .
#2715000
1!
1'
b1000011000 .
#2720000
0!
0'
b1000011001 .
#2725000
1!
1'
b1000011010 .
#2730000
0!
0'
b1000011011 .
#2735000
1!
1'
b1000011100 .
#2740000
0!
0'
b1000011101 .
#2745000
1!
1'
b1000011110 .
#2750000
0!
0'
b1000011111 .
#2755000
1!
1'
b1000100000 .
#2760000
0!
0'
b1000100001 .
#2765000
1!
1'
b1000100010 .
#2770000
0!
0'
b1000100011 .
#2775000
1!
1'
b1000100100 .
#2780000
0!
0'
b1000100101 .
#2785000
1!
1'
b1000100110 .
#2790000
0!
0'
b1000100111 .
#2795000
1!
1'
b1000101000 .
#2800000
0!
0'
b1000101001 .
#2805000
1!
1'
b1000101010 .
#2810000
0!
0'
b1000101011 .
#2815000
1!
1'
b1000101100 .
#2820000
0!
0'
b1000101101 .
#2825000
1!
1'
b1000101110 .
#2830000
0!
0'
b1000101111 .
#2835000
1!
1'
b1000110000 .
#2840000
0!
0'
b1000110001 .
#2845000
1!
1'
b1000110010 .
#2850000
0!
0'
b1000110011 .
#2855000
1!
1'
b1000110100 .
#2860000
0!
0'
b1000110101 .
#2865000
1!
1'
b1000110110 .
#2870000
0!
0'
b1000110111 .
#2875000
1!
1'
b1000111000 .
#2880000
0!
0'
b1000111001 .
#2885000
1!
1'
b1000111010 .
#2890000
0!
0'
b1000111011 .
#2895000
1!
1'
b1000111100 .
#2900000
0!
0'
b1000111101 .
#2905000
1!
1'
b1000111110 .
#2910000
0!
0'
b1000111111 .
#2915000
1!
1'
b1001000000 .
#2920000
0!
0'
b1001000001 .
#2925000
1!
1'
b1001000010 .
#2930000
0!
0'
b1001000011 .
#2935000
1!
1'
b1001000100 .
#2940000
0!
0'
b1001000101 .
#2945000
1!
1'
b1001000110 .
#2950000
0!
0'
b1001000111 .
#2955000
1!
1'
b1001001000 .
#2960000
0!
0'
b1001001001 .
#2965000
1!
1'
b1001001010 .
#2970000
0!
0'
b1001001011 .
#2975000
1!
1'
b1001001100 .
#2980000
0!
0'
b1001001101 .
#2985000
1!
1'
b1001001110 .
#2990000
0!
0'
b1001001111 .
#2995000
1!
1'
b1001010000 .
#3000000
0!
0'
b1001010001 .
#3005000
1!
1'
b1001010010 .
#3010000
0!
0'
b1001010011 .
#3015000
1!
1'
b1001010100 .
#3020000
0!
0'
b1001010101 .
#3025000
1!
1'
b1001010110 .
#3030000
0!
0'
b1001010111 .
#3035000
1!
1'
b1001011000 .
#3040000
0!
0'
b1001011001 .
#3045000
1!
1'
b1001011010 .
#3050000
0!
0'
b1001011011 .
#3055000
1!
1'
b1001011100 .
#3060000
0!
0'
b1001011101 .
#3065000
1!
1'
b1001011110 .
#3070000
0!
0'
b1001011111 .
#3075000
1!
1'
b1001100000 .
#3080000
0!
0'
b1001100001 .
#3085000
1!
1'
b1001100010 .
#3090000
0!
0'
b1001100011 .
#3095000
1!
1'
b1001100100 .
#3100000
0!
0'
b1001100101 .
#3105000
1!
1'
b1001100110 .
#3110000
0!
0'
b1001100111 .
#3115000
1!
1'
b1001101000 .
#3120000
0!
0'
b1001101001 .
#3125000
1!
1'
b1001101010 .
#3130000
0!
0'
b1001101011 .
#3135000
1!
1'
b1001101100 .
#3140000
0!
0'
b1001101101 .
#3145000
1!
1'
b1001101110 .
#3150000
0!
0'
b1001101111 .
#3155000
1!
1'
b1001110000 .
#3160000
0!
0'
b1001110001 .
#3165000
1!
1'
b1001110010 .
#3170000
0!
0'
b1001110011 .
#3175000
1!
1'
b1001110100 .
#3180000
0!
0'
b1001110101 .
#3185000
1!
1'
b1001110110 .
#3190000
0!
0'
b1001110111 .
#3195000
1!
1'
b1001111000 .
#3200000
0!
0'
b1001111001 .
#3205000
1!
1'
b1001111010 .
#3210000
0!
0'
b1001111011 .
#3215000
1!
1'
b1001111100 .
#3220000
0!
0'
b1001111101 .
#3225000
1!
1'
b1001111110 .
#3230000
0!
0'
b1001111111 .
#3235000
1!
1'
b1010000000 .
#3240000
0!
0'
b1010000001 .
#3245000
1!
1'
b1010000010 .
#3250000
0!
0'
b1010000011 .
#3255000
1!
1'
b1010000100 .
#3260000
0!
0'
b1010000101 .
#3265000
1!
1'
b1010000110 .
#3270000
0!
0'
b1010000111 .
#3275000
1!
1'
b1010001000 .
#3280000
0!
0'
b1010001001 .
#3285000
1!
1'
b1010001010 .
#3290000
0!
0'
b1010001011 .
#3295000
1!
1'
b1010001100 .
#3300000
0!
0'
b1010001101 .
#3305000
1!
1'
b1010001110 .
#3310000
0!
0'
b1010001111 .
#3315000
1!
1'
b1010010000 .
#3320000
0!
0'
b1010010001 .
#3325000
1!
1'
b1010010010 .
#3330000
0!
0'
b1010010011 .
#3335000
1!
1'
b1010010100 .
#3340000
0!
0'
b1010010101 .
#3345000
1!
1'
b1010010110 .
#3350000
0!
0'
b1010010111 .
#3355000
1!
1'
b1010011000 .
#3360000
0!
0'
b1010011001 .
#3365000
1!
1'
b1010011010 .
#3370000
0!
0'
b1010011011 .
#3375000
1!
1'
b1010011100 .
#3380000
0!
0'
b1010011101 .
#3385000
1!
1'
b1010011110 .
#3390000
0!
0'
b1010011111 .
#3395000
1!
1'
b1010100000 .
#3400000
0!
0'
b1010100001 .
#3405000
1!
1'
b1010100010 .
#3410000
0!
0'
b1010100011 .
#3415000
1!
1'
b1010100100 .
#3420000
0!
0'
b1010100101 .
#3425000
1!
1'
b1010100110 .
#3430000
0!
0'
b1010100111 .
#3435000
1!
1'
b1010101000 .
#3440000
0!
0'
b1010101001 .
#3445000
1!
1'
b1010101010 .
#3450000
0!
0'
b1010101011 .
#3455000
1!
1'
b1010101100 .
#3460000
0!
0'
b1010101101 .
#3465000
1!
1'
b1010101110 .
#3470000
0!
0'
b1010101111 .
#3475000
1!
1'
b1010110000 .
#3480000
0!
0'
b1010110001 .
#3485000
1!
1'
b1010110010 .
#3490000
0!
0'
b1010110011 .
#3495000
1!
1'
b1010110100 .
#3500000
0!
0'
b1010110101 .
#3505000
1!
1'
b1010110110 .
#3510000
0!
0'
b1010110111 .
#3515000
1!
1'
b1010111000 .
#3520000
0!
0'
b1010111001 .
#3525000
1!
1'
b1010111010 .
#3530000
0!
0'
b1010111011 .
#3535000
1!
1'
b1010111100 .
#3540000
0!
0'
b1010111101 .
#3545000
1!
1'
b1010111110 .
#3550000
0!
0'
b1010111111 .
#3555000
1!
1'
b1011000000 .
#3560000
0!
0'
b1011000001 .
#3565000
1!
1'
b1011000010 .
#3570000
0!
0'
b1011000011 .
#3575000
1!
1'
b1011000100 .
#3580000
0!
0'
b1011000101 .
#3585000
1!
1'
b1011000110 .
#3590000
0!
0'
b1011000111 .
#3595000
1!
1'
b1011001000 .
#3600000
0!
0'
b1011001001 .
#3605000
1!
1'
b1011001010 .
#3610000
0!
0'
b1011001011 .
#3615000
1!
1'
b1011001100 .
#3620000
0!
0'
b1011001101 .
#3625000
1!
1'
b1011001110 .
#3630000
0!
0'
b1011001111 .
#3635000
1!
1'
b1011010000 .
