.Xil/Vivado-21936-DESKTOP-M3QN9GM/realtime/div_gen_0_stub.v
// Copyright 1986-2022 Xilinx, Inc. All Rights Reserved.
// Copyright 2022-2023 Advanced Micro Devices, Inc. All Rights Reserved.

// This empty module with port declaration file causes synthesis tools to infer a black box for IP.
// Please paste the declaration into a Verilog source file or add the file as an additional source.
(* x_core_info = "div_gen_v5_1_19,Vivado 2023.1" *)
module div_gen_0(aclk, s_axis_divisor_tvalid, 
  s_axis_divisor_tdata, s_axis_dividend_tvalid, s_axis_dividend_tdata, 
  m_axis_dout_tvalid, m_axis_dout_tdata);
  input aclk /* synthesis syn_isclock = 1 */;
  input s_axis_divisor_tvalid;
  input [31:0]s_axis_divisor_tdata;
  input s_axis_dividend_tvalid;
  input [31:0]s_axis_dividend_tdata;
  output m_axis_dout_tvalid;
  output [63:0]m_axis_dout_tdata;
endmodule

sim/div_tb.sv
`timescale 1ns / 1ps
`default_nettype none

module div_tb();

  logic clk_in;
  logic rst_in;
  logic signed [31:0] fft_data_reg_1; // used by the external master to signal that it is able to provide data (critical in pipelining)
  logic signed [31:0] change_1; // asserted by the external master on the last sample of the frame (can be used to regulate flow of data)
  logic signed [61:0] sig_1; // used by the external master to signal that it is able to provide data (critical in pipelining)  
  logic signed [31:0] out_actual;
  logic val;
  div_gen_0 testing_div(
    .aclk(clk_in),
    .s_axis_divisor_tvalid(1),
    .s_axis_divisor_tdata(fft_data_reg_1),
    .s_axis_dividend_tdata(change_1),
    .m_axis_dout_tvalid(val),
    .m_axis_dout_tdata(sig_1));

  always begin // 100 MHz clock
      #5; 
      clk_in = !clk_in;
      out_actual = sig_1[61:32];
  end

  initial begin
    $dumpfile("div_tb.vcd"); 
    $dumpvars(0,div_tb);
    $display("Starting Sim");
    clk_in = 0;
    rst_in = 0;
    out_actual = 0;
    #10;
    // Reset all variables
    rst_in = 1;
    #5;
    
    #10;
    // Begin Test
    #10;
    rst_in = 0; 
    
    
    for (int i = 0; i<10000; i=i+1)begin // Begin FFT Analysis
     #5; // Check clock cycling
     change_1 = 32'b1111_1111_1111_1111;
     fft_data_reg_1 = 32'b0000_0000_1001;
    end
    for (int i = 0; i<10000; i=i+1)begin // Begin FFT Analysis
      change_1 = 32'd9;
      fft_data_reg_1 = 32'd3;
      #5; // Check clock cycling
    end
    for (int i = 0; i<10000; i=i+1)begin // Begin FFT Analysis
      change_1 = 32'd1 * 32'd100;
      fft_data_reg_1 = 32'd5;
      #5; // Check clock cycling
    end

    $display("Simulation finished");
    $finish;
  end
endmodule
`default_nettype wire

ip_3_tb/ip_3_tb.sim/sim_1/behav/xsim/div_tb.vcd
$date
   Tue Dec 12 12:59:19 2023
$end
$version
  2023.1
$end
$timescale
  1ps
$end
$scope module div_tb $end
$var reg 1 ! clk_in $end
$var reg 1 " rst_in $end
$var reg 32 # fft_data_reg_1 [31:0] $end
$var reg 32 $ change_1 [31:0] $end
$var reg 62 % sig_1 [61:0] $end
$var reg 32 & out_actual [31:0] $end
$var reg 1 ' val $end
$scope module testing_div $end
$var wire 1 ( aclk $end
$var wire 1 ) s_axis_divisor_tvalid $end
$var wire 32 * s_axis_divisor_tdata $end
$var wire 1 + s_axis_dividend_tvalid $end
$var wire 32 , s_axis_dividend_tdata $end
$var wire 1 - m_axis_dout_tvalid $end
$var wire 64 . m_axis_dout_tdata $end
$upscope $end
$scope begin Block45_2 $end
$var reg 32 / i [31:0] $end
$upscope $end
$scope begin Block50_3 $end
$var reg 32 0 i [31:0] $end
$upscope $end
$scope begin Block55_4 $end
$var reg 32 1 i [31:0] $end
$upscope $end
$upscope $end
$enddefinitions $end
#0
$dumpvars
0!
0"
bx #
bx $
b0 %
b0 &
0'
0(
1)
bx *
x+
bx ,
0-
b0 .
b0 /
b0 0
b0 1
$end
#5000
1!
1(
#10000
0!
1"
0(
#15000
1!
1(
#20000
0!
0(
#25000
1!
1(
#30000
0!
0(
#35000
1!
0"
1(
#40000
0!
b1001 #
b1111111111111111 $
0(
b1001 *
b1111111111111111 ,
b1 /
#45000
1!
1(
b10 /
#50000
0!
0(
b11 /
#55000
1!
1(
b100 /
#60000
0!
0(
b101 /
#65000
1!
1(
b110 /
#70000
0!
0(
b111 /
#75000
1!
1(
b1000 /
#80000
0!
0(
b1001 /
#85000
1!
1(
b1010 /
#90000
0!
0(
b1011 /
#95000
1!
1(
b1100 /
#100000
0!
0(
b1101 /
#105000
1!
1(
b1110 /
#110000
0!
0(
b1111 /
#115000
1!
1(
b10000 /
#120000
0!
0(
b10001 /
#125000
1!
1(
b10010 /
#130000
0!
0(
b10011 /
#135000
1!
1(
b10100 /
#140000
0!
0(
b10101 /
#145000
1!
1(
b10110 /
#150000
0!
0(
b10111 /
#155000
1!
1(
b11000 /
#160000
0!
0(
b11001 /
#165000
1!
1(
b11010 /
#170000
0!
0(
b11011 /
#175000
1!
1(
b11100 /
#180000
0!
0(
b11101 /
#185000
1!
1(
b11110 /
#190000
0!
0(
b11111 /
#195000
1!
1(
b100000 /
#200000
0!
0(
b100001 /
#205000
1!
1(
b100010 /
#210000
0!
0(
b100011 /
#215000
1!
1(
b100100 /
#220000
0!
0(
b100101 /
#225000
1!
1(
b100110 /
#230000
0!
0(
b100111 /
#235000
1!
1(
b101000 /
#240000
0!
0(
b101001 /
#245000
1!
1(
b101010 /
#250000
0!
0(
b101011 /
#255000
1!
1(
b101100 /
#260000
0!
0(
b101101 /
#265000
1!
1(
b101110 /
#270000
0!
0(
b101111 /
#275000
1!
1(
b110000 /
#280000
0!
0(
b110001 /
#285000
1!
1(
b110010 /
#290000
0!
0(
b110011 /
#295000
1!
1(
b110100 /
#300000
0!
0(
b110101 /
#305000
1!
1(
b110110 /
#310000
0!
0(
b110111 /
#315000
1!
1(
b111000 /
#320000
0!
0(
b111001 /
#325000
1!
1(
b111010 /
#330000
0!
0(
b111011 /
#335000
1!
1(
b111100 /
#340000
0!
0(
b111101 /
#345000
1!
1(
b111110 /
#350000
0!
0(
b111111 /
#355000
1!
1(
b1000000 /
#360000
0!
0(
b1000001 /
#365000
1!
1(
b1000010 /
#370000
0!
0(
b1000011 /
#375000
1!
1(
b1000100 /
#380000
0!
0(
b1000101 /
#385000
1!
1(
b1000110 /
#390000
0!
0(
b1000111 /
#395000
1!
1(
b1001000 /
#400000
0!
0(
b1001001 /
#405000
1!
1(
b1001010 /
#410000
0!
0(
b1001011 /
#415000
1!
1(
b1001100 /
#420000
0!
0(
b1001101 /
#425000
1!
1(
b1001110 /
#430000
0!
0(
b1001111 /
#435000
1!
1(
b1010000 /
#440000
0!
0(
b1010001 /
#445000
1!
1(
b1010010 /
#450000
0!
0(
b1010011 /
#455000
1!
1(
b1010100 /
#460000
0!
0(
b1010101 /
#465000
1!
1(
b1010110 /
#470000
0!
0(
b1010111 /
#475000
1!
1(
b1011000 /
#480000
0!
0(
b1011001 /
#485000
1!
1(
b1011010 /
#490000
0!
0(
b1011011 /
#495000
1!
1(
b1011100 /
#500000
0!
0(
b1011101 /
#505000
1!
1(
b1011110 /
#510000
0!
0(
b1011111 /
#515000
1!
1(
b1100000 /
#520000
0!
0(
b1100001 /
#525000
1!
1(
b1100010 /
#530000
0!
0(
b1100011 /
#535000
1!
1(
b1100100 /
#540000
0!
0(
b1100101 /
#545000
1!
1(
b1100110 /
#550000
0!
0(
b1100111 /
#555000
1!
1(
b1101000 /
#560000
0!
0(
b1101001 /
#565000
1!
1(
b1101010 /
#570000
0!
0(
b1101011 /
#575000
1!
1(
b1101100 /
#580000
0!
0(
b1101101 /
#585000
1!
1(
b1101110 /
#590000
0!
0(
b1101111 /
#595000
1!
1(
b1110000 /
#600000
0!
0(
b1110001 /
#605000
1!
1(
b1110010 /
#610000
0!
0(
b1110011 /
#615000
1!
1(
b1110100 /
#620000
0!
0(
b1110101 /
#625000
1!
1(
b1110110 /
#630000
0!
0(
b1110111 /
#635000
1!
1(
b1111000 /
#640000
0!
0(
b1111001 /
#645000
1!
1(
b1111010 /
#650000
0!
0(
b1111011 /
#655000
1!
1(
b1111100 /
#660000
0!
0(
b1111101 /
#665000
1!
1(
b1111110 /
#670000
0!
0(
b1111111 /
#675000
1!
bx %
1(
bx .
b10000000 /
#680000
0!
b0xxxxxxxxxxxxxxxxxxxxxxxxxxxxxx &
0(
b10000001 /
#685000
1!
1(
b10000010 /
#690000
0!
0(
b10000011 /
#695000
1!
1(
b10000100 /
#700000
0!
0(
b10000101 /
#705000
1!
1(
b10000110 /
#710000
0!
0(
b10000111 /
#715000
1!
b111000111000101010101010101010101010101010101 %
1(
b111000111000101010101010101010101010101010101 .
b10001000 /
#720000
0!
b1110001110001 &
0(
b10001001 /
#725000
1!
1(
b10001010 /
#730000
0!
0(
b10001011 /
#735000
1!
1(
b10001100 /
#740000
0!
0(
b10001101 /
#745000
1!
1(
b10001110 /
#750000
0!
0(
b10001111 /
#755000
1!
1(
b10010000 /
#760000
0!
0(
b10010001 /
#765000
1!
1(
b10010010 /
#770000
0!
0(
b10010011 /
#775000
1!
1(
b10010100 /
#780000
0!
0(
b10010101 /
#785000
1!
1(
b10010110 /
#790000
0!
0(
b10010111 /
#795000
1!
1(
b10011000 /
#800000
0!
0(
b10011001 /
#805000
1!
1(
b10011010 /
#810000
0!
0(
b10011011 /
#815000
1!
1(
b10011100 /
#820000
0!
0(
b10011101 /
#825000
1!
1(
b10011110 /
#830000
0!
0(
b10011111 /
#835000
1!
1(
b10100000 /
#840000
0!
0(
b10100001 /
#845000
1!
1(
b10100010 /
#850000
0!
0(
b10100011 /
#855000
1!
1(
b10100100 /
#860000
0!
0(
b10100101 /
#865000
1!
1(
b10100110 /
#870000
0!
0(
b10100111 /
#875000
1!
1(
b10101000 /
#880000
0!
0(
b10101001 /
#885000
1!
1(
b10101010 /
#890000
0!
0(
b10101011 /
#895000
1!
1(
b10101100 /
#900000
0!
0(
b10101101 /
#905000
1!
1(
b10101110 /
#910000
0!
0(
b10101111 /
#915000
1!
1(
b10110000 /
#920000
0!
0(
b10110001 /
#925000
1!
1(
b10110010 /
#930000
0!
0(
b10110011 /
#935000
1!
1(
b10110100 /
#940000
0!
0(
b10110101 /
#945000
1!
1(
b10110110 /
#950000
0!
0(
b10110111 /
#955000
1!
1(
b10111000 /
#960000
0!
0(
b10111001 /
#965000
1!
1(
b10111010 /
#970000
0!
0(
b10111011 /
#975000
1!
1(
b10111100 /
#980000
0!
0(
b10111101 /
#985000
1!
1(
b10111110 /
#990000
0!
0(
b10111111 /
#995000
1!
1(
b11000000 /
#1000000
0!
0(
b11000001 /
